[
    {
        "title": "遭「化骨水」噴濺 竹南鼎元光電女移工",
        "date": "2019/08/30",
        "content": " 發現一個魔酸的影片   https://www.bilibili.com/video/av51556457/  有人實驗把湯匙跟手放進去  結果為啥手沒事  有人知道原因嗎   ※ 引述《sky936122 (科科)》之銘言： : 1.媒體來源:ETtoday新聞雲 : 2.記者署名: 記者黃孟珍／苗栗報導 : 3.完整新聞標題: : 遭「化骨水」噴濺　竹南鼎元光電女移工「雙腿嚴重腐蝕」慘死！ : 4.完整新聞內文: : 苗栗縣竹南科園區內的鼎元光電科技公司，28日上午9時許驚傳工安意外，1名菲律賓籍女 : 移工（29歲），被俗稱「化骨水」的氫氟酸藥水打翻噴濺下肢，導致雙腿大面積嚴重腐蝕 : ，經轉送台北榮總毒物科急救，仍於28日晚間10時宣告不治。 : 鼎元光電發言人表示，這名菲律賓籍的女移工，因為在工作時，所接觸的腐蝕性液體晃動 : ，女移工轉身去承接不慎，才造成裡面的氫氟酸藥水打翻，噴濺到身上；廠內員工見狀立 : 刻前去幫忙，並立刻通報消防隊，無奈還是回天乏術。 : 苗栗縣消防局也表示，氫氟酸是1種強酸且有毒，科技廠用蝕刻電路板，又稱化骨水；用 : 以清洗劑等用途；當噴濺皮膚，廠商需自備六氟靈或敵氟靈中和清洗劑及葡萄糖酸鈣藥膏 : 塗抹（會吃人體鈣）這些藥劑尚需備置與地方急診室醫護配合，另有毒會是氟離子會與血 : 液鈣，鎂，鉀離子結合導致器官懷死。 : 苗栗縣消防局第二大隊長曹春風表示，這種工安意外可算是一種化學災害；救護人員抵達 : 現場時，傷者意識還算清楚，但因疼痛表情相當痛苦；而廠方第1時間內並沒有用六氟靈 : 或敵氟靈沖洗，因此造成嚴重的結果。 : 據了解，這名女移工原定9月就要回到菲律賓，怎料卻在即將返家之際卻命喪台灣；而目 : 前公司方面也在開會檢討後續相關問題，至於詳細的發生原因，還待警方釐清之中。 : 比王水還致命的氫氟酸，無色無味，其所釋出的氟離子腐蝕力很強，會直接穿透組織，對 : 人體具有高度腐蝕性，連骨頭都可以被溶解，因此又稱為化骨水、蝕骨水、白骨酸，很多 : 電影情節都會把化骨水做為滅屍手段，可以殺人於無形。 : 5.完整新聞連結 (或短網址): : https://s.yam.com/ZPMfe : 6.備註: : ※ 一個人一天只能張貼一則新聞，被刪或自刪也算額度內，超貼者水桶，請注意   ----- Sent from JPTT on my InFocus Amazing A8.  ",
        "comment": [
            {
                "push": "推 ",
                "text": ": 他有說是放他的手嗎"
            },
            {
                "push": "推 ",
                "text": ": 因為那只是溫水而已 秘訣在湯匙上"
            },
            {
                "push": "推 ",
                "text": ": 你把手用鐵氟龍包起來就能伸進去了"
            },
            {
                "push": "→ ",
                "text": ": 覺得影片應該有造假"
            },
            {
                "push": "→ ",
                "text": ": https://youtu.be/cvRcUeWjBu0"
            },
            {
                "push": "→ ",
                "text": ": 這段都是直接剪別的的了"
            },
            {
                "push": "推 ",
                "text": ": 沒水分"
            },
            {
                "push": "推 ",
                "text": ": 湯匙融化是因為那是Ga金屬熔點超低"
            },
            {
                "push": "推 ",
                "text": ": 感覺是假的正常來說鐵屬不太可能溶這"
            },
            {
                "push": "→ ",
                "text": ": 麼快"
            },
            {
                "push": "噓 ",
                "text": ": 支那造假又不是一天兩天的事情了"
            }
        ]
    },
    {
        "title": "遭「化骨水」噴濺 竹南鼎元光電女移工",
        "date": "2019/08/30",
        "content": "※ 引述《newnewcow (紐牛)》之銘言： : 這我才剛考完 : 被含氟的酸鹼類潑到 一分鐘之內就要用六氟靈 : 越晚用 效果越差 : 沒有含氟的酸鹼潑到才用敵腐靈 : 如果沒有這些 也要馬上用清水沖洗好幾十分鐘 : 不過六氟靈真的很貴 然後保存期限也才幾年 : 但是工廠省這個錢真的很要不得 : ----- : Sent from JPTT on my iPhone     案例後續  單位主管大過兩支；不調職，或由代理人頂上但原主管留原單位（因為薪水不高又有危險 性請不到人）  廠內基層主管上危險藥品管制課程兩小時（廠內工安部門的隨便來講一下就好，應付接下 來的政府工安檢查）  勞保理賠可憐的外勞，200萬解決，一條外勞爛命而已，200萬對你們來說很多了捏，反正 外勞家人敢來台吵？語言不通你怎麼吵得贏我？台灣哇A角頭ㄟ，我們就在台灣打官司拖 阿看誰命長  然後廠長震怒下令底下寫個改善報告  報告： 以後會對作業者宣導危險藥劑不能怎樣啦blablabla... 被潑灑到要立即以六氟靈處置即時送醫啦   呵呵   但實際上這種這麼貴的藥劑保存期限又短，老闆才不會買咧，台灣老闆為了接單買機台多 貴都會去借錢買，這種急救的藥品你們員工自己小心一點就好了啦，反正死的是外勞，台 灣人遇到這種危險工作也都馬喜歡丟給外勞去做，出了事才裝懊惱  外勞菲律賓的還算好的，英文聽說讀寫流利  可惜台灣人大部分都無法用英文溝通，無法跟外勞解說這些溶劑的危險性，和怎麼處置  可憐的外勞，多花10萬塊就能去英語系國家了，偏偏愛選離家近的哈哈  ",
        "comment": [
            {
                "push": "推 ",
                "text": ": 被仲介騙的"
            },
            {
                "push": "推 ",
                "text": ": 其實是我練化骨綿掌誤傷的"
            },
            {
                "push": "→ ",
                "text": ": 拜託不要據報我QQ"
            },
            {
                "push": "推 ",
                "text": ": 跟單挫林一樣 要準備都沒有"
            },
            {
                "push": "噓 ",
                "text": ": 別國外勞有總量管制啊！台灣的話......."
            },
            {
                "push": "推 ",
                "text": ": 部分外勞是取自己方便，明明就有告知危險性"
            },
            {
                "push": "→ ",
                "text": ": ……"
            },
            {
                "push": "推 ",
                "text": ": 觀念正確喔"
            },
            {
                "push": "推 ",
                "text": ": 工安，你以為廠長會沒事，先跑法院"
            },
            {
                "push": "推 ",
                "text": ": 政府資方掛鉤爽爽賺死幾個外勞沒差"
            },
            {
                "push": "推 ",
                "text": ": 台灣工安就是準備*一堆*表格，備查。"
            },
            {
                "push": "→ ",
                "text": ": 很佩服出事後，能夠馬上生出一堆接談紀錄"
            },
            {
                "push": "→ ",
                "text": ": ，教育訓練紀錄..."
            },
            {
                "push": "→ ",
                "text": ": 廠長正在努力生出各種紀錄中"
            },
            {
                "push": "推 ",
                "text": ": 滿滿台灣價值"
            },
            {
                "push": "推 ",
                "text": ": 專業"
            },
            {
                "push": "推 ",
                "text": ": 幸福城市你敢嘴？"
            },
            {
                "push": "推 ",
                "text": ": 很棒 這很台灣"
            },
            {
                "push": "推 ",
                "text": ": 路過"
            },
            {
                "push": "推 ",
                "text": ": 人員身故意外不勒令停業幾天 老闆才"
            },
            {
                "push": "→ ",
                "text": ": 不會怕 這很台灣價值"
            },
            {
                "push": "推 ",
                "text": ": 台商的名聲  打聽一下就知道了"
            },
            {
                "push": "推 ",
                "text": ": 這個很台灣資方本色"
            },
            {
                "push": "噓 ",
                "text": ": 垃圾公司"
            },
            {
                "push": "噓 ",
                "text": ": 區區一個移工能帶給公司多少產值VS一個不具"
            },
            {
                "push": "→ ",
                "text": ": 負責認的高層能為公司帶來多少前瞻性。"
            },
            {
                "push": "→ ",
                "text": ": R.I.P...."
            },
            {
                "push": "推 ",
                "text": ": 推"
            },
            {
                "push": "噓 ",
                "text": ": 別國對低階外勞也沒比較好啦  想去日"
            },
            {
                "push": "→ ",
                "text": ": 本清輻射？"
            },
            {
                "push": "推 ",
                "text": ": QQ"
            },
            {
                "push": "推 ",
                "text": ": 六氟靈保存期限沒有很短啊 就算過期一點"
            },
            {
                "push": "→ ",
                "text": ": 總比沒噴好"
            },
            {
                "push": "推 ",
                "text": ": 很中華民國的處理方式"
            },
            {
                "push": "推 ",
                "text": ": 哪天被外國以爛勞權為由車過，真的不要太"
            },
            {
                "push": "→ ",
                "text": ": 意外，粒屎共YA"
            },
            {
                "push": "推 ",
                "text": ": 台灣的勞動環境真的可悲"
            },
            {
                "push": "→ ",
                "text": ": 六氟靈有到很貴嗎"
            },
            {
                "push": "推 ",
                "text": ": 對老闆沒用 10元都算貴"
            },
            {
                "push": "→ ",
                "text": ": 其實六氟靈沒多少錢啊, 準備個一兩罐還"
            },
            {
                "push": "→ ",
                "text": ": 好吧, 這點錢都不願意花然後花200萬..."
            },
            {
                "push": "推 ",
                "text": ": 這個很鬼島! 我詛咒這些畜生"
            },
            {
                "push": "噓 ",
                "text": ": 很好笑嗎為什麼要哈哈"
            },
            {
                "push": "噓 ",
                "text": ": 可以c這很台灣"
            },
            {
                "push": "噓 ",
                "text": ": 垃圾公司  真的很有台灣價值"
            },
            {
                "push": "推 ",
                "text": ": 偉哉台灣"
            },
            {
                "push": "推 ",
                "text": ": 這就是台灣價值"
            },
            {
                "push": "推 ",
                "text": ": 唉~~~~"
            },
            {
                "push": "→ ",
                "text": ": 500ml 4000元可以放兩年 對老闆來說很貴?!"
            },
            {
                "push": "推 ",
                "text": ": 貴阿，我公司連夾a4紙那個塑膠板的"
            },
            {
                "push": "→ ",
                "text": ": 錢都在省，給我們用瓦楞紙板加鳳尾"
            },
            {
                "push": "→ ",
                "text": ": 夾，第一次看到時超無言"
            },
            {
                "push": "推 ",
                "text": ": 有時候板子上還會有XX椪柑之類的字"
            },
            {
                "push": "→ ",
                "text": ": 樣"
            },
            {
                "push": "噓 ",
                "text": ": 哈哈哈哈哈哈哈噓"
            },
            {
                "push": "推 ",
                "text": ": 鬼島日常"
            },
            {
                "push": "推 ",
                "text": ": 被噴到擦藥也沒救,HF超毒，防護要夠"
            },
            {
                "push": "推 ",
                "text": ": 一堆公司連文具都不買了"
            },
            {
                "push": "推 ",
                "text": ": 台灣價值！"
            },
            {
                "push": "推 ",
                "text": ": 大概是這樣"
            },
            {
                "push": "推 ",
                "text": ":"
            }
        ]
    },
    {
        "title": "遭「化骨水」噴濺 竹南鼎元光電女移工",
        "date": "2019/08/29",
        "content": "唉.....  只能說台灣不論是環保工安都很不上道  以前還待過廠區極有機氣體\"排到\"辦公室的,還是在科學園區中,  之後,我就完全不相信台灣許多老企業老產業是有幾間有真正競爭力,  成本外部化到很會,  就是一間沒競爭力的老公司,上層每個都退休年紀,還是要占者位置,  中階主管整天在會議室,甚至在薪水上動手腳,  一個正常國家的產業轉型汱除都沒看到,只看到老人老文化占住利益,  十年的央行低匯,長期經濟部科專變相等補助在這恐怕是幫了一個大忙   ※ 引述《sky936122 (科科)》之銘言： : 1.媒體來源:ETtoday新聞雲 : 2.記者署名: 記者黃孟珍／苗栗報導 : 3.完整新聞標題: : 遭「化骨水」噴濺　竹南鼎元光電女移工「雙腿嚴重腐蝕」慘死！ : 4.完整新聞內文: : 苗栗縣竹南科園區內的鼎元光電科技公司，28日上午9時許驚傳工安意外，1名菲律賓籍女 : 移工（29歲），被俗稱「化骨水」的氫氟酸藥水打翻噴濺下肢，導致雙腿大面積嚴重腐蝕 : ，經轉送台北榮總毒物科急救，仍於28日晚間10時宣告不治。 : 鼎元光電發言人表示，這名菲律賓籍的女移工，因為在工作時，所接觸的腐蝕性液體晃動 : ，女移工轉身去承接不慎，才造成裡面的氫氟酸藥水打翻，噴濺到身上；廠內員工見狀立 : 刻前去幫忙，並立刻通報消防隊，無奈還是回天乏術。 : 苗栗縣消防局也表示，氫氟酸是1種強酸且有毒，科技廠用蝕刻電路板，又稱化骨水；用 : 以清洗劑等用途；當噴濺皮膚，廠商需自備六氟靈或敵氟靈中和清洗劑及葡萄糖酸鈣藥膏 : 塗抹（會吃人體鈣）這些藥劑尚需備置與地方急診室醫護配合，另有毒會是氟離子會與血 : 液鈣，鎂，鉀離子結合導致器官懷死。 : 苗栗縣消防局第二大隊長曹春風表示，這種工安意外可算是一種化學災害；救護人員抵達 : 現場時，傷者意識還算清楚，但因疼痛表情相當痛苦；而廠方第1時間內並沒有用六氟靈 : 或敵氟靈沖洗，因此造成嚴重的結果。 : 據了解，這名女移工原定9月就要回到菲律賓，怎料卻在即將返家之際卻命喪台灣；而目 : 前公司方面也在開會檢討後續相關問題，至於詳細的發生原因，還待警方釐清之中。 : 比王水還致命的氫氟酸，無色無味，其所釋出的氟離子腐蝕力很強，會直接穿透組織，對 : 人體具有高度腐蝕性，連骨頭都可以被溶解，因此又稱為化骨水、蝕骨水、白骨酸，很多 : 電影情節都會把化骨水做為滅屍手段，可以殺人於無形。 : 5.完整新聞連結 (或短網址): : https://s.yam.com/ZPMfe : 6.備註: : ※ 一個人一天只能張貼一則新聞，被刪或自刪也算額度內，超貼者水桶，請注意  ",
        "comment": [
            {
                "push": "噓 ",
                "text": ": 哈哈哈，中高層像你講的那麼廢，那你為什"
            },
            {
                "push": "→ ",
                "text": ": 麼還被壓在地上磨，而不是出來開一家幹爆他"
            },
            {
                "push": "→ ",
                "text": ": https://i.imgur.com/edhp6XA.jpg"
            },
            {
                "push": "→ ",
                "text": ": 們"
            },
            {
                "push": "噓 ",
                "text": ": 你有比那些老人強嗎"
            },
            {
                "push": "→ ",
                "text": ": 如果你有創業，你就能體會企業生存不易，可"
            },
            {
                "push": "→ ",
                "text": ": 不是靠運氣，適者生存，能活那麼多年就是"
            },
            {
                "push": "→ ",
                "text": ": 有不為人知的本領"
            },
            {
                "push": "推 ",
                "text": ": 幹，看過fab裡從天花板滴液體下來，地上"
            },
            {
                "push": "→ ",
                "text": ": 的金屬擋板都被滴到變色了"
            },
            {
                "push": "→ ",
                "text": ": 某廠還有機台噴液體出來的，操，什麼爛"
            },
            {
                "push": "→ ",
                "text": ": 廠"
            },
            {
                "push": "→ ",
                "text": ": 買一堆2手機台，幹"
            },
            {
                "push": "推 ",
                "text": ": 今晚洗廢文洗超快的"
            },
            {
                "push": "推 ",
                "text": ": 在業界做過的能認同你"
            }
        ]
    },
    {
        "title": "遭「化骨水」噴濺 竹南鼎元光電女移工",
        "date": "2019/08/29",
        "content": "這我才剛考完 被含氟的酸鹼類潑到 一分鐘之內就要用六氟靈 越晚用 效果越差 沒有含氟的酸鹼潑到才用敵腐靈 如果沒有這些 也要馬上用清水沖洗好幾十分鐘 不過六氟靈真的很貴 然後保存期限也才幾年 但是工廠省這個錢真的很要不得 ----- Sent from JPTT on my iPhone  ",
        "comment": [
            {
                "push": "推 ",
                "text": ": 台北榮總才有解藥嗎"
            },
            {
                "push": "→ ",
                "text": ": 看濃度好嗎… 廠區裡的氫氟酸廢水 整個"
            },
            {
                "push": "→ ",
                "text": ": 人跳進去都不會怎樣"
            },
            {
                "push": "推 ",
                "text": ": 很多fab都過期"
            },
            {
                "push": "→ ",
                "text": ": 南部一堆隨便搞搞的主板廠 二樓要不要來跳"
            },
            {
                "push": "推 ",
                "text": ": 真的是 垃圾工廠"
            },
            {
                "push": "→ ",
                "text": ": 看員工就知道了，臉上一堆疤 身上都穿舊衣"
            },
            {
                "push": "→ ",
                "text": ": 因為防護太爛 衣服穿一穿會有洞"
            },
            {
                "push": "→ ",
                "text": ": 所以以後的sop 是有要多一個人陪同背六"
            },
            {
                "push": "→ ",
                "text": ": 氟靈 才來得急 挽救嗎"
            },
            {
                "push": "→ ",
                "text": ": 台鐵都敢那樣混了 等菜英屎跳進去吧"
            },
            {
                "push": "推 ",
                "text": ": 台電環安B類"
            },
            {
                "push": "推 ",
                "text": ": 500ml 4000元可以放兩年 是多貴"
            }
        ]
    },
    {
        "title": "遭「化骨水」噴濺 竹南鼎元光電女移工",
        "date": "2019/08/29",
        "content": "  這個HF  是相當泛用的濕蝕刻液 (不知道蝕刻液在幹嘛的請自行股狗，科普不是本篇重點XD) 不只產界，做相關研究的學校研究室也常常在用  他的沸點19.5度C  也就是說，在台灣夏天的常溫下，他就沸騰啦~  正所謂液體易擋，氣體難防  只要沒在低溫且戴防毒面具下操作，基本上就直接吸嗨   然後呢，當年強者我朋友學長  準備畢業沒事做，嫌論文太單薄，想加點頁數在附錄  突然靈光一閃，想到一般我們常溫下操作，等他蝕刻完畢都要一段時間  那麼，如果給HF加點動力，是不是就不用等那麼久?  於是，就給HF灌注一點點動力，也就是 加 熱  請注意，沸點19.5度C  然而一般使用的HF純度不會到100%，裡面還有一些水  所以，還是可以加熱超過19.5度  該學長，分段加熱，並收集相關反應數據  就看容器內的HF歡騰的冒出泡泡，啵啵啵啵~~  整間實驗室也充滿歡樂的HF  越高溫越歡樂，好嗨森阿~  我記得該學長把HF加熱到75度C的樣子  那段實驗時間沒什麼人敢靠近實驗室  學長也超認真的把自己包成肉粽，  兩年實驗室生涯都沒包的這麼認真過  數據結果確實是大幅縮減反應時間啦  但後來沒人敢再這麼玩過，  不過還是有些不怕死被進度逼急的人有偷偷加個5度10度這樣   現在想起來這個HF加熱實驗  我只想說  幹  神經病!       我知道有人想知道該學長的下場  也有人腹黑的期待有什麼獵奇結局   好吧   結局就是.....   台G顧機台  夠獵奇吧  幫QQ      ※ 引述《wush (wush)》之銘言： : 突然想到「奪魂鋸」第六集 : 在片尾有個很經典的橋段是保險公司老闆被氫氟酸制裁 : https://imgur.com/URVPhlG : 想請教專業人士，像這樣被萬箭齊發注好注滿，最後的下場真的就是上下半身分離嗎？ : : 或敵氟靈沖洗，因此造成嚴重的結果。 : : 據了解，這名女移工原定9月就要回到菲律賓，怎料卻在即將返家之際卻命喪台灣；而目 : : 前公司方面也在開會檢討後續相關問題，至於詳細的發生原因，還待警方釐清之中。 : : 比王水還致命的氫氟酸，無色無味，其所釋出的氟離子腐蝕力很強，會直接穿透組織，對 : : 人體具有高度腐蝕性，連骨頭都可以被溶解，因此又稱為化骨水、蝕骨水、白骨酸，很多 : : 電影情節都會把化骨水做為滅屍手段，可以殺人於無形。 : : 5.完整新聞連結 (或短網址): : : https://s.yam.com/ZPMfe : : 6.備註:  ",
        "comment": [
            {
                "push": "→ ",
                "text": ": .........."
            },
            {
                "push": "→ ",
                "text": ": 調硝化甘油也很刺激！"
            },
            {
                "push": "→ ",
                "text": ": 我以為我加熱硫酸夠強了"
            },
            {
                "push": "→ ",
                "text": ": 顧久瞭真的只剩顧機台了 QQ"
            },
            {
                "push": "推 ",
                "text": ": 哈哈哈，顧機台"
            },
            {
                "push": "推 ",
                "text": ": 怕"
            },
            {
                "push": "→ ",
                "text": ": 日韓貿易戰其中一項 高純度蝕刻氣體氫氟酸"
            },
            {
                "push": "→ ",
                "text": ": 一般都不是用100% 所以會微微加熱是真"
            },
            {
                "push": "→ ",
                "text": ": 的"
            },
            {
                "push": "→ ",
                "text": ": 阿製程中就真的有加熱的.....孤陋寡聞"
            },
            {
                "push": "→ ",
                "text": ": 是說溶於水的一般用蒸氣壓？沸點好像"
            },
            {
                "push": "→ ",
                "text": ": 怪怪的？"
            },
            {
                "push": "→ ",
                "text": ": 蒸氣分壓嗎XD"
            },
            {
                "push": "→ ",
                "text": ": 這樣說大概87%人不知道吧"
            },
            {
                "push": "推 ",
                "text": ": 他其實是在報復實驗室吧"
            },
            {
                "push": "噓 ",
                "text": ": 不知道你在說什麼 沸點19.5度C的是"
            },
            {
                "push": "→ ",
                "text": ": 氟化氫 是氣體 氟化氫溶於水才叫氫"
            },
            {
                "push": "→ ",
                "text": ": 氟酸 你那間學校畢業的？"
            },
            {
                "push": "推 ",
                "text": ": 氫氟酸跟氟化氫是不同的東西..."
            },
            {
                "push": "推 ",
                "text": ": 完了，被樓上打臉了嗎XDD"
            },
            {
                "push": "推 ",
                "text": ": 吸到HF，HF溶於水變氫氟酸，會怎樣嗎"
            },
            {
                "push": "→ ",
                "text": ": 也許有人水杯、珍奶沒加蓋"
            },
            {
                "push": "→ ",
                "text": ": 氟化氫雖然沸點很低但是溶於水後由"
            },
            {
                "push": "→ ",
                "text": ": 於氫鍵束縛的關係沸點會比水還要高"
            },
            {
                "push": "→ ",
                "text": ": 氫氟酸的毒理機制是極易與人體中的"
            },
            {
                "push": "→ ",
                "text": ": 鈣結合"
            },
            {
                "push": "推 ",
                "text": ": 實驗室還是不要擺飲料，怕"
            },
            {
                "push": "→ ",
                "text": ": 鈣消耗完後細胞會釋出鉀 血鈣降低"
            },
            {
                "push": "→ ",
                "text": ": 血鉀過高都是致命的"
            },
            {
                "push": "→ ",
                "text": ": ru大說的是對的"
            },
            {
                "push": "推 ",
                "text": ": 笑了XD"
            },
            {
                "push": "推 ",
                "text": ": 長知識推（？）"
            },
            {
                "push": "推 ",
                "text": ": 顧機台戳到笑點XD"
            }
        ]
    },
    {
        "title": "遭「化骨水」噴濺 竹南鼎元光電女移工",
        "date": "2019/08/29",
        "content": "※ 引述《execute (很好)》之銘言： : 工作上很常接觸bhf(吃玻璃) : hf恐怖的地方是無色無味 : 皮膚接觸到的當下是不會有感覺與症狀 : 沒有任何症狀下直到hf與骨頭的鈣接觸後 : 患者才會感覺痛 這時就已經沒救 : 所以有hf的地方的sop : 身體被任何液體淋到一律先灑六氟靈沖洗  因為半導體現場也有使用到HF  看整個報導出來像是在換酸時候  剛剛跟同事們討論..  被噴濺到這麼大個面積 （雙腿）  這樣是要多大瓶的六氟靈才能解啊....？  附上六氟靈的沖洗一般說明： https://i.imgur.com/BBDlS6I.jpg  ",
        "comment": [
            {
                "push": "推 ",
                "text": ": 幹 好恐怖"
            },
            {
                "push": "→ ",
                "text": ": 5L裝的不是就說給妳噴灑用?"
            },
            {
                "push": "→ ",
                "text": ": 半導體廠的作業員，都高風險的阿"
            },
            {
                "push": "→ ",
                "text": ": 所以廠方乾脆不沖洗了.就放著打給119.."
            },
            {
                "push": "→ ",
                "text": ": 100ml好像600吧"
            },
            {
                "push": "推 ",
                "text": ": 那個流程有那麼草率嗎 管制毒化物"
            },
            {
                "push": "→ ",
                "text": ": 耶"
            },
            {
                "push": "→ ",
                "text": ": 台灣管制藥品不拿取得阿XD"
            },
            {
                "push": "→ ",
                "text": ": 大不了掏過來"
            },
            {
                "push": "→ ",
                "text": ": 不難"
            },
            {
                "push": "→ ",
                "text": ": 感覺就是當場發現太嚴重了放給她死"
            },
            {
                "push": "→ ",
                "text": ": 台灣有可能"
            },
            {
                "push": "推 ",
                "text": ": 立即下半身截肢應該救得回來"
            },
            {
                "push": "推 ",
                "text": ": 現場哪來的截肢工具"
            },
            {
                "push": "推 ",
                "text": ": 比較好奇的是像這種大面積噴濺 有救回的"
            },
            {
                "push": "→ ",
                "text": ": 案例嗎?"
            },
            {
                "push": "→ ",
                "text": ": 沒有，2%表面積就足以致命"
            },
            {
                "push": "推 ",
                "text": ": 立即截肢？你當是19世紀的野戰醫院嗎？"
            },
            {
                "push": "推 ",
                "text": ": 準備一缸直接整個身體泡進去有救嗎"
            }
        ]
    },
    {
        "title": "遭「化骨水」噴濺 竹南鼎元光電女移工",
        "date": "2019/08/29",
        "content": "突然想到「奪魂鋸」第六集 在片尾有個很經典的橋段是保險公司老闆被氫氟酸制裁 https://imgur.com/URVPhlG  想請教專業人士，像這樣被萬箭齊發注好注滿，最後的下場真的就是上下半身分離嗎？  : 或敵氟靈沖洗，因此造成嚴重的結果。 : 據了解，這名女移工原定9月就要回到菲律賓，怎料卻在即將返家之際卻命喪台灣；而目 : 前公司方面也在開會檢討後續相關問題，至於詳細的發生原因，還待警方釐清之中。 : 比王水還致命的氫氟酸，無色無味，其所釋出的氟離子腐蝕力很強，會直接穿透組織，對 : 人體具有高度腐蝕性，連骨頭都可以被溶解，因此又稱為化骨水、蝕骨水、白骨酸，很多 : 電影情節都會把化骨水做為滅屍手段，可以殺人於無形。 : 5.完整新聞連結 (或短網址): : https://s.yam.com/ZPMfe : 6.備註: : ※ 一個人一天只能張貼一則新聞，被刪或自刪也算額度內，超貼者水桶，請注意  ",
        "comment": [
            {
                "push": "→ ",
                "text": ": 吃骨不吃肉吧？"
            },
            {
                "push": "推 ",
                "text": ": 不會 HF是弱酸"
            },
            {
                "push": "推 ",
                "text": ": 毒在體內鈣離子都被吃掉...低血鈣症，肌"
            },
            {
                "push": "→ ",
                "text": ": 肉無法作用，死亡"
            },
            {
                "push": "推 ",
                "text": ": 目前沒任何酸類可以達到電影那種效果"
            },
            {
                "push": "→ ",
                "text": ": 國中理化有教 另外兩種酸混合才行"
            },
            {
                "push": "→ ",
                "text": ": 囧...真的沒印象國中理化有教過"
            },
            {
                "push": "→ ",
                "text": ": 電視電影說HF是怕人模仿"
            },
            {
                "push": "推 ",
                "text": ": 對肉腐蝕性最強的就硫酸惹"
            },
            {
                "push": "→ ",
                "text": ": 骨頭沒那麼好融"
            },
            {
                "push": "→ ",
                "text": ": 你幾年次 國中理化有教?"
            },
            {
                "push": "推 ",
                "text": ": 那是好幾十年前的國中理化:一笑三元"
            },
            {
                "push": "→ ",
                "text": ": 而且好幾十年前有某大學研究生實際使用過"
            },
            {
                "push": "→ ",
                "text": ": 啊~~~這麼說我就想起來了  一笑三元"
            },
            {
                "push": "→ ",
                "text": ": 很經典的實際案例"
            },
            {
                "push": "推 ",
                "text": ": 清大溶屍案 那個妹子已經出獄囉"
            },
            {
                "push": "推 ",
                "text": ": 吃肉還是食人魚洗液piranha solution"
            },
            {
                "push": "→ ",
                "text": ": 比較好，1雙氧水3硫酸"
            },
            {
                "push": "推 ",
                "text": ": 硫酸 硝酸 鹽酸 HF 全上"
            },
            {
                "push": "推 ",
                "text": ": 這集我記得當時看是翻王水"
            }
        ]
    },
    {
        "title": "遭「化骨水」噴濺 竹南鼎元光電女移工",
        "date": "2019/08/29",
        "content": "※ 引述《sky936122 (科科)》之銘言： : 1.媒體來源:ETtoday新聞雲 : 2.記者署名: 記者黃孟珍／苗栗報導 : 3.完整新聞標題: : 遭「化骨水」噴濺　竹南鼎元光電女移工「雙腿嚴重腐蝕」慘死！  看到這篇推文一堆人罵工安  我是不知道這間工安是怎樣  但我學生時代  在PTT打工版，找到一個板橋的暑期打工  說啥是簡單的鎖螺絲  結果從板橋被載到台北松山某建案  要在15F左右的高度上面鎖螺絲  且為了方便在兩棟建築物中間走動  只鋪了一塊木板就要你走過來走過去  沒有廁所  小便還OK，想大便自己去想辦法  然後爬高當然也沒有安全設備  我就問老師父  阿這樣不是很危險嗎  他就說  我是叫你去鎖螺絲，不是叫你往下跳  自己小心點就不會有事，會出事情還不都是自己不注意，你看我有掉下去嗎   恩  我本來是當天就想走的  但是被載到我不熟的地方  於是忍1天  隔天就不去了  且還是基本時薪勒  當時好像95吧，但給1小時1百(沒勞健保)  還好是當天結的  不然我看會拿不到  因為我以前也有做過其他工地打工  是包過濾水庫的粉的工作  因為老闆兒子一直抽菸  我對菸會過敏  我就說我做不下去了  老闆本來不想給我當天的錢  說啥做不下去、做不完檔期、在他們業界是不給錢的  是他人好才給我的    哈哈  工安  哈哈  別笑年輕人為啥不去工地  這都是我親身經驗  白癡才去做工地  根本就是吃定有些人無法做服務業(有些人面對人群有障礙，這種人還不少)  所以一樣給低薪，但是更辛苦，只差在不用面對人群   當年輕人漸漸看透後  就開始酸年輕人吃不了苦  然後要更多的外勞  ",
        "comment": [
            {
                "push": "推 ",
                "text": ": 所以你這不就是說明是工安問題嗎 = ="
            },
            {
                "push": "→ ",
                "text": ": 台灣都是條例一大堆，執行就再說"
            },
            {
                "push": "推 ",
                "text": ": 基本時薪95他給你100很佛了好嗎=="
            },
            {
                "push": "推 ",
                "text": ": 你被坑了吧 工地給基本時薪"
            },
            {
                "push": "→ ",
                "text": ": 工地都嘛這樣 別人不會出事就你會=="
            },
            {
                "push": "→ ",
                "text": ": 那還不如去外燴端菜 有1000"
            },
            {
                "push": "→ ",
                "text": ": 高空危險作業 沒有完善的安衛設施 我猜勞健"
            },
            {
                "push": "→ ",
                "text": ": 要求太多 師傅奇毛子就不好呀"
            },
            {
                "push": "→ ",
                "text": ": 保都沒有 給基本時薪+5元 真佛"
            },
            {
                "push": "推 ",
                "text": ": 不要以偏概全 我去過的工地也有很守法"
            },
            {
                "push": "→ ",
                "text": ": 的 但真的有少數人會偷喝酒後開怪手"
            },
            {
                "push": "→ ",
                "text": ": 有在辦工安證照班 看很多考營造甲的"
            },
            {
                "push": "→ ",
                "text": ": 你掉下去家人連勞保給付都拿不到 這種根本不"
            },
            {
                "push": "→ ",
                "text": ": 有的很認真 有的就隨便考一直考不過"
            },
            {
                "push": "→ ",
                "text": ": 要做"
            },
            {
                "push": "推 ",
                "text": ": 土師父 沒有工安意識不意外 除非是做科學園"
            },
            {
                "push": "→ ",
                "text": ": 區的才會有點觀念"
            },
            {
                "push": "推 ",
                "text": ": 所以說那些坐辦公室的整天在酸人工安"
            },
            {
                "push": "→ ",
                "text": ": 就莫名其妙  現場顧過工人就知道那些"
            },
            {
                "push": "→ ",
                "text": ": 工人各各都比老闆還不怕事 要勸導開"
            },
            {
                "push": "→ ",
                "text": ": 罰你就祈禱下班不要被蓋布袋"
            },
            {
                "push": "推 ",
                "text": ": 科學園區沒有多安全啦 修機台那個有"
            },
            {
                "push": "→ ",
                "text": ": 斷電掛牌上鎖全做到的? 不守規矩的個"
            },
            {
                "push": "推 ",
                "text": ": 就知道建築業的利潤怎麼來的了吧"
            },
            {
                "push": "→ ",
                "text": ": 性已經從老闆到勞工的每個人身上了"
            },
            {
                "push": "推 ",
                "text": ": 台灣的工安是做工的要自己注意安全"
            },
            {
                "push": "推 ",
                "text": ": 工安問題真的重要"
            },
            {
                "push": "→ ",
                "text": ": 台灣你照規矩萊還會被工人酸怕死、沒"
            },
            {
                "push": "→ ",
                "text": ": 懶覺，台灣很多人性格就不會倒楣到我"
            },
            {
                "push": "推 ",
                "text": ": 哈哈公安"
            },
            {
                "push": "推 ",
                "text": ": 你是不是有說過一樣的故事？"
            },
            {
                "push": "推 ",
                "text": ": 推"
            },
            {
                "push": "推 ",
                "text": ": 連老闆維修自己都會摔死了"
            },
            {
                "push": "→ ",
                "text": ": 我上班的公司前面在蓋鐵皮屋頂，約2層"
            },
            {
                "push": "→ ",
                "text": ": 樓高，工人直接在上面走動蓋屋頂，完全"
            },
            {
                "push": "→ ",
                "text": ": 沒有安全措施"
            },
            {
                "push": "推 ",
                "text": ": 老一輩的不重視工安 甚至自以為勇敢"
            },
            {
                "push": "→ ",
                "text": ": 怎麼你找的打工都這種"
            },
            {
                "push": "→ ",
                "text": ": 你這就日領的粗工阿...真的想跑環境規範"
            },
            {
                "push": "→ ",
                "text": ": 好一點的工程，去找專門跑科學園區的包"
            },
            {
                "push": "→ ",
                "text": ": 商會比外面的好，再次之是國營事業的包"
            },
            {
                "push": "→ ",
                "text": ": 商。"
            },
            {
                "push": "推 ",
                "text": ": 鍵盤手會跟你說工地年收幾百萬超讚"
            },
            {
                "push": "推 ",
                "text": ": 所以你想說什麼?台灣垃圾公司一堆，有在做"
            },
            {
                "push": "→ ",
                "text": ": 工安的公司也有"
            },
            {
                "push": "→ ",
                "text": ": 以前工程根本就沒在重視工安的"
            },
            {
                "push": "推 ",
                "text": ": 時薪95的年代 學生打工工地助手這種應"
            },
            {
                "push": "→ ",
                "text": ": 該是算日結1200～1500…你真的被坑…"
            },
            {
                "push": "推 ",
                "text": ": 推"
            }
        ]
    },
    {
        "title": "遭「化骨水」噴濺 竹南鼎元光電女移工",
        "date": "2019/08/29",
        "content": "HF齁  如果只是噴到四肢  趕快切到可能還有救  如果噴到軀幹  只有死路一條  不過如果要切到變人彘  不如死掉算了   ※ 引述《execute (很好)》之銘言： : 工作上很常接觸bhf(吃玻璃) : hf恐怖的地方是無色無味 : 皮膚接觸到的當下是不會有感覺與症狀 : 沒有任何症狀下直到hf與骨頭的鈣接觸後 : 患者才會感覺痛 這時就已經沒救 : 所以有hf的地方的sop : 身體被任何液體淋到一律先灑六氟靈沖洗  ",
        "comment": [
            {
                "push": "噓 ",
                "text": ": 如果噴到懶叫咧"
            },
            {
                "push": "→ ",
                "text": ": 覽較沒有骨頭 不受影醒"
            },
            {
                "push": "推 ",
                "text": ": 樓上噴看看"
            },
            {
                "push": "推 ",
                "text": ": 2樓懶較一直抽筋怎麼辦？"
            }
        ]
    },
    {
        "title": "遭「化骨水」噴濺 竹南鼎元光電女移工",
        "date": "2019/08/29",
        "content": "大部份死因 不是因為跑到骨頭 而是氫氟酸會滲入皮膚 和血液中的鈣結合 造成血液中鈣鉀離子不平衡 這會怎麼樣呢 也就是會造成肌肉抽筋 為什麼那麼痛 也是因為嚴重抽筋 而當漫延到心臟時 心臟抽筋想當然就沒救惹 而且嚴重持續抽筋 也會橫紋肌溶解症 也會GG 大概4這樣    ※ 引述《execute (很好)》之銘言： : 工作上很常接觸bhf(吃玻璃) : hf恐怖的地方是無色無味 : 皮膚接觸到的當下是不會有感覺與症狀 : 沒有任何症狀下直到hf與骨頭的鈣接觸後 : 患者才會感覺痛 這時就已經沒救 : 所以有hf的地方的sop : 身體被任何液體淋到一律先灑六氟靈沖洗   ",
        "comment": [
            {
                "push": "推 ",
                "text": ": 那狂吞鈣片有救嗎"
            },
            {
                "push": "→ ",
                "text": ": 怕"
            },
            {
                "push": "推 ",
                "text": ": 感覺好專業"
            },
            {
                "push": "推 ",
                "text": ": 好恐怖啊"
            },
            {
                "push": "推 ",
                "text": ": 黑道可以拿來棄屍吧"
            },
            {
                "push": "推 ",
                "text": ": 不行，HF的侵蝕是造成皮膚黑掉骨頭脆掉"
            },
            {
                "push": "→ ",
                "text": ": ，不是像小說寫的倒下去屍體就跟冰塊融"
            },
            {
                "push": "→ ",
                "text": ": 化一樣"
            },
            {
                "push": "→ ",
                "text": ": 用濃硫酸分解屍體都比HF好用"
            },
            {
                "push": "→ ",
                "text": ": 光是腳趾頭抽筋就很痛了 全身抽筋..."
            }
        ]
    },
    {
        "title": "遭「化骨水」噴濺 竹南鼎元光電女移工",
        "date": "2019/08/29",
        "content": "工作上很常接觸bhf(吃玻璃) hf恐怖的地方是無色無味 皮膚接觸到的當下是不會有感覺與症狀 沒有任何症狀下直到hf與骨頭的鈣接觸後 患者才會感覺痛 這時就已經沒救  所以有hf的地方的sop 身體被任何液體淋到一律先灑六氟靈沖洗  ",
        "comment": [
            {
                "push": "推 ",
                "text": ": 化骨系"
            },
            {
                "push": "推 ",
                "text": ": 以前做實驗都戴兩層手套才敢碰HF"
            },
            {
                "push": "推 ",
                "text": ": 這救回來會更慘嗎"
            },
            {
                "push": "推 ",
                "text": ": 沖了可以挽回到什麼程度?"
            },
            {
                "push": "推 ",
                "text": ": 就是讓氫氟酸不再侵蝕人體的鈣"
            },
            {
                "push": "推 ",
                "text": ": 真可怕的東西..."
            },
            {
                "push": "→ ",
                "text": ": 已經被吃掉的沒救的"
            },
            {
                "push": "推 ",
                "text": ": LAB有用到wet etching的自己小心~"
            },
            {
                "push": "推 ",
                "text": ": 餵狗六氟靈貌似是很貴的東西"
            },
            {
                "push": "推 ",
                "text": ": 看情況，可能會跟嚴重的骨質疏鬆症患"
            },
            {
                "push": "→ ",
                "text": ": 者一樣變成玻璃娃娃，肌肉也會相當程"
            },
            {
                "push": "→ ",
                "text": ": 度的損傷，而且是不可逆"
            },
            {
                "push": "→ ",
                "text": ": 幹 越看越恐怖"
            },
            {
                "push": "推 ",
                "text": ": 氫氟酸 這東西超猛的.."
            },
            {
                "push": "推 ",
                "text": ": 這麼毒 不禁用嗎"
            },
            {
                "push": "→ ",
                "text": ": 有沒有東西可以取代氫氟酸? 這東西真的太危險"
            },
            {
                "push": "推 ",
                "text": ": 幹 超怕=="
            },
            {
                "push": "→ ",
                "text": ": 台灣又一堆人不遵守sop或是根本工廠沒在管"
            },
            {
                "push": "推 ",
                "text": ": 樓上，怎麼禁，這東西還是濃度越高越好"
            },
            {
                "push": "→ ",
                "text": ": ，而且沒有替代物(價格上)，台灣還是"
            },
            {
                "push": "→ ",
                "text": ": 亞洲地區一個主要產區"
            },
            {
                "push": "推 ",
                "text": ": 巴拉刈都能禁了 HF不禁嗎"
            },
            {
                "push": "推 ",
                "text": ": 製程上很好用，要替代只會增加成本吧"
            },
            {
                "push": "→ ",
                "text": ": 叫RD研發不用HF的製程"
            },
            {
                "push": "→ ",
                "text": ": 說一個替代品來聽聽"
            },
            {
                "push": "→ ",
                "text": ": 增加成本就會降低企業競爭力"
            },
            {
                "push": "→ ",
                "text": ": 巴拉刈影響產值還不到萬分之一吧"
            },
            {
                "push": "→ ",
                "text": ": 增加那些成本就沒辦法跟別人競爭了嗎?"
            },
            {
                "push": "推 ",
                "text": ": 而且這東西不是廣義上的有毒物質，現在"
            },
            {
                "push": "→ ",
                "text": ": 都說有害物，氫氟酸就不是有毒物質的"
            },
            {
                "push": "→ ",
                "text": ": 其中之一"
            },
            {
                "push": "推 ",
                "text": ": 被化古水潑到 馬上撒六氟靈 也沒救嗎?"
            },
            {
                "push": "推 ",
                "text": ": 這是工安沒做好，什麼都要禁也太誇張了"
            },
            {
                "push": "→ ",
                "text": ": 問題是有感覺時就沒救了"
            },
            {
                "push": "推 ",
                "text": ": 有感覺就是HF已經在吃身上的鈣了"
            },
            {
                "push": "→ ",
                "text": ": 工安這是很有趣啦 快中子反應爐也說工"
            },
            {
                "push": "→ ",
                "text": ": 安問題 然後日本都搞到廢爐"
            },
            {
                "push": "推 ",
                "text": ": 大面積潑到只能趕快打針 塗藥膏只是心理"
            },
            {
                "push": "→ ",
                "text": ": 台灣公安完整驗一輪不知道產值有沒有"
            },
            {
                "push": "→ ",
                "text": ": 剩一半"
            },
            {
                "push": "推 ",
                "text": ": 老實說資方寧願賠錢給受害者也要繼續用HF"
            },
            {
                "push": "推 ",
                "text": ": 先讓我嘆口氣，單說六氟靈吧，小面積可"
            },
            {
                "push": "→ ",
                "text": ": 成本的差異就是這麼大"
            },
            {
                "push": "→ ",
                "text": ": 以，可是氫氟酸解離性相當低，穿透到人"
            },
            {
                "push": "→ ",
                "text": ": 體內部的作用相當強，面積太大，超過"
            },
            {
                "push": "→ ",
                "text": ": 黃金時間(十分內)致死率相當高，而且就"
            },
            {
                "push": "→ ",
                "text": ": 跟上面提到的巴拉刈一樣，你只能眼睜睜"
            },
            {
                "push": "推 ",
                "text": ": HF在半導體業用這麼廣泛 怎麼可能禁啦"
            },
            {
                "push": "→ ",
                "text": ": 看著自己(病患)死去"
            },
            {
                "push": "→ ",
                "text": ": 問一下 那時候瞬間截肢有救嗎"
            },
            {
                "push": "→ ",
                "text": ": 截肢有救阿 問題是要切到哪裡??"
            },
            {
                "push": "推 ",
                "text": ": 論文也是做玻璃 要清洗白金坩堝要用到"
            },
            {
                "push": "→ ",
                "text": ":  隨時常備葡萄糖酸鈣 在操作台"
            },
            {
                "push": "推 ",
                "text": ": 像這種危險的工作還是讓機器人來做吧"
            },
            {
                "push": "推 ",
                "text": ": 那玩意進到人體會擴散的"
            },
            {
                "push": "推 ",
                "text": ": 有些製程可能甚至連替代品都沒有吧"
            },
            {
                "push": "→ ",
                "text": ": 你想花錢提高成本都沒辦法"
            },
            {
                "push": "推 ",
                "text": ": 禁用?HF?RD研發? 歡迎來到現實世界 XD"
            },
            {
                "push": "推 ",
                "text": ": 應該要穿防護衣什麼的吧，好可怕"
            },
            {
                "push": "推 ",
                "text": ": 幹 真殺人武器.."
            },
            {
                "push": "推 ",
                "text": ": 禁用HF就只能做到面板的電性等級 那個不"
            },
            {
                "push": "→ ",
                "text": ": 賺錢"
            },
            {
                "push": "推 ",
                "text": ": 有防護衣擋的下來嗎？"
            },
            {
                "push": "推 ",
                "text": ": HF不是強酸 六氟靈 不貴而且有操作HF一定"
            },
            {
                "push": "→ ",
                "text": ": 要準備"
            },
            {
                "push": "→ ",
                "text": ": 正常都要穿防護衣 HF其實腐蝕力很弱"
            },
            {
                "push": "推 ",
                "text": ": 垃圾台灣鬼島人渣賤狗理組科技狗屌的"
            },
            {
                "push": "推 ",
                "text": ": 可怕.."
            },
            {
                "push": "推 ",
                "text": ": HF潑到除了怕腐蝕骨頭 身體吸收後造成"
            },
            {
                "push": "→ ",
                "text": ": 離子不平衡.."
            },
            {
                "push": "→ ",
                "text": ": 禁HF咧 那妳可以回家生火 不要用電子產"
            },
            {
                "push": "→ ",
                "text": ": 品了.."
            },
            {
                "push": "推 ",
                "text": ": HF能說禁就禁韓國就不怕跟日本打貿易"
            },
            {
                "push": "→ ",
                "text": ": 戰了"
            },
            {
                "push": "推 ",
                "text": ": 嘻嘻 幸好我們LAB不做蝕刻了 看到那些"
            },
            {
                "push": "→ ",
                "text": ": 廢液藥品瓶都已經被吃到看不清楚內容物"
            },
            {
                "push": "→ ",
                "text": ": 了"
            },
            {
                "push": "推 ",
                "text": ": 台灣電子產業發達，氫氟酸使用量也多，槽車"
            },
            {
                "push": "→ ",
                "text": ": 幾乎天天跑。只要發生翻覆事故，附近人多一"
            },
            {
                "push": "→ ",
                "text": ": 點就會是災難了(揮發性高，蒸氣密度0.99，"
            },
            {
                "push": "→ ",
                "text": ": 隨風飄)"
            },
            {
                "push": "→ ",
                "text": ": 裝載氫氟酸的槽體叫Iso tank，可以像貨櫃一"
            },
            {
                "push": "→ ",
                "text": ": 樣堆疊，基隆港很常見。之前也在林口看到槽"
            },
            {
                "push": "→ ",
                "text": ": 車在文化三路上跑"
            },
            {
                "push": "推 ",
                "text": ": 講禁HF快去念材料科學研發替代品不要只嘴"
            },
            {
                "push": "→ ",
                "text": ": 前鎮子日韓禁運大戰就包含HF韓國就快死了"
            },
            {
                "push": "推 ",
                "text": ": 化骨綿掌"
            },
            {
                "push": "推 ",
                "text": ": 巴拉刈是噴農地的 這好歹是密閉空間用"
            },
            {
                "push": "推 ",
                "text": ": 巴拉掛一堆替代品 HF沒有其他替代品"
            },
            {
                "push": "推 ",
                "text": ": 結論：工安都不做，禁農藥也是笑話，誰"
            },
            {
                "push": "→ ",
                "text": ": 沒事喝那個，咦現在誰執政阿？"
            },
            {
                "push": "→ ",
                "text": ": 那個勞工心裡最軟的那一塊，是用HF調理"
            },
            {
                "push": "→ ",
                "text": ": 的ㄇ"
            },
            {
                "push": "推 ",
                "text": ": 禁了叫台gg關門算了"
            },
            {
                "push": "→ ",
                "text": ": 但是廠方沒有幫工人沖洗.(間接殺人)"
            },
            {
                "push": "推 ",
                "text": ": 禁用??南韓買不到日本HF都快崩潰"
            },
            {
                "push": "推 ",
                "text": ": 一小罐3000哪裡不貴？現場有準備的廠"
            },
            {
                "push": "→ ",
                "text": ": 六氟靈會過期，而且葡萄糖酸鈣軟膏比"
            },
            {
                "push": "→ ",
                "text": ": 較便宜......所以"
            },
            {
                "push": "→ ",
                "text": ": 噴到哪就切哪"
            },
            {
                "push": "推 ",
                "text": ": 禁用HF？你文組啊？"
            },
            {
                "push": "推 ",
                "text": ": 笑死 禁用 文組治國就靠你了"
            },
            {
                "push": "推 ",
                "text": ": 連六氟靈都嫌貴的廠還是別開了 連工安"
            },
            {
                "push": "→ ",
                "text": ": 都要省"
            },
            {
                "push": "推 ",
                "text": ": 致死車禍一堆要不要禁止開車啊 這邏輯"
            }
        ]
    },
    {
        "title": "遭「化骨水」噴濺 竹南鼎元光電女移工",
        "date": "2019/08/29",
        "content": "工安上班偷發文  因為工人都在休息...  好啦，首先真的RIP...  氫氟酸如果到致死濃度，還有一個非常強烈的副作用  痛，很痛，非常痛  不班門弄斧，直接貼一段pdf  https://i.imgur.com/jV8wWbA.jpg  牙痛抽過神經嗎，神經就是這麼敏感，然後這個痛是放大幾十倍，範圍也一樣...  人生就有夠苦了...這種死法更硬派...  還拖了十二小時真的慘...  ",
        "comment": [
            {
                "push": "→ ",
                "text": ": 雞就是這樣，鳳凰不會關心的"
            },
            {
                "push": "→ ",
                "text": ": R.I.P."
            },
            {
                "push": "推 ",
                "text": ": 比凌遲還痛~慘"
            },
            {
                "push": "推 ",
                "text": ": 幹 看起來超可怕"
            },
            {
                "push": "推 ",
                "text": ": 如鐵槌擊打...真難想像"
            },
            {
                "push": "→ ",
                "text": ": 夭壽，這死得好慘"
            },
            {
                "push": "推 ",
                "text": ": 怕"
            },
            {
                "push": "推 ",
                "text": ": 非離子狀態穿透皮膚到深層軟組織 啥意思?"
            }
        ]
    },
    {
        "title": "遭「化骨水」噴濺 竹南鼎元光電女移工",
        "date": "2019/08/29",
        "content": "1.媒體來源:ETtoday新聞雲   2.記者署名: 記者黃孟珍／苗栗報導  3.完整新聞標題: 遭「化骨水」噴濺　竹南鼎元光電女移工「雙腿嚴重腐蝕」慘死！    4.完整新聞內文: 苗栗縣竹南科園區內的鼎元光電科技公司，28日上午9時許驚傳工安意外，1名菲律賓籍女 移工（29歲），被俗稱「化骨水」的氫氟酸藥水打翻噴濺下肢，導致雙腿大面積嚴重腐蝕 ，經轉送台北榮總毒物科急救，仍於28日晚間10時宣告不治。  鼎元光電發言人表示，這名菲律賓籍的女移工，因為在工作時，所接觸的腐蝕性液體晃動 ，女移工轉身去承接不慎，才造成裡面的氫氟酸藥水打翻，噴濺到身上；廠內員工見狀立 刻前去幫忙，並立刻通報消防隊，無奈還是回天乏術。  苗栗縣消防局也表示，氫氟酸是1種強酸且有毒，科技廠用蝕刻電路板，又稱化骨水；用 以清洗劑等用途；當噴濺皮膚，廠商需自備六氟靈或敵氟靈中和清洗劑及葡萄糖酸鈣藥膏 塗抹（會吃人體鈣）這些藥劑尚需備置與地方急診室醫護配合，另有毒會是氟離子會與血 液鈣，鎂，鉀離子結合導致器官懷死。  苗栗縣消防局第二大隊長曹春風表示，這種工安意外可算是一種化學災害；救護人員抵達 現場時，傷者意識還算清楚，但因疼痛表情相當痛苦；而廠方第1時間內並沒有用六氟靈 或敵氟靈沖洗，因此造成嚴重的結果。  據了解，這名女移工原定9月就要回到菲律賓，怎料卻在即將返家之際卻命喪台灣；而目 前公司方面也在開會檢討後續相關問題，至於詳細的發生原因，還待警方釐清之中。  比王水還致命的氫氟酸，無色無味，其所釋出的氟離子腐蝕力很強，會直接穿透組織，對 人體具有高度腐蝕性，連骨頭都可以被溶解，因此又稱為化骨水、蝕骨水、白骨酸，很多 電影情節都會把化骨水做為滅屍手段，可以殺人於無形。     5.完整新聞連結 (或短網址): https://s.yam.com/ZPMfe   6.備註: ※ 一個人一天只能張貼一則新聞，被刪或自刪也算額度內，超貼者水桶，請注意  ",
        "comment": [
            {
                "push": "→ ",
                "text": ": .....這個好慘"
            },
            {
                "push": "→ ",
                "text": ": 可憐的外勞"
            },
            {
                "push": "→ ",
                "text": ": Q.Q 真的RIP"
            },
            {
                "push": "噓 ",
                "text": ": 化屍粉"
            },
            {
                "push": "→ ",
                "text": ": 慘"
            },
            {
                "push": "→ ",
                "text": ": 立馬截肢能活嗎?"
            },
            {
                "push": "推 ",
                "text": ": omg"
            },
            {
                "push": "推 ",
                "text": ": 台灣工安...."
            },
            {
                "push": "噓 ",
                "text": ": ......"
            },
            {
                "push": "推 ",
                "text": ": 政府：查無不法 謝謝指教"
            },
            {
                "push": "推 ",
                "text": ": 應該是超大面積接觸"
            },
            {
                "push": "噓 ",
                "text": ": 危險的東西 居然放在會晃動的地方 天啊!"
            },
            {
                "push": "推 ",
                "text": ": 老兵八字輕"
            },
            {
                "push": "→ ",
                "text": ": 好可憐 9月就要回國了......"
            },
            {
                "push": "推 ",
                "text": ": 慘"
            },
            {
                "push": "推 ",
                "text": ": 怕"
            },
            {
                "push": "推 ",
                "text": ": 夭壽，這死得好慘"
            },
            {
                "push": "推 ",
                "text": ": 老兵不出操沒聽過嗎？重罰6萬"
            },
            {
                "push": "推 ",
                "text": ": 好慘"
            },
            {
                "push": "→ ",
                "text": ": 弱酸吧"
            },
            {
                "push": "→ ",
                "text": ": 勞安大地震…"
            },
            {
                "push": "推 ",
                "text": ": 氫氟酸真的恐怖 以前看過有人手指頭碰一"
            },
            {
                "push": "推 ",
                "text": ": 這種救活也是受罪 唉"
            },
            {
                "push": "→ ",
                "text": ": 下而已 手指頭就整個黑掉了"
            },
            {
                "push": "推 ",
                "text": ": 違反公安重罰2萬"
            },
            {
                "push": "→ ",
                "text": ": 廠方第1時間內並沒有用六氟靈或敵氟靈沖"
            },
            {
                "push": "推 ",
                "text": ": QQ"
            },
            {
                "push": "→ ",
                "text": ": 洗，MSDS在哪？"
            },
            {
                "push": "→ ",
                "text": ": 絕命毒師S01E02都是真的"
            },
            {
                "push": "推 ",
                "text": ": 太扯...工安是啥洨"
            },
            {
                "push": "推 ",
                "text": ": 怕.jpg"
            },
            {
                "push": "推 ",
                "text": ": 用這些強腐蝕性的不用穿防護衣嗎"
            },
            {
                "push": "→ ",
                "text": ": 現在都改用SDS了"
            },
            {
                "push": "噓 ",
                "text": ": 沒有防護也沒備藥? 人命不值錢耶"
            },
            {
                "push": "→ ",
                "text": ": 這廠可以直接關了，連化學災害的應變能力"
            },
            {
                "push": "→ ",
                "text": ": 都沒有還敢賺科技廠的錢啊"
            },
            {
                "push": "→ ",
                "text": ": 重罰2萬"
            },
            {
                "push": "噓 ",
                "text": ": 為什麼一個人搬"
            },
            {
                "push": "推 ",
                "text": ": 廠方第1時間內並沒有用六氟靈或敵氟靈"
            },
            {
                "push": "→ ",
                "text": ": 沖洗？？？"
            },
            {
                "push": "→ ",
                "text": ": 很多上完有機作業主管課程跟沒上過一樣"
            },
            {
                "push": "推 ",
                "text": ": 視工安為無物~這業者要被重罰吧 真誇張"
            },
            {
                "push": "推 ",
                "text": ": 操 台灣可笑工安又害人回不去家鄉"
            },
            {
                "push": "推 ",
                "text": ": 關鍵字 廠房沒有..."
            },
            {
                "push": "→ ",
                "text": ": 沒做模擬訓練的話 出意外都亂成一團"
            },
            {
                "push": "→ ",
                "text": ": 工廠會想找東南亞勞工 10間有9間都是雷暴蟲"
            },
            {
                "push": "推 ",
                "text": ": 重罰2.........外籍喔免罰"
            },
            {
                "push": "噓 ",
                "text": ": 全無勞安常識，忝為高科技業"
            },
            {
                "push": "推 ",
                "text": ": HF只是弱酸而已吧"
            },
            {
                "push": "推 ",
                "text": ": 台灣籍作業員自求多福"
            },
            {
                "push": "推 ",
                "text": ": 勞安跟環工等著吃官司了 真扯 慘死"
            },
            {
                "push": "推 ",
                "text": ": 心情難過 RIP"
            },
            {
                "push": "→ ",
                "text": ": 光電業真扯"
            },
            {
                "push": "→ ",
                "text": ": 把身體的鈣吃光，恐怖"
            },
            {
                "push": "推 ",
                "text": ": 好可怕…"
            },
            {
                "push": "推 ",
                "text": ": 這公司不用關廠調查哦"
            },
            {
                "push": "推 ",
                "text": ": 台灣的無良廠商是不是又要重罰五萬了?"
            },
            {
                "push": "噓 ",
                "text": ": 這工廠公安應變能力有問題吧"
            },
            {
                "push": "推 ",
                "text": ": 這工安出大問題了吧 有夠扯的"
            },
            {
                "push": "推 ",
                "text": ": R.I.P."
            },
            {
                "push": "→ ",
                "text": ": 在台灣 工安就是作表面功夫用的"
            },
            {
                "push": "推 ",
                "text": ": ..................."
            },
            {
                "push": "推 ",
                "text": ": 不是說得上課嗎? 怎麼沒做好第一時間處理"
            },
            {
                "push": "噓 ",
                "text": ": 幹你娘氫氟酸能濺出來，這工廠應該強"
            },
            {
                "push": "→ ",
                "text": ": 制關廠檢查工安"
            },
            {
                "push": "推 ",
                "text": ": 慘……台灣工安 不意外"
            },
            {
                "push": "噓 ",
                "text": ": 三小 這公安訓練比學校還弱是怎樣"
            },
            {
                "push": "推 ",
                "text": ": 好慘 一路好走..."
            },
            {
                "push": "推 ",
                "text": ": 柯洛弗十號地窖"
            },
            {
                "push": "噓 ",
                "text": ": 沒第一時間沖洗是在幹三小？勒令停業啦操"
            },
            {
                "push": "推 ",
                "text": ": Say my name"
            },
            {
                "push": "推 ",
                "text": ": 這種廠關一關吧！"
            },
            {
                "push": "推 ",
                "text": ": R.I.P."
            },
            {
                "push": "推 ",
                "text": ": 29歲客死異鄉，這工廠根本沒有工安訓練"
            },
            {
                "push": "推 ",
                "text": ": 這麼危險的東西 叫人工來搬?"
            },
            {
                "push": "推 ",
                "text": ": 這如果在美國廠商準備被罰天價吧，"
            },
            {
                "push": "→ ",
                "text": ": 搞不好還關廠。台灣鬼島就..."
            },
            {
                "push": "噓 ",
                "text": ": 沒防護衣？"
            },
            {
                "push": "推 ",
                "text": ": 為了23K送命，不要怪年輕人為什麼挑工作"
            },
            {
                "push": "噓 ",
                "text": ": 鬼島公安不意外 下輩子別被騙來了"
            },
            {
                "push": "推 ",
                "text": ": 真的慘......"
            },
            {
                "push": "推 ",
                "text": ": 慘 被氫氟酸噴到 應該沒救了"
            },
            {
                "push": "推 ",
                "text": ": 這種不用關廠調查？ 偉哉鬼島"
            },
            {
                "push": "推 ",
                "text": ": 另外一則新聞，該公司防護衣只有上半身"
            },
            {
                "push": "推 ",
                "text": ": 幹 R.I.P 台灣公司就是這樣..."
            },
            {
                "push": "推 ",
                "text": ": 化骨綿掌"
            },
            {
                "push": "推 ",
                "text": ": 是不是應該比照巴拉刈禁用"
            },
            {
                "push": "推 ",
                "text": ": 工廠環安有問題吧！"
            },
            {
                "push": "推 ",
                "text": ": 基本配備：C衣+PAPR+防酸鹼手套+防酸鹼鞋"
            },
            {
                "push": "推 ",
                "text": ": 台灣工安 ㄎㄎ"
            },
            {
                "push": "推 ",
                "text": ": 幫QQ"
            },
            {
                "push": "推 ",
                "text": ": 好痛"
            },
            {
                "push": "推 ",
                "text": ": 化骨綿掌"
            },
            {
                "push": "推 ",
                "text": ": 難怪工廠都招不到年輕人 連命都沒了"
            },
            {
                "push": "推 ",
                "text": ": 是一種弱酸 但有強反應性…"
            },
            {
                "push": "推 ",
                "text": ": 為什麼第一時間沒有處置？ 一條人命耶！！"
            },
            {
                "push": "推 ",
                "text": ": 大面積.."
            },
            {
                "push": "→ ",
                "text": ": 沒有寶特瓶保護衣 幫QQ"
            },
            {
                "push": "→ ",
                "text": ": 現場沖身洗眼器該不會只是擺設吧"
            },
            {
                "push": "噓 ",
                "text": ": 我說那個防潑濺的裝備呢"
            },
            {
                "push": "噓 ",
                "text": ": Cost down到只給穿無塵衣嗎！買不起防護"
            },
            {
                "push": "推 ",
                "text": ": 這絕對有工安疏失，要大賠吧，沒防護就"
            },
            {
                "push": "推 ",
                "text": ": 這麼危險的東西還沒有防護，第一時間"
            },
            {
                "push": "→ ",
                "text": ": 衣乾脆公司也關一關算了！"
            },
            {
                "push": "→ ",
                "text": ": 算了，還沒有備藥"
            },
            {
                "push": "推 ",
                "text": ": R.I.P."
            },
            {
                "push": "→ ",
                "text": ": 又沒有適當的處理，台灣工安真的很慘"
            },
            {
                "push": "→ ",
                "text": ": 而且他媽的急救藥劑哪裡去了"
            },
            {
                "push": "推 ",
                "text": ": 好可怕...R.I.P."
            },
            {
                "push": "→ ",
                "text": ": 死前不知道多痛苦"
            },
            {
                "push": "推 ",
                "text": ": QQ超毒 RIP"
            },
            {
                "push": "推 ",
                "text": ": rip"
            },
            {
                "push": "推 ",
                "text": ": 這個真的超恐怖..."
            },
            {
                "push": "→ ",
                "text": ": 這是工廠有重大疏失吧？"
            },
            {
                "push": "推 ",
                "text": ": 科技廠人命浮雲來的"
            },
            {
                "push": "→ ",
                "text": ": 說比照禁用的 文組氣息太重了吧 氫氟酸"
            },
            {
                "push": "→ ",
                "text": ": 是光電蝕刻必要藥劑 不然韓國怎麼被日"
            },
            {
                "push": "→ ",
                "text": ": 本斷貨唉唉叫？  是要公安不落實的停工"
            },
            {
                "push": "推 ",
                "text": ": rip"
            },
            {
                "push": "推 ",
                "text": ": 幹你馬的黑心公司,這東西有那麼容易會放在"
            },
            {
                "push": "推 ",
                "text": ": 誇張 連發生意外該有的應對處置都沒有"
            },
            {
                "push": "→ ",
                "text": ": 讓人會打翻噴濺的地方?"
            },
            {
                "push": "→ ",
                "text": ": RIP…真的好可憐"
            },
            {
                "push": "推 ",
                "text": ": 怕"
            },
            {
                "push": "推 ",
                "text": ": 這還不給他安檢勞檢到翻過去？"
            },
            {
                "push": "推 ",
                "text": ": 謝謝你 台灣對不起你 幹 最好公司要負責"
            },
            {
                "push": "→ ",
                "text": ": 任把保險理賠的錢給她家人喔!"
            },
            {
                "push": "推 ",
                "text": ": RIP"
            },
            {
                "push": "推 ",
                "text": ": 用手去承接？ 有光電廠的氫氟酸是用人"
            },
            {
                "push": "→ ",
                "text": ": 工操作的嗎？ 不是都放高硬塑膠瓶嗎？"
            },
            {
                "push": "→ ",
                "text": ": 有機會接觸到的職位 不用全副防護嗎?"
            },
            {
                "push": "推 ",
                "text": ": QQ RIP"
            },
            {
                "push": "推 ",
                "text": ": RIP"
            },
            {
                "push": "推 ",
                "text": ": 幹...光用文字敘述我就快吐了"
            },
            {
                "push": "推 ",
                "text": ": 幹 公司安全性防護跟知識不足吧 令人難"
            },
            {
                "push": "→ ",
                "text": ": 過的新聞QQ"
            },
            {
                "push": "推 ",
                "text": ": 會碰到這種藥劑的不用防護嗎"
            },
            {
                "push": "推 ",
                "text": ": 貪婪勞工"
            },
            {
                "push": "推 ",
                "text": ": 9月要回國..."
            },
            {
                "push": "推 ",
                "text": ": 勞檢快去重罰"
            },
            {
                "push": "推 ",
                "text": ": 現在作業員真的滿多東男亞勞工..."
            },
            {
                "push": "推 ",
                "text": ": 這種公司台灣不知道還有幾家"
            },
            {
                "push": "推 ",
                "text": ": 在歐美發生這種是直接強制關厰，我們有"
            },
            {
                "push": "→ ",
                "text": ": 嗎"
            },
            {
                "push": "推 ",
                "text": ": 幹，這工安機制有嚴重瑕疵吧，馬的，外籍"
            },
            {
                "push": "推 ",
                "text": ": 這也太屌..."
            },
            {
                "push": "→ ",
                "text": ": 移工的命不值錢嗎？操爛公司"
            },
            {
                "push": "推 ",
                "text": ": 太危險了吧"
            },
            {
                "push": "推 ",
                "text": ": 幹嚇死我了"
            },
            {
                "push": "推 ",
                "text": ": 9月要回菲律賓 29號就  好難過QQ RIP"
            },
            {
                "push": "→ ",
                "text": ": 查一下馬上用六氟靈是可以沒事的"
            },
            {
                "push": "→ ",
                "text": ": 但是一瓶非常貴"
            },
            {
                "push": "→ ",
                "text": ": 這種破工廠 強制關起來吧"
            },
            {
                "push": "→ ",
                "text": ": 他媽的爛公司"
            },
            {
                "push": "推 ",
                "text": ": 這什麼工廠 老闆應該賠錢+坐牢"
            },
            {
                "push": "推 ",
                "text": ": 樓上 不是沒事 是不會死但有後遺症"
            },
            {
                "push": "→ ",
                "text": ": 請到鳳凰就不會怕化骨水了"
            },
            {
                "push": "推 ",
                "text": ": 這麼危險的事給移工做"
            },
            {
                "push": "推 ",
                "text": ": 這三小垃圾工廠糙"
            },
            {
                "push": "→ ",
                "text": ": 台灣的工安規定很嚴格了 問題是沒有照做"
            },
            {
                "push": "→ ",
                "text": ": 這公司問題很大，用氫氟酸事故的SOP呢"
            },
            {
                "push": "推 ",
                "text": ": 這種東西能這麼容易噴出來是三小公司"
            },
            {
                "push": "噓 ",
                "text": ": 沒第一時間沖洗？ 敢不敢報名字出來"
            },
            {
                "push": "推 ",
                "text": ": 垃圾資方 高調"
            },
            {
                "push": "推 ",
                "text": ": 化骨水  第一次聽到  @@"
            },
            {
                "push": "推 ",
                "text": ": 慘"
            },
            {
                "push": "→ ",
                "text": ": 有些公司危險的都給阿賓做"
            },
            {
                "push": "推 ",
                "text": ": 怕……R.I.P."
            },
            {
                "push": "推 ",
                "text": ": 阿看到名字了 高調"
            },
            {
                "push": "推 ",
                "text": ": 好恐怖"
            },
            {
                "push": "噓 ",
                "text": ": ... 這是三小爛公安"
            },
            {
                "push": "噓 ",
                "text": ": 文組不要發言好嗎"
            },
            {
                "push": "噓 ",
                "text": ": 怎麼會這麼容易噴出來？這公司.."
            },
            {
                "push": "推 ",
                "text": ": 廠商有過失了吧"
            },
            {
                "push": "推 ",
                "text": ": 老白就是用這個處理屍體的..."
            },
            {
                "push": "噓 ",
                "text": ": 公司沒中和東西 真的夠爛"
            },
            {
                "push": "推 ",
                "text": ": 賠償事宜呢？"
            },
            {
                "push": "推 ",
                "text": ": 超慘"
            },
            {
                "push": "推 ",
                "text": ": 港警水泡車裝這個不就好了保證跑光"
            },
            {
                "push": "→ ",
                "text": ": ....."
            },
            {
                "push": "推 ",
                "text": ": 工安爛到什麼程度才會發生這種事"
            },
            {
                "push": "推 ",
                "text": ": 慘"
            },
            {
                "push": "推 ",
                "text": ": 老闆都不准我們用這個"
            },
            {
                "push": "推 ",
                "text": ": 這要罰多點"
            },
            {
                "push": "→ ",
                "text": ": 抓老闆去關"
            },
            {
                "push": "推 ",
                "text": ": 痛"
            },
            {
                "push": "噓 ",
                "text": ": 鬼島不意外 最美的風景是人 資方會自"
            },
            {
                "push": "推 ",
                "text": ": 來看看是不是重罰兩萬"
            },
            {
                "push": "推 ",
                "text": ": 律"
            },
            {
                "push": "推 ",
                "text": ": 這間公司該勞檢了吧 真的是人為意外嗎？"
            },
            {
                "push": "→ ",
                "text": ": 還是因為環境不良設備不足造成的？"
            },
            {
                "push": "推 ",
                "text": ": 很嚴重的公安疏失"
            },
            {
                "push": "推 ",
                "text": ": 公司賺錢比較要緊其他請忍耐"
            },
            {
                "push": "推 ",
                "text": ": 這應該停工吧 公安都沒防護沒做好 殺死"
            },
            {
                "push": "推 ",
                "text": ": 有氫氟酸的地方沒敵氟靈？"
            },
            {
                "push": "→ ",
                "text": ": 人"
            },
            {
                "push": "→ ",
                "text": ": 這間公司根本沒公安"
            },
            {
                "push": "噓 ",
                "text": ": 台灣有些上市櫃電子公司工安程序超有"
            },
            {
                "push": "噓 ",
                "text": ": 蔡英文：你們要自立自強啊"
            },
            {
                "push": "推 ",
                "text": ": 扯..."
            },
            {
                "push": "推 ",
                "text": ": 廠長飛天了"
            },
            {
                "push": "推 ",
                "text": ": 出人命應該會停工吧"
            },
            {
                "push": "→ ",
                "text": ": 這工安實在太瞎"
            },
            {
                "push": "推 ",
                "text": ": 這個很毒欸，工安不合格"
            },
            {
                "push": "推 ",
                "text": ": 有HF的沒敵氟靈 扯"
            },
            {
                "push": "推 ",
                "text": ": 裝備都沒有嗎..."
            },
            {
                "push": "推 ",
                "text": ": 先猜HF"
            },
            {
                "push": "噓 ",
                "text": ": 工安超爛   視人命如草芥"
            },
            {
                "push": "推 ",
                "text": ": 哇 辛苦移工"
            },
            {
                "push": "→ ",
                "text": ": 準備被勞檢到關廠吧"
            },
            {
                "push": "噓 ",
                "text": ": HF能濺出來  猛  這廠商夠猛"
            },
            {
                "push": "推 ",
                "text": ": 太扯了5重大工安意外...RIP"
            },
            {
                "push": "推 ",
                "text": ": 怕豹"
            },
            {
                "push": "推 ",
                "text": ": 高調 幹有夠可怕"
            },
            {
                "push": "推 ",
                "text": ": 可怕"
            },
            {
                "push": "→ ",
                "text": ": 不過到底為什麼會讓這麼危險的東西晃動"
            },
            {
                "push": "→ ",
                "text": ": 再來女移工會去接 顯然也不知這東西的危"
            },
            {
                "push": "→ ",
                "text": ": 險 旁邊都沒人告訴她要注意嗎..."
            },
            {
                "push": "推 ",
                "text": ": 如果要用這個又不準備相關防護救命措施，"
            },
            {
                "push": "→ ",
                "text": ": 應該是殺人罪"
            },
            {
                "push": "推 ",
                "text": ": 全廠要高光了"
            },
            {
                "push": "推 ",
                "text": ": 這家好像是做燈的..."
            },
            {
                "push": "推 ",
                "text": ": 丟臉死了，爛到炸，只想著賺錢的無良公"
            },
            {
                "push": "→ ",
                "text": ": 司"
            },
            {
                "push": "推 ",
                "text": ": R.I.P..."
            },
            {
                "push": "推 ",
                "text": ": 來鬼島工作還想活著回去R"
            },
            {
                "push": "推 ",
                "text": ": 故意的啦 命賤又不怕妳告 恐無勞健保職災險"
            },
            {
                "push": "推 ",
                "text": ": R.I.P."
            },
            {
                "push": "推 ",
                "text": ": 有沒有無塵衣?沖洗設備?充足的教育訓練?"
            },
            {
                "push": "→ ",
                "text": ": 這種公司應該直接罰負責人到破產吧…"
            },
            {
                "push": "推 ",
                "text": ": 備藥，要錢的ㄟ，出事了不起重罰6萬，藥品"
            },
            {
                "push": "噓 ",
                "text": ": 這種東西竟然會有接觸機會"
            },
            {
                "push": "→ ",
                "text": ": 一年搞不好要幾十萬，鬼島慣老闆怎麼可能"
            },
            {
                "push": "推 ",
                "text": ": 垃圾公司，幹你娘"
            },
            {
                "push": "→ ",
                "text": ": 買，反正環安勞安又不會抓去關"
            },
            {
                "push": "→ ",
                "text": ": 工安吃大便的嗎"
            },
            {
                "push": "推 ",
                "text": ": 不知道賠多少"
            },
            {
                "push": "推 ",
                "text": ": 有沒有第一時間急救? 這間公司麻煩大了"
            },
            {
                "push": "→ ",
                "text": ": 有些人是寧死也不回去，就變這樣了"
            },
            {
                "push": "推 ",
                "text": ": 為什麼這麼危險藥劑沒防護"
            },
            {
                "push": "推 ",
                "text": ": 第一時間只能噴六氟靈+擦葡萄酸鈣"
            },
            {
                "push": "推 ",
                "text": ": 臺灣難波萬"
            },
            {
                "push": "推 ",
                "text": ": 生氣欸，這麼危險的東西，沒備藥沒防護"
            },
            {
                "push": "→ ",
                "text": ": ，開什麼玩笑"
            },
            {
                "push": "推 ",
                "text": ": 重罰三萬 下面一位"
            },
            {
                "push": "推 ",
                "text": ": 扯"
            },
            {
                "push": "→ ",
                "text": ": 免洗外勞 可撥"
            },
            {
                "push": "推 ",
                "text": ": 好慘"
            },
            {
                "push": "噓 ",
                "text": ": 勞檢重罰"
            },
            {
                "push": "→ ",
                "text": ": 有申請使用許可就一定要在操作場所內"
            },
            {
                "push": "→ ",
                "text": ": 配置中和劑耶 這三小？"
            },
            {
                "push": "推 ",
                "text": ": 幹腐蝕到死"
            },
            {
                "push": "推 ",
                "text": ": 絕命終結站都是真的"
            },
            {
                "push": "推 ",
                "text": ": 這種中和劑都碼放到過期的一堆"
            },
            {
                "push": "推 ",
                "text": ": 好慘 這種東西竟然會掉落想去接= ="
            },
            {
                "push": "推 ",
                "text": ": OUT!!"
            },
            {
                "push": "→ ",
                "text": ": 看到中和劑就想到 以前實驗室老闆看到"
            },
            {
                "push": "推 ",
                "text": ": 扯 出事了 公司要負責"
            },
            {
                "push": "→ ",
                "text": ": 價錢後 就裝死不買了 哈哈哈..."
            },
            {
                "push": "推 ",
                "text": ": ....."
            },
            {
                "push": "推 ",
                "text": ": 老闆發大財"
            },
            {
                "push": "推 ",
                "text": ": 藥比人貴，死了就再買一個人就好啦"
            },
            {
                "push": "推 ",
                "text": ": 唉好慘"
            },
            {
                "push": "→ ",
                "text": ": 工安怎麼做的 高危藥品這麼容易打翻"
            },
            {
                "push": "推 ",
                "text": ": R.I.P."
            },
            {
                "push": "推 ",
                "text": ": 唉！菲律賓都大學畢的"
            },
            {
                "push": "推 ",
                "text": ": 幹果然鬼島 廠房沒有應急處理是三小"
            },
            {
                "push": "→ ",
                "text": ": 廠方第1時間內並沒有用六氟靈"
            },
            {
                "push": "→ ",
                "text": ": 或敵氟靈沖洗<<台灣垃圾老闆不ey"
            },
            {
                "push": "推 ",
                "text": ": 外勞家屬討得回公道嗎？"
            },
            {
                "push": "推 ",
                "text": ": 真的很可怕"
            },
            {
                "push": "推 ",
                "text": ": 過期還好......沒用才是重點都有出5L大噴"
            },
            {
                "push": "→ ",
                "text": ": 通常都會準備 現場怎麼沒反應"
            },
            {
                "push": "→ ",
                "text": ": 疑似滴到都立馬狂洗"
            },
            {
                "push": "推 ",
                "text": ": 工安問題很大"
            },
            {
                "push": "噓 ",
                "text": ": 管理層級這麼多層出事也不會辦到老闆"
            },
            {
                "push": "→ ",
                "text": ": 解藥這麼貴 罰金這麼便宜 工安檢查塞"
            },
            {
                "push": "→ ",
                "text": ": 點錢就過關 政治人物通通都財團的狗"
            },
            {
                "push": "推 ",
                "text": ": 南無阿彌陀佛"
            },
            {
                "push": "→ ",
                "text": ": 我他媽X你鬼島"
            },
            {
                "push": "推 ",
                "text": ": QQ"
            },
            {
                "push": "推 ",
                "text": ": 我記得骨頭會直接廢掉"
            },
            {
                "push": "推 ",
                "text": ": 好可怕"
            },
            {
                "push": "推 ",
                "text": ": rip"
            },
            {
                "push": "推 ",
                "text": ": 哇靠  這東西能直接搬??? 工廠工安在幹嘛"
            },
            {
                "push": "推 ",
                "text": ": 這種爛公司害人不淺 什麼防護急救通通"
            },
            {
                "push": "推 ",
                "text": ": 政府：自己跟老闆反應"
            },
            {
                "push": "→ ",
                "text": ": 都沒有"
            },
            {
                "push": "推 ",
                "text": ": 公司有問題吧"
            },
            {
                "push": "噓 ",
                "text": ": 沒工安的公司"
            },
            {
                "push": "推 ",
                "text": ": 慘  重罰兩萬"
            },
            {
                "push": "推 ",
                "text": ": 腿的骨頭應該都不見了 專門吃鈣的酸"
            },
            {
                "push": "推 ",
                "text": ": HF是很可怕的東西"
            },
            {
                "push": "推 ",
                "text": ": 好可憐"
            },
            {
                "push": "推 ",
                "text": ": 幹 死的不是高官名人 就他媽不了了之"
            },
            {
                "push": "→ ",
                "text": ": ，幹整天拼他媽狗屁選舉有個屌用，幹"
            },
            {
                "push": "→ ",
                "text": ": 藥這麼貴  當然重罰6萬就好 科科"
            },
            {
                "push": "推 ",
                "text": ": 垃圾公司搭配慣老闆 台灣定番！"
            },
            {
                "push": "推 ",
                "text": ": 女移工轉身去承接…"
            },
            {
                "push": "噓 ",
                "text": ": 整篇疑點超多，不過我猜政府大概又重"
            },
            {
                "push": "→ ",
                "text": ": 罰2萬不了了之也不去查"
            },
            {
                "push": "推 ",
                "text": ": QQ"
            },
            {
                "push": "噓 ",
                "text": ": 另一篇內容合理多了"
            },
            {
                "push": "推 ",
                "text": ": 我佩服我自己待過這公司一年"
            },
            {
                "push": "推 ",
                "text": ": 這工廠有問題吧！"
            },
            {
                "push": "推 ",
                "text": ": RIP"
            },
            {
                "push": "推 ",
                "text": ": 這桶HF倒完就要回老家了"
            },
            {
                "push": "→ ",
                "text": ": 一定河蟹的啦"
            },
            {
                "push": "推 ",
                "text": ": 這廠工安可以廢了吧 連敵氟靈都沒有"
            },
            {
                "push": "→ ",
                "text": ": 沒有個人防護具？？"
            },
            {
                "push": "推 ",
                "text": ": 葡萄糖胺打下去啊"
            },
            {
                "push": "推 ",
                "text": ": 氟離子會與血液鈣，鎂，鉀離子結合"
            },
            {
                "push": "→ ",
                "text": ": 導致器官(懷)死。"
            },
            {
                "push": "噓 ",
                "text": ": 這該重罰吧"
            },
            {
                "push": "推 ",
                "text": ": 這被滴到一滴都會造成相當恐怖的傷害了"
            },
            {
                "push": "推 ",
                "text": ": 唉..."
            },
            {
                "push": "推 ",
                "text": ": 我下個月就要回國了！      （手滑）"
            },
            {
                "push": "噓 ",
                "text": ": 這一定要重罰   2萬   不能在多了"
            },
            {
                "push": "→ ",
                "text": ": 知道很毒的反應是躲開，明顯沒工安宣導"
            },
            {
                "push": "→ ",
                "text": ": 就像知道熱水很燙，打翻不會去接一樣"
            },
            {
                "push": "噓 ",
                "text": ": 幹，HF溶液這麼隨便處理，廠方還真"
            },
            {
                "push": "→ ",
                "text": ": 的不怕罰"
            },
            {
                "push": "推 ",
                "text": ": 唉"
            },
            {
                "push": "推 ",
                "text": ": QQ,R.I.P."
            },
            {
                "push": "推 ",
                "text": ": 又是工安"
            },
            {
                "push": "→ ",
                "text": ": 請正名奴工"
            },
            {
                "push": "噓 ",
                "text": ": 看了真的憤怒！希望有人可以幫忙向公"
            },
            {
                "push": "→ ",
                "text": ": 司求償啊！"
            },
            {
                "push": "推 ",
                "text": ": 工安不能省"
            },
            {
                "push": "→ ",
                "text": ": r.i.p"
            },
            {
                "push": "噓 ",
                "text": ": 沒有任何防護措施 是什麼鬼"
            },
            {
                "push": "推 ",
                "text": ": 高調..！"
            },
            {
                "push": "→ ",
                "text": ": 這什麼爛工廠啊 有用就要準備藥"
            },
            {
                "push": "推 ",
                "text": ": 幹 公司沒有備中和用的藥？"
            },
            {
                "push": "噓 ",
                "text": ": 氫氟酸是弱酸 沒讀過高中?"
            },
            {
                "push": "噓 ",
                "text": ": 弱酸"
            },
            {
                "push": "→ ",
                "text": ": 可憐的外勞"
            },
            {
                "push": "噓 ",
                "text": ": 絕對是慣老闆嫌藥太貴才沒買"
            },
            {
                "push": "推 ",
                "text": ": 怕.jpg"
            },
            {
                "push": "推 ",
                "text": ": 有新聞寫以葡萄糖酸鈣凝膠塗抹，不知"
            },
            {
                "push": "→ ",
                "text": ": 道算是中和藥物嗎"
            },
            {
                "push": "噓 ",
                "text": ": 垃圾公司"
            },
            {
                "push": "推 ",
                "text": ": R.I.P"
            },
            {
                "push": "推 ",
                "text": ": 怕"
            },
            {
                "push": "推 ",
                "text": ": 平常沒在演練是不是"
            },
            {
                "push": "推 ",
                "text": ": 敵腐靈到底哪裡貴了  根本純粹太摳"
            },
            {
                "push": "推 ",
                "text": ": ...rip"
            },
            {
                "push": "推 ",
                "text": ": 慘"
            },
            {
                "push": "→ ",
                "text": ": 這是什麼工安、可憐的外勞 =="
            },
            {
                "push": "推 ",
                "text": ": 是沒有還是沒訓練啊？有點誇張耶"
            },
            {
                "push": "噓 ",
                "text": ": 台灣工安就是個笑話"
            },
            {
                "push": "推 ",
                "text": ": 唉好不容易出國工作要回家了......"
            },
            {
                "push": "推 ",
                "text": ": 好慘…R.I.P"
            },
            {
                "push": "推 ",
                "text": ": 絕命毒師有演"
            },
            {
                "push": "推 ",
                "text": ": 台灣資方對不起你  RIP 希望同鄉能幫你討公"
            },
            {
                "push": "→ ",
                "text": ": 道"
            },
            {
                "push": "噓 ",
                "text": ": 強酸？"
            },
            {
                "push": "推 ",
                "text": ": 說話笑話 工廠注重工安"
            },
            {
                "push": "→ ",
                "text": ": 好可憐 為生計客死異鄉"
            },
            {
                "push": "推 ",
                "text": ": 慘"
            },
            {
                "push": "推 ",
                "text": ": 害死移工..........."
            },
            {
                "push": "→ ",
                "text": ": 可惡資方 一定賠點小錢全身而退"
            },
            {
                "push": "→ ",
                "text": ": 化骨綿掌 流手汗"
            },
            {
                "push": "→ ",
                "text": ": 政府，沒差啦。人多"
            },
            {
                "push": "噓 ",
                "text": ": 噓公司"
            },
            {
                "push": "噓 ",
                "text": ": 怎麼沒有馬上洗啊！太扯了啦！"
            },
            {
                "push": "推 ",
                "text": ": 連這藥都沒給也太扯"
            },
            {
                "push": "→ ",
                "text": ": 疼痛指數應該報表了吧！天啊（頭皮麻"
            },
            {
                "push": "→ ",
                "text": ": 了）"
            },
            {
                "push": "推 ",
                "text": ": HF是弱酸 但是會跟骨頭裡的鈣結合 俗"
            },
            {
                "push": "→ ",
                "text": ": 稱化骨水 葡萄糖酸鈣可以讓藥劑的鈣"
            },
            {
                "push": "→ ",
                "text": ": 先跟HF結合 所以都要放 工安都要上的"
            },
            {
                "push": "推 ",
                "text": ": 政府該主動安檢了吧"
            },
            {
                "push": "噓 ",
                "text": ": 廠房 負責啊"
            },
            {
                "push": "→ ",
                "text": ": 台灣很多公司根本就沒在管工安 唉 這"
            },
            {
                "push": "→ ",
                "text": ": 太多黑暗的故事了"
            },
            {
                "push": "推 ",
                "text": ": RIP"
            },
            {
                "push": "推 ",
                "text": ": 一堆工廠公安根本笑話 擺擺樣子而已"
            },
            {
                "push": "推 ",
                "text": ": 半導體常見 公安"
            },
            {
                "push": "推 ",
                "text": ": 唉可憐… R.I.P."
            },
            {
                "push": "推 ",
                "text": ": 沒穿化學防護衣?"
            },
            {
                "push": "推 ",
                "text": ": 不用停工？？嚴重工安耶"
            },
            {
                "push": "推 ",
                "text": ": 可憐的外勞，後續ㄧ定就被蓋掉了 因為她"
            },
            {
                "push": "→ ",
                "text": ": 沒有家人幫她爭取"
            },
            {
                "push": "推 ",
                "text": ": 別欺負外勞"
            },
            {
                "push": "→ ",
                "text": ": 醫生白癡喔 這種就不要救了"
            },
            {
                "push": "推 ",
                "text": ": 妖受"
            },
            {
                "push": "推 ",
                "text": ": 有機制幫移工討公道嗎？"
            },
            {
                "push": "推 ",
                "text": ": 太可怕了囧....."
            },
            {
                "push": "推 ",
                "text": ": 被這碰到就只能打止痛交代後事了嗎…"
            },
            {
                "push": "→ ",
                "text": ": 怕..."
            },
            {
                "push": "推 ",
                "text": ": 哇靠，這公安…有應對方式還沒做，到"
            },
            {
                "push": "→ ",
                "text": ": 底有多爛"
            },
            {
                "push": "→ ",
                "text": ": 這個不查真的會有報應"
            },
            {
                "push": "推 ",
                "text": ": RIP"
            },
            {
                "push": "推 ",
                "text": ": 老闆的良心過得去嗎？"
            },
            {
                "push": "推 ",
                "text": ": 天啊"
            },
            {
                "push": "推 ",
                "text": ": 不用關廠嗎 政府幹啥吃的"
            },
            {
                "push": "→ ",
                "text": ": 在苗栗 新聞過了就沒事了"
            },
            {
                "push": "推 ",
                "text": ": 台灣公安真的可笑"
            },
            {
                "push": "推 ",
                "text": ": 這家勞安大概要起飛了"
            },
            {
                "push": "推 ",
                "text": ": 臺灣做工安很卑微 老闆根本不挺"
            },
            {
                "push": "推 ",
                "text": ": 說HF弱酸的你化學老師在瞪你了"
            },
            {
                "push": "→ ",
                "text": ": 好，我認錯，化學老師對不起"
            },
            {
                "push": "推 ",
                "text": ": 政府都沒在稽查的嗎......"
            },
            {
                "push": "推 ",
                "text": ": 鬼島一堆垃圾老闆"
            },
            {
                "push": "推 ",
                "text": ": 工廠很扯喔"
            },
            {
                "push": "推 ",
                "text": ": 毫無工安 可憐的移工......"
            },
            {
                "push": "推 ",
                "text": ": 這個一定要用力處罰，不然廠商決不會"
            },
            {
                "push": "→ ",
                "text": ": 記住教訓，下次又一樣"
            },
            {
                "push": "推 ",
                "text": ": R.I P. 都快回家鄉了幫QQ"
            },
            {
                "push": "推 ",
                "text": ": 夭壽"
            },
            {
                "push": "推 ",
                "text": ": 台灣老闆繼續賺錢壓榨勞工！！！台灣人要"
            },
            {
                "push": "→ ",
                "text": ": 自己覺醒，走黑的偏的在台灣最快有錢！！"
            },
            {
                "push": "→ ",
                "text": ": ！"
            },
            {
                "push": "推 ",
                "text": ": 很慘"
            },
            {
                "push": "→ ",
                "text": ": 台灣中小企業有錢94這樣來的，壓榨來的"
            },
            {
                "push": "推 ",
                "text": ": 把工安當屁的公司"
            },
            {
                "push": "推 ",
                "text": ": 絕對要重罰"
            },
            {
                "push": "推 ",
                "text": ": R.I.P"
            },
            {
                "push": "→ ",
                "text": ": 廠方沒有用六氟靈或敵氟靈沖洗....."
            },
            {
                "push": "推 ",
                "text": ": 好可憐QQ"
            },
            {
                "push": "噓 ",
                "text": ": 這記者後半段到底在打什麼 中文邏輯有"
            },
            {
                "push": "→ ",
                "text": ": 問題膩"
            },
            {
                "push": "推 ",
                "text": ": 恐怖= ="
            },
            {
                "push": "噓 ",
                "text": ": 說個笑話 台灣有科技業"
            },
            {
                "push": "噓 ",
                "text": ": 要選舉了，把他搞大，政府會更重視"
            },
            {
                "push": "推 ",
                "text": ": 頂多發到廠長"
            },
            {
                "push": "推 ",
                "text": ": 史上最強酸。這老闆造孽！"
            },
            {
                "push": "推 ",
                "text": ": 怕！ 工安勞檢用力督下去"
            },
            {
                "push": "推 ",
                "text": ": 這公安慘了"
            },
            {
                "push": "推 ",
                "text": ": 想到女版說的 要外勞滾 錢給多一點會"
            },
            {
                "push": "→ ",
                "text": ": 沒人做嗎"
            },
            {
                "push": "噓 ",
                "text": ": 拜託重罰 真的很缺德 RIP 台灣害了你"
            },
            {
                "push": "推 ",
                "text": ": R.I.P"
            },
            {
                "push": "噓 ",
                "text": ": 老闆應該也來被潑一下啦！！！"
            },
            {
                "push": "噓 ",
                "text": ": 你知道科技公司養活多少台灣家庭嗎？"
            },
            {
                "push": "→ ",
                "text": ": 台灣價值＝客家價值"
            },
            {
                "push": "→ ",
                "text": ": 真慘，痛死的！"
            },
            {
                "push": "→ ",
                "text": ": 這家廠長，現場公安組長，總經理應該要"
            },
            {
                "push": "噓 ",
                "text": ": 這工廠都不用罰嗎？太扯了"
            },
            {
                "push": "→ ",
                "text": ": 移送法辦"
            },
            {
                "push": "推 ",
                "text": ": 乾，光看文字就毛"
            },
            {
                "push": "→ ",
                "text": ": 這麼毒的化學藥劑，隨便都可以打翻……"
            },
            {
                "push": "推 ",
                "text": ": 希望國昌老師能瞭解一下"
            },
            {
                "push": "→ ",
                "text": ": 安全措施都沒有喔？"
            },
            {
                "push": "→ ",
                "text": ": 別鬧呀，套40張很久了"
            },
            {
                "push": "推 ",
                "text": ": 台灣工安何時會進步？"
            },
            {
                "push": "推 ",
                "text": ": 好恐怖"
            },
            {
                "push": "推 ",
                "text": ": 現場有放滴腐靈的很少，通常都放在工"
            },
            {
                "push": "噓 ",
                "text": ": 嘻嘻 台 灣 在座的各位 一個都逃不掉"
            },
            {
                "push": "推 ",
                "text": ": 連六氟靈也要cost down....真的很夭壽"
            },
            {
                "push": "推 ",
                "text": ": 停工了嗎"
            },
            {
                "push": "推 ",
                "text": ": 為什麼第一時間沒有用????"
            },
            {
                "push": "噓 ",
                "text": ": HF是弱酸不是強酸....."
            },
            {
                "push": "推 ",
                "text": ": 台灣何時才要把勞工當成人"
            },
            {
                "push": "推 ",
                "text": ": 這就是公安問題 還有處置不當"
            },
            {
                "push": "推 ",
                "text": ": 氫氟酸的解離度低 是定義上的弱酸 威脅"
            },
            {
                "push": "→ ",
                "text": ": 性是在於氟離子 氟離子本身穿透性強 又"
            },
            {
                "push": "→ ",
                "text": ": 能跟體內的鈣鎂離子結合並沉澱 使血液中"
            },
            {
                "push": "→ ",
                "text": ": 的鈣鎂離子濃度迅速降低 需要仰賴鈣鎂離"
            },
            {
                "push": "→ ",
                "text": ": 子的運作的器官會因此而慢慢壞死"
            },
            {
                "push": "推 ",
                "text": ": 誇張公司"
            },
            {
                "push": "推 ",
                "text": ": 希望有民代幫這個可憐的外勞向公司求償"
            },
            {
                "push": "推 ",
                "text": ": 算了吧鬼島政客那死樣子 賣賣芒果就沒事了"
            },
            {
                "push": "噓 ",
                "text": ": 第一時間內並沒有用六氟靈或敵氟靈沖洗"
            },
            {
                "push": "→ ",
                "text": ": 這個砂石車輾過去再倒車是同一個道理嗎"
            },
            {
                "push": "推 ",
                "text": ": 這家的工安..."
            },
            {
                "push": "→ ",
                "text": ": 倒車是壓別人 這跟普悠馬撞車後還是不換零"
            },
            {
                "push": "→ ",
                "text": ": 件同理 等下一個倒楣鬼"
            },
            {
                "push": "推 ",
                "text": ": Rip"
            },
            {
                "push": "推 ",
                "text": ": 好痛.......辛苦了"
            },
            {
                "push": "推 ",
                "text": ": 銃夢畫過 痛到射精"
            },
            {
                "push": "推 ",
                "text": ": RIP   破麻蔡的去跟你老闆講 果然經典"
            },
            {
                "push": "推 ",
                "text": ": 防護衣呢"
            },
            {
                "push": "推 ",
                "text": ": 沒有沖洗..."
            },
            {
                "push": "噓 ",
                "text": ": 至少關廠一年 提出解決計畫吧"
            },
            {
                "push": "推 ",
                "text": ": 唉......下被子不要來台灣了"
            },
            {
                "push": "→ ",
                "text": ": 真是垃圾公司，不把人命看再眼裡"
            },
            {
                "push": "推 ",
                "text": ": 沒有台灣價值"
            },
            {
                "push": "→ ",
                "text": ": 天啊..."
            },
            {
                "push": "→ ",
                "text": ": 沒有六氟靈就100%是工廠的鍋"
            },
            {
                "push": "推 ",
                "text": ": RIP，什麼公司裝這種液體的容器搞到會晃動.."
            },
            {
                "push": "→ ",
                "text": ": 好可憐，R.I.P."
            },
            {
                "push": "推 ",
                "text": ": 阿彌陀佛"
            },
            {
                "push": "→ ",
                "text": ": 聽說台灣勞工缺人…廢話  拿生命開玩"
            },
            {
                "push": "→ ",
                "text": ": 笑嗎，僱主是什麼雜碎本國人怎麼不知"
            },
            {
                "push": "推 ",
                "text": ": 台灣工安真他媽的垃圾"
            },
            {
                "push": "推 ",
                "text": ": 六氟靈一直沖應該有解才對"
            },
            {
                "push": "噓 ",
                "text": ": 重罰三千。。。"
            },
            {
                "push": "→ ",
                "text": ": 幹  這超毒欸  恐怖"
            },
            {
                "push": "推 ",
                "text": ": 台灣真的對工安一點都不在乎"
            },
            {
                "push": "推 ",
                "text": ": 智障屎蛆怎摸不叫兩聲苗栗沒勞檢聽聽啊"
            },
            {
                "push": "推 ",
                "text": ": 氟離子會跟身體的鈣行程氟化鈣...."
            },
            {
                "push": "推 ",
                "text": ": 韓導表示：死了一隻雞"
            },
            {
                "push": "推 ",
                "text": ": 一路好走，希望下次有人能及時處理"
            },
            {
                "push": "推 ",
                "text": ": 太扯了這種死法好痛苦啊"
            },
            {
                "push": "推 ",
                "text": ": 破麻蔡迷迷還敢提勞檢 讚喔 快去總統府"
            },
            {
                "push": "推 ",
                "text": ": 修惡勞基法 迷迷裝死  現在快奮起啊 是洨英"
            },
            {
                "push": "→ ",
                "text": ": 這是弱酸"
            },
            {
                "push": "推 ",
                "text": ": 查無不法謝謝指教"
            },
            {
                "push": "推 ",
                "text": ": 弱酸但對鈣質強作用阿，弱只是水解離程度"
            },
            {
                "push": "→ ",
                "text": ": 幹噓文好噁心，硬要帶政治是有多可撥"
            },
            {
                "push": "推 ",
                "text": ": 台灣工安呵呵"
            },
            {
                "push": "推 ",
                "text": ": 氫氟酸是弱酸吧"
            },
            {
                "push": "推 ",
                "text": ": 石蕊試紙碰到漏出的少量HF就變紅色"
            },
            {
                "push": "→ ",
                "text": ": 100趴純HF真的很恐怖"
            },
            {
                "push": "推 ",
                "text": ": http://i.imgur.com/iZH9AEo.jpg"
            },
            {
                "push": "推 ",
                "text": ": 奪魂鋸現實版！！！"
            },
            {
                "push": "推 ",
                "text": ": 好可憐...."
            },
            {
                "push": "推 ",
                "text": ": 這工安是不存在了嗎？"
            },
            {
                "push": "噓 ",
                "text": ": 最後一段第一句跟最後一句是亂寫的"
            },
            {
                "push": "推 ",
                "text": ": QQ 工廠太罔顧安全教育"
            },
            {
                "push": "噓 ",
                "text": ": 記者不懂不要亂寫好嗎"
            },
            {
                "push": "推 ",
                "text": ": RIP"
            },
            {
                "push": "推 ",
                "text": ": 氫氟酸是弱酸"
            },
            {
                "push": "推 ",
                "text": ": 公安沒問題嗎！不用罰不用改善嗎！"
            },
            {
                "push": "噓 ",
                "text": ": 我看廠內連六氟靈都沒買吧"
            },
            {
                "push": "→ ",
                "text": ": 記者第三段在寫啥，可以檢查一下再交卷"
            },
            {
                "push": "→ ",
                "text": ": 嗎？"
            },
            {
                "push": "噓 ",
                "text": ": 一堆外行人在那邊糾結氫氟酸強酸弱酸有意"
            },
            {
                "push": "→ ",
                "text": ": 義麻 難道弱酸造成的危害就會比強酸小?"
            },
            {
                "push": "噓 ",
                "text": ": 工安也太差了 連基本工安都沒宣導？"
            },
            {
                "push": "→ ",
                "text": ": 準備被環檢所電爆吧"
            },
            {
                "push": "推 ",
                "text": ": 真的是慘死 R.I.P"
            },
            {
                "push": "推 ",
                "text": ": 懂的人根本不會去想親自下去鄵做PCB"
            },
            {
                "push": "→ ",
                "text": ": 電解液 會去做的都是極缺錢或者外勞"
            },
            {
                "push": "推 ",
                "text": ": 我之前客戶啦 只能說不ey"
            },
            {
                "push": "推 ",
                "text": ": RIP"
            },
            {
                "push": "→ ",
                "text": ": 9月才差幾天.."
            },
            {
                "push": "推 ",
                "text": ": 老闆：不怕…反正負責人不是我"
            },
            {
                "push": "推 ",
                "text": ": 按照陳吉仲的邏輯 該禁氫氟酸囉"
            },
            {
                "push": "→ ",
                "text": ": 廠方第一時間內並沒有用六氟靈沖洗-->這工"
            },
            {
                "push": "→ ",
                "text": ": 安零分吧！？"
            }
        ]
    }
]