[
    {
        "title": "台幹爆被迫返中 廣達：自主選擇",
        "date": "2020/02/17",
        "content": "1.媒體來源:蘋果日報   2.記者署名 【吳國仲╱台北報導】  3.完整新聞標題:  台幹爆被迫返中 廣達：自主選擇   4.完整新聞內文:  【吳國仲╱台北報導】武漢肺炎疫情持續升溫，台廠多開放中國台幹暫留台灣上班，但《 蘋果》接獲廣達（2382）員工投訴，稱常駐台幹沒有其它選擇只能返回中國，公司漠視員 工健康及生命安全，並爆料上海廠已暫停招聘新人。 廣達駁斥投訴非事實，公司對外派中國員工也有提供替代方案，可以留在台灣上班，並強 調這些台灣幹部及員工，基於責任心與職責所在，自主回歸駐地的參與率很高，公司力挺 員工可「自主選擇」是否回駐地。 廣達指，中國廠10日起復工，生產端重要台灣員工，為確認復工仍需至現場指揮調度，這 部分無法靠遠距溝通取代。廣達在中國生產基地主要位於上海、重慶及常熟，目前按階段 重啟生產，各廠區都依先前SARS規格防疫。    5.完整新聞連結 (或短網址):  https://tw.appledaily.com/finance/20200216/VPVBDUXJXVZBFUWAHCFFPBS3UE/   6.備註:  蘋果日報記者，你們到底會不會寫新聞ㄚ！！！   並強調這些台灣幹部及員工，基於責任心與職責所在，自主回歸駐地的參與率很高，  並強調這些台奴和台勞們， 基於「烤雞需求」與「怕被FIRE」，自主回歸集中營比例很高   ",
        "comment": [
            {
                "push": "推 ",
                "text": ": 資方說自主選擇 你敢不從？"
            },
            {
                "push": "推 ",
                "text": ": 好公司"
            },
            {
                "push": "→ ",
                "text": ": 抵制香肉醬"
            },
            {
                "push": "推 ",
                "text": ": 你們要自立自強 自己跟老闆說"
            },
            {
                "push": "推 ",
                "text": ": 誰敢不去"
            },
            {
                "push": "推 ",
                "text": ": 老闆說你自主就自主 不爽不要幹"
            },
            {
                "push": "→ ",
                "text": ": 不爽不要幹"
            },
            {
                "push": "推 ",
                "text": ": 豬瘟都拿去做肉醬"
            },
            {
                "push": "噓 ",
                "text": ": 可憐吶"
            },
            {
                "push": "推 ",
                "text": ": 別人家的小孩死不完，看那家人性化帶人帶槍"
            },
            {
                "push": "→ ",
                "text": ": 投靠，"
            },
            {
                "push": "推 ",
                "text": ": 自己選的工作，後果自己承擔"
            },
            {
                "push": "→ ",
                "text": ": 就業自由 懂？"
            },
            {
                "push": "→ ",
                "text": ": 都嘛自願加班、自願返工的"
            },
            {
                "push": "→ ",
                "text": ": 最嚴重也是自願離職的"
            },
            {
                "push": "噓 ",
                "text": ": 委屈就辭職，跑過去又在該"
            },
            {
                "push": "→ ",
                "text": ": 被自願"
            },
            {
                "push": "推 ",
                "text": ": 反正老闆可以放大絕，不爽不要做"
            }
        ]
    },
    {
        "title": "上海力挺 廣達上海廠已有近2萬名員工回到",
        "date": "2020/02/11",
        "content": " 1.媒體來源: 聯合報  2.記者署名 記者林則宏  3.完整新聞標題: 上海力挺 廣達上海廠已有近2萬名員工回到生產線  4.完整新聞內文: 廣達集團上海生產製造基地—廣達上海製造城，10日已經有三分之二的員工返回工作崗位。 中共上海市委常委鄭鋼淼10日下午專程前往視察，肯定廣達能按有關規定嚴格做好疫情防控 工作。鄭鋼淼並呼籲台資企業都能共同努力，做到防疫、生產兩不誤。  根據上海市台灣同胞投資企業協會發布的新聞，鄭鋼淼10日下午前往廣達集團上海製造城視 察，並在現場召開部分台商座談會，聽取台資企業負責人關於企業疫情防控及復工復產情況 彙報，分析當前疫情對台企的影響，研商幫助台企紓困解難的途徑和辦法。  廣達上海製造城員工達3萬多人，10日開工首日就已經有近2萬名員工復工上崗。  新聞稿稱，鄭鋼淼在黃廣達集團中國製造總部董事黃健堂陪同下，參觀生產線及部分辦公區 域，充分肯定廣達集團按照有關規定嚴格做好疫情防控工作，超前儲備企業復產所需口罩、 消毒水等防護物資等有效措施，鼓勵企業克服困難，穩定預期，增強信心，為支援上海社會 經濟發展作出應有貢獻。  鄭鋼淼表示，在當前疫情防控的關鍵階段，要堅決貫徹落實中共總書記習近平重要講話精神 ，因地因時因業施策，全力確保企業有序復工復產。上海市政府近期已發布「上海市全力防 控疫情支援服務企業平穩健康發展的若干政策措施」，針對當下企業發展實際困難，給予相 關政策支援。  上海市台辦主任李文輝表示，據不完全統計，截至2月9日，上海台胞、台企累計向湖北武漢 等地捐款捐物人民幣4,600多萬元，他感謝廣大台胞、台商與大陸一起共抗疫情。  李文輝也呼籲台資企業，在復工復產過程中要嚴格按照有關要求，落實企業主體責任，做好 疫情防控和安全生產，有序復工復產化危為機，提高轉型升級能力，增強企業市場競爭力。   5.完整新聞連結 (或短網址): https://udn.com/news/story/7332/4337457?from=udn-ch1_breaknews-1-0-news  6.備註:  -- 皇民表示:  ",
        "comment": [
            {
                "push": "推 ",
                "text": ": 慣老闆的驕傲"
            },
            {
                "push": "噓 ",
                "text": ": 板凳坐好等看戲"
            },
            {
                "push": "噓 ",
                "text": ": 肉鬆不意外"
            },
            {
                "push": "→ ",
                "text": ": 要不然叫誰復工？"
            },
            {
                "push": "→ ",
                "text": ": 武漢肺炎 第二季？"
            },
            {
                "push": "噓 ",
                "text": ": 先 rip , 不謝"
            },
            {
                "push": "→ ",
                "text": ": 看起來中國許多地方已經獨立分治 不鳥中央"
            },
            {
                "push": "→ ",
                "text": ": 了"
            },
            {
                "push": "推 ",
                "text": ": 看著14天後...."
            },
            {
                "push": "→ ",
                "text": ": 恥骨被點了"
            },
            {
                "push": "→ ",
                "text": ": 海巴子做到發病  直接推去燒  再補新的人力"
            },
            {
                "push": "→ ",
                "text": ": 就好  這樣？"
            },
            {
                "push": "推 ",
                "text": ": 祝上海大爆發"
            },
            {
                "push": "推 ",
                "text": ": 產品會不會留有病毒"
            }
        ]
    },
    {
        "title": "廣達法說〉看好量子電腦未來發展",
        "date": "2019/11/14",
        "content": "1.媒體來源: 鉅亨網  2.記者署名 記者劉韋廷  3.完整新聞標題: 〈廣達法說〉看好量子電腦未來發展 將帶動雲端伺服器成長  4.完整新聞內文: 廣達 (2382-TW) 今 (13) 日舉辦法說會，對於市場傳出將放棄代工穿戴式裝置，廣達重 申不評論市場傳聞，強調每一項產品都會經過審慎評估，另一方面，廣達也看好未來 10 年量子電腦發展，可望帶動雲端伺服器需求提升。  副董事長梁次震表示，對於市場傳出將放棄代工穿戴式裝置，廣達並沒有說要退出或放棄 穿戴式市場，對每一樣產品都將審慎評估，只要有獲益的都不會放棄。  隨著 IBM、Google 近期提出量子電腦的願景，廣達董事長林百里表示，預期 10 年內世 界可能就會進入量子電腦時代，由於運算更加複雜，需要接收的資料也更多，將有利廣達 在雲端的發展。  Google 日前在《Nature》發表一篇論文指出，可以在真實世界系統裡實現量子加速  (Quantum speedup)，對於目前超級電腦需要約 1 萬年才能計算出來的答案，量子電腦 僅需 200 秒就能完成。  面對未來科技發展，林百里表示，將帶領廣達扮演好研發型公司的角色，他也再次強調， 未來科技是一架飛機，將由雲端、AI、5G、物聯網推動，並不容易受總體經濟影響，預期 未來幾年 AI、5G 將成為大國在國防、國力的競爭項目，也看好智慧製造、智慧醫療、智 慧城市發展上，仍有很大的發展空間、待突破的技術。  5.完整新聞連結 (或短網址): https://news.cnyes.com/news/id/4411863  6.備註:    不過台灣代工的系統廠商能做什麼??    目前量子電腦技術還沒定案  國外大廠各玩各的    更別說量產  就算是在數位時代呼風喚雨的台積電  將來也未必能吃到這塊    台灣能做些什麼????      ",
        "comment": [
            {
                "push": "→ ",
                "text": ": 肉鬆"
            },
            {
                "push": "推 ",
                "text": ": 股價都漲20%了  管它做什麼"
            },
            {
                "push": "→ ",
                "text": ": 好想拿量子電腦玩踩地雷。"
            },
            {
                "push": "推 ",
                "text": ": 要找林百里這種香港人來台灣比較好，不"
            },
            {
                "push": "→ ",
                "text": ": 要找那種只會街頭鬧事的~~"
            },
            {
                "push": "推 ",
                "text": ": 廣達鴻海 支持"
            },
            {
                "push": "→ ",
                "text": ": 廣達是以為quantum跟quanta很接近"
            },
            {
                "push": "→ ",
                "text": ": 可以炒一波嗎"
            },
            {
                "push": "噓 ",
                "text": ": 靠腰。 他大概連量子電腦是啥都不知道"
            },
            {
                "push": "→ ",
                "text": ": 說真的 全台灣有幾個人懂量子力學？"
            },
            {
                "push": "→ ",
                "text": ": 他又不是要做量子電腦"
            }
        ]
    },
    {
        "title": "廣達香肉醬可以怎麼吃？",
        "date": "2019/07/30",
        "content": "這個廣達香肉醬 新東陽肉醬  臺糖辣肉醬是本宅最愛  通常我都是煮一鍋麵  放半罐肉醬  就可以吃了  如果要補蔬菜就買個高麗菜下去燙一下 超鮮脆  也可以煮成乾麵  弄個蘑菇醬和肉醬炒一炒拌麵也不賴  你們咧  ",
        "comment": [
            {
                "push": "→ ",
                "text": ": 自問自答廢文"
            },
            {
                "push": "推 ",
                "text": ": 求內推"
            },
            {
                "push": "推 ",
                "text": ":  https://i.imgur.com/q4iwWdz.jpg"
            },
            {
                "push": "噓 ",
                "text": ": 丟掉 打電話叫披薩"
            },
            {
                "push": "→ ",
                "text": ": 補"
            },
            {
                "push": "噓 ",
                "text": ": 補"
            },
            {
                "push": "推 ",
                "text": ": 問一下子路肉醬怎麼吃比較好"
            },
            {
                "push": "→ ",
                "text": ": 你跟我媽一樣 她也是廣達香加高麗菜加麵"
            },
            {
                "push": "→ ",
                "text": ": 你想暗示什麼"
            },
            {
                "push": "→ ",
                "text": ": 我覺得她廚藝超厲害 能把食材跳過食物階段"
            },
            {
                "push": "→ ",
                "text": ": 所以我從來不吃她煮的東西"
            },
            {
                "push": "推 ",
                "text": ": 炒豆腐變麻婆豆腐"
            },
            {
                "push": "推 ",
                "text": ": 飯糰 蛋餅"
            },
            {
                "push": "推 ",
                "text": ": 吐司夾肉醬"
            },
            {
                "push": "→ ",
                "text": ": 白飯用了很好吃"
            },
            {
                "push": "→ ",
                "text": ": 先用廣達代工的NB加熱再吃"
            },
            {
                "push": "推 ",
                "text": ": 廣達 香肉 醬"
            },
            {
                "push": "推 ",
                "text": ": 香肉"
            },
            {
                "push": "→ ",
                "text": ": 狗狗路過廣達，嚇到挫屎尿"
            },
            {
                "push": "→ ",
                "text": ": 沒空"
            },
            {
                "push": "推 ",
                "text": ": 廣達香肉醬配白飯比煮麵好吃"
            },
            {
                "push": "→ ",
                "text": ": 煮麵用維力的炸醬比較搭"
            }
        ]
    },
    {
        "title": "蘋果新款Mac Pro臺式電腦交廣達中國大陸工廠代工 ",
        "date": "2019/06/29",
        "content": "路透社援引華爾街日報消息  蘋果已與代工廠廣達電腦(Quanta Computer Inc.)接洽  討論生產售價達6000美元的新款Mac Pro臺式電腦  將其交給廣達在上海附近的一家工廠代工  認為Mac Pro從美國組裝  變為中國的組裝將有助於降低運輸成本  對此消息廣達拒絕置評  蘋果的一名發言人則回應稱  新款Mac Pro也是在加州設計  零部件來自包括美國在內的多個國家  最終組裝只是生產過程的一部分  據統計蘋果公司總收入的近18%來自大中華區  -- UltraSeven  : 人民幣貶到19 只是這1-2年的問題而已...         2019/05/29 07:28  ",
        "comment": [
            {
                "push": "→ ",
                "text": ": 6000美元=="
            },
            {
                "push": "→ ",
                "text": ": 爆掛?"
            },
            {
                "push": "推 ",
                "text": ": 組裝而已啊，毛三到四"
            },
            {
                "push": "→ ",
                "text": ": all in 廣達"
            },
            {
                "push": "→ ",
                "text": ": 舊聞了"
            },
            {
                "push": "推 ",
                "text": ": 那糞蘋果是不是該大降價了 把錢還消費者了"
            },
            {
                "push": "推 ",
                "text": ": 6000鎂 5700鎂信仰XD"
            },
            {
                "push": "→ ",
                "text": ": 6000很便宜 趕快買10台"
            },
            {
                "push": "推 ",
                "text": ": 沒差吧 這台升級變廢物 哪組裝都垃圾"
            },
            {
                "push": "噓 ",
                "text": ": 台式電腦是殺小 支那用語"
            },
            {
                "push": "噓 ",
                "text": ": 台式？"
            },
            {
                "push": "噓 ",
                "text": ": 台哩老木"
            },
            {
                "push": "→ ",
                "text": ": 台灣從不是中華人民共和國的一部分!"
            },
            {
                "push": "→ ",
                "text": ": TWofPRC 你媽給狗幹得正爽嗎?"
            }
        ]
    },
    {
        "title": "WSJ:蘋果新Mac Pro移往中國交由廣達生產",
        "date": "2019/06/29",
        "content": "看到 Mac Pro 那精美的價格  一年產量肯定少的可憐  移出美國肯定對蘋果來說不痛不癢  五毛果然就是五毛  看到這個也可以扯川普  醒醒吧 那玩意兒不是賣給每天領五毛的低收入戶的  ※ 引述《kusowan (你感受一下)》之銘言： : https://ec.ltn.com.tw/article/breakingnews/2837164 : 豬油 : 〔財經頻道／綜合報導〕蘋果（Apple）先前傳出為避免生產過度集中在中國、受到川 普? : 此外，《華爾街日報》也指出，這個消息正巧是在蘋果位於德州的桌機代工廠Flex補貼 結 : 川普表示 : 嘻嘻  ",
        "comment": []
    },
    {
        "title": "WSJ:蘋果新Mac Pro移往中國交由廣達生產",
        "date": "2019/06/29",
        "content": "https://ec.ltn.com.tw/article/breakingnews/2837164  豬油  〔財經頻道／綜合報導〕蘋果（Apple）先前傳出為避免生產過度集中在中國、受到川普全面關稅打擊，正評估將15%到30%產能從中國轉移到東南亞，且已要求供應商評估相關成本。而《華爾街日報》指出，有知情人士透露蘋果桌機新Mac Pro製造將從美國移往中國，由筆電MacBook主力代工廠廣達承包。  報導稱，新Mac Pro將由廣達在上海廠生產，並已加大產量，由於該廠位置距離其他蘋果的亞洲供應商較近，可望降低零件運輸成本。蘋果發言人則表示，新Mac Pro像其他產品一樣，在加州設計和製造，成品會包含來自美國、其他多國的零組件。 此外，《華爾街日報》也指出，這個消息正巧是在蘋果位於德州的桌機代工廠Flex補貼結束後傳出。廣達尚未回應路透的評論要求。  金融機構D.A. Davidson分析師Tom Forte認為，蘋果對美、中能達成貿易協議，看起來十分有信心；反之也可能是暗示，相較之下中國現有的環境、設施益處遠大於在美國重新建立供應鏈或生產線，「中國製造」仍然是成本較低的方案之一。  川普表示  嘻嘻  -- https://i.imgur.com/cWfSYwz.png  ",
        "comment": [
            {
                "push": "→ ",
                "text": ": 庫克再亂搞小心蘋果掉下來"
            },
            {
                "push": "推 ",
                "text": ": 廣達全下"
            },
            {
                "push": "推 ",
                "text": ": 不夠潮 拒買"
            },
            {
                "push": "推 ",
                "text": ": 所以郭董說G20結束 贏一半也輸一半"
            },
            {
                "push": "噓 ",
                "text": ": 中國製造2.0"
            },
            {
                "push": "推 ",
                "text": ": 超級潮嘔嘔嘔嘔嘔"
            },
            {
                "push": "→ ",
                "text": ": 的確還是MIC 但卻不是鴻海單"
            },
            {
                "push": "→ ",
                "text": ": 廣達股價才剛有起色"
            },
            {
                "push": "噓 ",
                "text": ": 要被抵制了"
            },
            {
                "push": "推 ",
                "text": ": 庫克會搞死蘋果"
            },
            {
                "push": "→ ",
                "text": ": 川普真是滿手好牌打到輸，笑死"
            },
            {
                "push": "推 ",
                "text": ": 郭台銘神預言"
            },
            {
                "push": "→ ",
                "text": ": 蘋果桌機新Mac Pro製造將從美國移往中"
            },
            {
                "push": "→ ",
                "text": ": 國？？"
            },
            {
                "push": "→ ",
                "text": ": MIC不潮 不買"
            },
            {
                "push": "→ ",
                "text": ": 廣達不是要撤了嗎"
            },
            {
                "push": "→ ",
                "text": ": 聽說是習維尼跪舔我川，才會這樣。席維"
            },
            {
                "push": "→ ",
                "text": ": 尼舔功一流"
            },
            {
                "push": "推 ",
                "text": ": 不就吸收25%關稅還是比較便宜的意思"
            },
            {
                "push": "推 ",
                "text": ": 這跟川普有啥關係，Mac Pro 一年的"
            },
            {
                "push": "→ ",
                "text": ": 產量才幾台，移出美國根本不痛不癢"
            },
            {
                "push": "噓 ",
                "text": ": 覺青要拒買啦！氣死了"
            },
            {
                "push": "→ ",
                "text": ": 出貨文"
            },
            {
                "push": "推 ",
                "text": ": 向下"
            }
        ]
    },
    {
        "title": "天氣女孩Mini下嫁廣達少東 林百里兒子",
        "date": "2019/05/22",
        "content": "「天氣女孩」下嫁廣達少東 林百里兒子娶了這位女星  資產高達37億美金的廣達集團林百里小兒子林宇輝傳出喜訊，今年38歲的他本月中和女友 求婚成功，而他的另一半正是成擔任歌手的天氣女孩成員之一的Mini林怡慧。據鏡周刊報 導，低調的林宇輝突然在臉書公開求婚喜訊，還秀出大鑽戒讓林的友人都十分詫異。  據鏡周刊報導，林與揮汗林怡慧是因工作認識，林怡慧3年前就已退團，兩人交往後十分 低調，林宇輝也未在父親林百里的廣達集團任職，而是自行成立娛樂和網路公司，因此才 認識林怡慧，兩人在臉書秀出求婚影片，女方也大方say yes 。 https://i.imgur.com/jlrsIuz.jpg  https://stars.udn.com/star/story/10091/3827103  -- 當然say yes難道跟$$ say no?  話說mini 情史不是很豐富  ",
        "comment": [
            {
                "push": "推 ",
                "text": ": 回"
            },
            {
                "push": "→ ",
                "text": ": $"
            },
            {
                "push": "→ ",
                "text": ": linchiling.rar"
            },
            {
                "push": "→ ",
                "text": ": 下嫁一詞是這樣用的？"
            },
            {
                "push": "推 ",
                "text": ": 倪福德?"
            },
            {
                "push": "推 ",
                "text": ": $$$$$$"
            },
            {
                "push": "推 ",
                "text": ": 嫁給廣達少東算\"下嫁\"? 這用詞怪怪的吧"
            },
            {
                "push": "噓 ",
                "text": ": 下嫁? 我還以為下嫁這詞是指女方條件比較好"
            },
            {
                "push": "推 ",
                "text": ": 這叫下嫁???"
            },
            {
                "push": "推 ",
                "text": ": 潮吹了"
            },
            {
                "push": "推 ",
                "text": ": $ay ye$"
            },
            {
                "push": "推 ",
                "text": ": 有錢，啥事都好辦，羨慕推"
            },
            {
                "push": "→ ",
                "text": ": 是跟魔幻力量那一位嗎？"
            },
            {
                "push": "推 ",
                "text": ": 小時不讀書 長大當XX"
            },
            {
                "push": "推 ",
                "text": ": 貓好可愛 那個肥肥的貓掌"
            },
            {
                "push": "→ ",
                "text": ": 這種臉白是"
            },
            {
                "push": "→ ",
                "text": ": 下嫁 ？"
            },
            {
                "push": "→ ",
                "text": ": 這叫高攀吧"
            },
            {
                "push": "推 ",
                "text": ": 這種大型企業不是都政治聯姻比較多嗎？好奇女生家世背"
            },
            {
                "push": "→ ",
                "text": ": Mini很正耶，天氣女孩唯一記住的，不過先前也有土地婆綽號"
            },
            {
                "push": "推 ",
                "text": ": 林與揮汗是殺小啦"
            },
            {
                "push": "推 ",
                "text": ": 呃 求婚會失敗ㄇ"
            },
            {
                "push": "推 ",
                "text": ": $$$$$$$$$$$$$$$$$$$$$$$$$$$$$$$$$$$$"
            },
            {
                "push": "→ ",
                "text": ": 林與揮汗林怡慧"
            },
            {
                "push": "→ ",
                "text": ": 真愛,羨慕"
            },
            {
                "push": "→ ",
                "text": ": 下架"
            },
            {
                "push": "→ ",
                "text": ": 攀上比較好一點"
            },
            {
                "push": "噓 ",
                "text": ": 記者素質真的越來越低了"
            },
            {
                "push": "→ ",
                "text": ": 以前土地公女朋友"
            },
            {
                "push": "→ ",
                "text": ": 看成廣東少東"
            },
            {
                "push": "推 ",
                "text": ": “成”擔任歌手是三小"
            },
            {
                "push": "噓 ",
                "text": ": 下巴"
            },
            {
                "push": "推 ",
                "text": ": 下嫁是比林百里他們家還有錢跟地位還高吧 用下嫁XD"
            },
            {
                "push": "推 ",
                "text": ": $$$$$$$$"
            },
            {
                "push": "推 ",
                "text": ": 男生看起來很宅不太會玩"
            },
            {
                "push": "→ ",
                "text": ": 爸爸情場殺手怎麼兒子這麼老實"
            },
            {
                "push": "推 ",
                "text": ": 揮汗 記者真好當"
            },
            {
                "push": "推 ",
                "text": ": 天氣女孩工作很敬業的，恭喜。應該用郎才女貌吧，下嫁是"
            },
            {
                "push": "推 ",
                "text": ": 土地公前女友"
            },
            {
                "push": "→ ",
                "text": ": 啥爛形容詞。"
            },
            {
                "push": "→ ",
                "text": ": 這篇新聞才幾個字 錯字連篇XDD"
            },
            {
                "push": "推 ",
                "text": ": $$$$$$$$$$$$$$$$$$$$$$$$$$$$$$$$"
            },
            {
                "push": "推 ",
                "text": ": 這記者是用手機打文章喔...林與揮汗是三小?"
            },
            {
                "push": "→ ",
                "text": ": 土地公畢竟不敵林百里兒"
            },
            {
                "push": "推 ",
                "text": ": 有點醜"
            },
            {
                "push": "推 ",
                "text": ": 土地公的形狀 大家都知道的事"
            },
            {
                "push": "推 ",
                "text": ": 女權阿  女生一定用下嫁"
            },
            {
                "push": "→ ",
                "text": ": 新聞連結沒有這篇新聞??被和諧了??"
            },
            {
                "push": "→ ",
                "text": ": 天氣女孩 沒聽過"
            },
            {
                "push": "推 ",
                "text": ": 記者國文不及格不是常識嗎"
            },
            {
                "push": "噓 ",
                "text": ": 這不是同婚嗎？ 同姓結婚"
            },
            {
                "push": "→ ",
                "text": ": 林與揮汗 哈哈哈在寫什麼"
            },
            {
                "push": "噓 ",
                "text": ": 這什麼爛新聞稿？記者丟不丟臉啊"
            },
            {
                "push": "推 ",
                "text": ": $$$$$$$$$$$$$$$$$$$真愛無誤$$$$$$$$$$$$$$$$$$$$$$$$$"
            },
            {
                "push": "噓 ",
                "text": ": 算回收大成功嗎？"
            },
            {
                "push": "→ ",
                "text": ": 倪福德"
            },
            {
                "push": "推 ",
                "text": ": 真假？土地公前女友？"
            },
            {
                "push": "→ ",
                "text": ": 小蜜桃..."
            },
            {
                "push": "推 ",
                "text": ": 下嫁這個字是這樣用的 國文老師從國中就翹課了?"
            },
            {
                "push": "噓 ",
                "text": ": 還求婚咧 還下嫁咧   這女的是比爾蓋茲的女兒嗎"
            },
            {
                "push": "→ ",
                "text": ": 錯字太誇張了吧"
            },
            {
                "push": "推 ",
                "text": ": 現在的記者...唉"
            },
            {
                "push": "噓 ",
                "text": ": 記者的國文程度真的ㄏ"
            },
            {
                "push": "推 ",
                "text": ": 揮汗"
            },
            {
                "push": "→ ",
                "text": ": 這麼有錢結果娶個34歲的?????"
            },
            {
                "push": "→ ",
                "text": ": 誰"
            },
            {
                "push": "噓 ",
                "text": ": 下架是三小"
            },
            {
                "push": "推 ",
                "text": ": 真愛"
            },
            {
                "push": "噓 ",
                "text": ": 下嫁?? 這記者國文程度???"
            },
            {
                "push": "→ ",
                "text": ": 下嫁、正是成擔任歌手、林與揮汗林怡慧"
            },
            {
                "push": "推 ",
                "text": ": 誰是土地公?"
            },
            {
                "push": "推 ",
                "text": ": 天氣女孩這團是啥時出的?"
            },
            {
                "push": "噓 ",
                "text": ": 聯合報 記者楊起鳳"
            },
            {
                "push": "推 ",
                "text": ": 真愛"
            },
            {
                "push": "→ ",
                "text": ": 倪福德"
            },
            {
                "push": "推 ",
                "text": ": 土地公+MINI餵狗就好了"
            },
            {
                "push": "推 ",
                "text": ": 這麼有錢還回收職棒球員的女友"
            },
            {
                "push": "噓 ",
                "text": ": 辦文學獎的報社耶,出這種報導?"
            },
            {
                "push": "→ ",
                "text": ": 真的耶 土地公前女友 好久囉"
            },
            {
                "push": "→ ",
                "text": ": 說真的 哪個女的不是誰誰誰的前女友... 處男才在意這個"
            },
            {
                "push": "推 ",
                "text": ": 好羨慕"
            },
            {
                "push": "→ ",
                "text": ": 職棒球員都很猛又壯又持久這少東ok嗎"
            },
            {
                "push": "→ ",
                "text": ": 校稿的是怎樣  國文很糟喔 下嫁這詞用錯了吧"
            },
            {
                "push": "→ ",
                "text": ": mini boo de geneki"
            },
            {
                "push": "噓 ",
                "text": ": 下嫁???"
            },
            {
                "push": "噓 ",
                "text": ": 下嫁？"
            },
            {
                "push": "推 ",
                "text": ": 土地公 倪福德 中職富邦擔任終結者"
            },
            {
                "push": "→ ",
                "text": ": 有貓有推"
            },
            {
                "push": "→ ",
                "text": ": 嫁毛利1.41%的…"
            },
            {
                "push": "→ ",
                "text": ": 下嫁??所以家境比少東好??"
            },
            {
                "push": "推 ",
                "text": ": 不是土地公不敵小開吧...女生當時也很死心蹋地倪"
            },
            {
                "push": "推 ",
                "text": ": 下巴"
            },
            {
                "push": "推 ",
                "text": ": 錢比威猛重要"
            },
            {
                "push": "噓 ",
                "text": ": 下架"
            },
            {
                "push": "推 ",
                "text": ": 上架"
            },
            {
                "push": "→ ",
                "text": ": 也是拉 年輕找猛的 老了找穩的"
            },
            {
                "push": "噓 ",
                "text": ": 下嫁?"
            },
            {
                "push": "→ ",
                "text": ": 下嫁"
            },
            {
                "push": "噓 ",
                "text": ": 現在記者有夠好當  不用查證  用字遣詞不當 錯字連篇"
            },
            {
                "push": "噓 ",
                "text": ": 下嫁和揮汗3洨 智障ㄇ"
            },
            {
                "push": "噓 ",
                "text": ": 下嫁是三小？明明就高攀"
            },
            {
                "push": "推 ",
                "text": ": 倪福德前女友欸..."
            },
            {
                "push": "推 ",
                "text": ": 倪QQ"
            },
            {
                "push": "推 ",
                "text": ": 新台幣下架"
            },
            {
                "push": "→ ",
                "text": ": 下嫁？記者國文真棒"
            },
            {
                "push": "推 ",
                "text": ": 隨便打篇文上去都不用再看一遍也不用第二人看過喔"
            },
            {
                "push": "→ ",
                "text": ": ye$"
            },
            {
                "push": "噓 ",
                "text": ": 沒在校稿的 可撥"
            },
            {
                "push": "推 ",
                "text": ": 吃棒不一定有錢 有錢不用擔心吃不到棒"
            },
            {
                "push": "推 ",
                "text": ": $$$$$$$"
            },
            {
                "push": "推 ",
                "text": ": 下嫁就這樣用R 求你嫁 很難懂嗎"
            },
            {
                "push": "推 ",
                "text": ": 記者懂下嫁的意思嗎"
            },
            {
                "push": "→ ",
                "text": ": 結婚通常以女方為大 這是禮貌禮儀"
            },
            {
                "push": "推 ",
                "text": ": 上架"
            },
            {
                "push": "→ ",
                "text": ": 不然說爽到了嫁到金龜婿膩"
            },
            {
                "push": "噓 ",
                "text": ": 明明就高攀！情史豐富...甚麼嘛~少東原來也是回收業者"
            },
            {
                "push": "噓 ",
                "text": ": 下巴墊的也太怪了吧...而且跟天氣女孩時照片不一樣啊."
            },
            {
                "push": "噓 ",
                "text": ": 揮汗？？"
            },
            {
                "push": "推 ",
                "text": ": 人家是女神欸當然是下嫁"
            },
            {
                "push": "推 ",
                "text": ": 哈哈哈哈   下半身換下半生~~"
            },
            {
                "push": "推 ",
                "text": ": 笑死 有過男友就回收 XDDDDD"
            },
            {
                "push": "噓 ",
                "text": ":"
            },
            {
                "push": "→ ",
                "text": ": 高攀吧!!!"
            },
            {
                "push": "推 ",
                "text": ": 下巴可以當釘子了"
            },
            {
                "push": "推 ",
                "text": ": 下嫁 XDDD"
            },
            {
                "push": "噓 ",
                "text": ": 娶別人用過的難道不是回收?  更何況她還交那麼多個"
            },
            {
                "push": "噓 ",
                "text": ": 記者真的很北七！到底懂不懂下嫁是什麼意思？"
            },
            {
                "push": "推 ",
                "text": ": 天氣女孩最正的是Yumi好嗎"
            },
            {
                "push": "→ ",
                "text": ": 高攀還是下嫁搞清楚再說"
            },
            {
                "push": "→ ",
                "text": ": 出嫁 婚嫁 都可以偏偏 用下嫁 XDD"
            },
            {
                "push": "→ ",
                "text": ": 錯字 選字也不會 整篇急著亂寫附奶圖腿圖騙點閱就是現今臺灣"
            },
            {
                "push": "→ ",
                "text": ": 垃圾媒體的悲哀"
            },
            {
                "push": "噓 ",
                "text": ": 下嫁"
            },
            {
                "push": "噓 ",
                "text": ": $$$$$$$"
            },
            {
                "push": "推 ",
                "text": ": 記者你的國文很差呢，詞用錯字打錯！"
            },
            {
                "push": "噓 ",
                "text": ": 上嫁吧"
            },
            {
                "push": "噓 ",
                "text": ": 錯字也太多XD"
            },
            {
                "push": "→ ",
                "text": ": 我看成廣東少林"
            },
            {
                "push": "推 ",
                "text": ": 下嫁不是這樣用的~查一下字典或GOOGLE吧"
            },
            {
                "push": "推 ",
                "text": ": 林與揮汗林怡慧是因工作認識，記者..."
            },
            {
                "push": "推 ",
                "text": ": Yes矮肚！不用工作爽當貴婦☺"
            },
            {
                "push": "噓 ",
                "text": ": 連結不見了QQ"
            },
            {
                "push": "噓 ",
                "text": ": 記者素質"
            },
            {
                "push": "噓 ",
                "text": ": 下嫁？他麻的這種素質難怪被酸"
            },
            {
                "push": "→ ",
                "text": ": $$"
            },
            {
                "push": "→ ",
                "text": ": 高攀"
            },
            {
                "push": "→ ",
                "text": ": 下嫁喔？女方背景這麼深厚～"
            },
            {
                "push": "推 ",
                "text": ": 下嫁，顧名思義，即地位高的嫁給地位低的"
            },
            {
                "push": "→ ",
                "text": ": 下嫁 XDD  林百里家是有多「下」？"
            },
            {
                "push": "推 ",
                "text": ": 前土地婆？"
            },
            {
                "push": "推 ",
                "text": ": 照片那下巴可以殺夫耶 超尖的"
            },
            {
                "push": "→ ",
                "text": ": 還有「成」擔任歌手是啥小？小學注音沒學好逆？"
            },
            {
                "push": "噓 ",
                "text": ": 下嫁？？？ ？？"
            },
            {
                "push": "→ ",
                "text": ": 真愛"
            },
            {
                "push": "推 ",
                "text": ": $$$$"
            },
            {
                "push": "→ ",
                "text": ": 價高者得"
            },
            {
                "push": "→ ",
                "text": ": 下嫁.....XD"
            },
            {
                "push": "噓 ",
                "text": ": 記者連詞意都搞不懂！ 馬的什麼世道"
            },
            {
                "push": "推 ",
                "text": ": 土地婆 超正的"
            },
            {
                "push": "推 ",
                "text": ": 下嫁？"
            },
            {
                "push": "→ ",
                "text": ": 淋雨揮汗"
            },
            {
                "push": "→ ",
                "text": ": mini好像在經營寵物旅館？"
            },
            {
                "push": "噓 ",
                "text": ": 修圖到以為跟外星人結婚"
            },
            {
                "push": "噓 ",
                "text": ": 下個屁d能記者"
            },
            {
                "push": "推 ",
                "text": ": 揮汗"
            },
            {
                "push": "→ ",
                "text": ": 塑膠味"
            },
            {
                "push": "推 ",
                "text": ": 上進，孝順！"
            },
            {
                "push": "推 ",
                "text": ": 下嫁？？？誰高誰低還不知道呢"
            },
            {
                "push": "推 ",
                "text": ": 下架XD"
            },
            {
                "push": "推 ",
                "text": ": 為了新台幣下嫁"
            },
            {
                "push": "推 ",
                "text": ": $$$$$$$$$$"
            },
            {
                "push": "噓 ",
                "text": ": 下嫁？ 蛤？"
            },
            {
                "push": "推 ",
                "text": ": 有沒有校稿啦淦"
            },
            {
                "push": "推 ",
                "text": ": 高攀還是下嫁 搞清楚"
            },
            {
                "push": "噓 ",
                "text": ": 要不要去查一下字典什麼叫「下嫁」？"
            },
            {
                "push": "噓 ",
                "text": ": 下嫁？？記者智商正常發揮"
            },
            {
                "push": "推 ",
                "text": ": 下嫁你阿罵，高攀才對吧"
            },
            {
                "push": "→ ",
                "text": ": 下嫁？？"
            },
            {
                "push": "→ ",
                "text": ": 新聞網頁消失了耶.....有人發現這事嗎?"
            },
            {
                "push": "推 ",
                "text": ": 記者大概被長官罵裁撤下新聞巴 當林百里看不到這新聞？"
            },
            {
                "push": "→ ",
                "text": ": 過氣歌手嫁給台灣前10富翁兒子叫做下嫁 中文老師在哭"
            },
            {
                "push": "推 ",
                "text": ": 下嫁有錯嗎"
            },
            {
                "push": "噓 ",
                "text": ": 下巴怎回事"
            },
            {
                "push": "→ ",
                "text": ": 下降？"
            },
            {
                "push": "推 ",
                "text": ": 小時不讀書 長大當記者"
            },
            {
                "push": "噓 ",
                "text": ": 其實沒消失  改內文錯字而已"
            },
            {
                "push": "→ ",
                "text": ": https://reurl.cc/3pODM"
            },
            {
                "push": "→ ",
                "text": ": 標題內文錯字一堆  記者智商滿分"
            },
            {
                "push": "→ ",
                "text": ": 下嫁...??"
            },
            {
                "push": "→ ",
                "text": ": 下嫁? 下架?"
            },
            {
                "push": "→ ",
                "text": ": 下嫁不太對 下架很難聽"
            },
            {
                "push": "噓 ",
                "text": ": 那個貓咪都被美肌糊到沒毛了"
            },
            {
                "push": "噓 ",
                "text": ": 下嫁xdd"
            },
            {
                "push": "推 ",
                "text": ": 哇 這肯定是真愛阿"
            },
            {
                "push": "推 ",
                "text": ": 下嫁個雕 釣魚大成功才對"
            },
            {
                "push": "噓 ",
                "text": ": 悲哀的記者們 如果嫁給你們才叫下嫁"
            },
            {
                "push": "噓 ",
                "text": ": 下嫁？"
            },
            {
                "push": "→ ",
                "text": ": 上嫁"
            },
            {
                "push": "噓 ",
                "text": ": 下嫁？"
            },
            {
                "push": "推 ",
                "text": ": 一堆中國人的中文造詣深厚"
            },
            {
                "push": "推 ",
                "text": ": 這種程度也可以當記者 然後又怪大家瞧不起記者 呵呵"
            },
            {
                "push": "推 ",
                "text": ": 高高高高高高高高高攀吧"
            },
            {
                "push": "推 ",
                "text": ": https://reurl.cc/e7z1M"
            },
            {
                "push": "噓 ",
                "text": ": 下嫁ㄏㄏ"
            },
            {
                "push": "推 ",
                "text": ": 天氣女孩有好幾代"
            }
        ]
    },
    {
        "title": "林百里：廣達淨利率只剩1.41% 怎麼吸收25",
        "date": "2019/05/15",
        "content": "1.媒體來源: 聯合  2.記者署名 蕭君暉  3.完整新聞標題: 林百里：廣達淨利率只剩1.41% 怎麼吸收25%關稅？  4.完整新聞內文: 美中貿易戰來勢洶洶，筆電可能納入中國輸美產品25%的關稅清單中，廣達董事長林百里 今（14）日向品牌廠喊話，廣達2019年第1季的淨利率只有1.41%，怎麼去承擔？筆電毛利 率低，希望客人可以自行吸收關稅成本，更何況這些費用是進他們政府的口袋，代工廠也 沒有辦法。  廣達今天公布2019年第1季稅後純益31.24億元，年增14.22%，季減24.56%，第1季每股純 益（EPS）0.81元，第1季毛利率季增與年增，表現不錯，該公司預估，第2季筆電出貨量 季增20%，雲端伺服器產品全年出貨持續以兩位數字增長。  廣達2019年第1季進入淡季，營收2,213.3億元，季減30.11%、年增0.18%；毛利率4.47%， 則創近五季新高，季增0.37個百分點、年增0.29個百分點，廣達指出，主要是因非PC（例 如雲端伺服器）營收比重拉升所致，第1季非PC營收比重已達55%。  廣達2019年第1季營益率1.29%，季增0.14個百分點、年減0.04個百分點；稅後純益31.24 億元，季減24.56%、年增14.22%，每股純益0.81元。另外，董事會日前也宣布，去年盈餘 每股擬配現金股利3.55元，盈餘配發率91%。  廣達表示，雖受CPU缺貨、全球景氣轉弱、加上美中貿易戰影響，但廣達2018年第4季開始 調整營運，2019第1季獲利仍較去年小幅成長，林百里說，未來將持續朝雲端設備、消費 性AI（如筆電與智慧手表）、以及工業AI（如5G及運輸）等三大類產品開發邁進。  廣達2019年第1季筆電出貨量730萬台，季減24%，年減18%，該公司預估，第2季筆電出貨 量將季增20%，主要是第1季基期較低，至於雲端伺服器產品，2019年仍以兩位數字成長。  5.完整新聞連結 (或短網址): https://udn.com/news/story/7240/3812735  6.備註: 原來廣達淨利剩下1.多%  ",
        "comment": [
            {
                "push": "推 ",
                "text": ": 肉鬆好吃"
            },
            {
                "push": "→ ",
                "text": ": 血汗"
            },
            {
                "push": "推 ",
                "text": ": 毛利也太低了吧..."
            },
            {
                "push": "噓 ",
                "text": ": 社科院覺青：貿易戰只有支那遭殃"
            },
            {
                "push": "推 ",
                "text": ": 就不要賣到美國去不就得了"
            },
            {
                "push": "→ ",
                "text": ": 關我屁事"
            },
            {
                "push": "→ ",
                "text": ": 肉鬆王表示:"
            },
            {
                "push": "→ ",
                "text": ": 回台或去東南亞啊"
            },
            {
                "push": "→ ",
                "text": ": 全球大國一起封鎖美國 經濟制裁美國 如同他當初如何對待"
            },
            {
                "push": "→ ",
                "text": ": 朝鮮"
            },
            {
                "push": "推 ",
                "text": ": 電腦還有人買嗎？"
            },
            {
                "push": "噓 ",
                "text": ": 問習近平啊 哈哈"
            },
            {
                "push": "→ ",
                "text": ": 廣達20幾年前就台灣筆電產線全移到中國去 現在又跑回來"
            },
            {
                "push": "推 ",
                "text": ": 沒辦法，誰叫中國偷技術。嘻嘻"
            },
            {
                "push": "→ ",
                "text": ": 慟毛一道二"
            },
            {
                "push": "→ ",
                "text": ": 林百里沒差啦 新加坡人 愛買名畫的大老闆"
            },
            {
                "push": "推 ",
                "text": ": 聽川皇的話去美國生產啊"
            },
            {
                "push": "推 ",
                "text": ": 經營到利潤只有1.多%也真是厲害"
            },
            {
                "push": "→ ",
                "text": ": 自己爛 選錯邊站 怪誰"
            },
            {
                "push": "→ ",
                "text": ": 離開中國啊"
            },
            {
                "push": "→ ",
                "text": ": 鍋董選總統該不會是救鴻海？"
            },
            {
                "push": "推 ",
                "text": ": 正常，不過這是淨利，成本都扣完了"
            },
            {
                "push": "推 ",
                "text": ": 關稅談好還不是回中國"
            },
            {
                "push": "→ ",
                "text": ": 1.多 我是不信"
            },
            {
                "push": "推 ",
                "text": ": 活該阿 去死吧"
            },
            {
                "push": "噓 ",
                "text": ": 乾我屁事"
            },
            {
                "push": "→ ",
                "text": ": 期末價格"
            },
            {
                "push": "推 ",
                "text": ": 市售筆電那價格才賺1%多？騙不到盤子才是真的"
            },
            {
                "push": "推 ",
                "text": ": 代工毛利馬都很低= ="
            },
            {
                "push": "推 ",
                "text": ": 川普說在美國境內生產就不會有關稅啦"
            },
            {
                "push": "→ ",
                "text": ": 代工廠只要不停線，低毛利還是得接"
            },
            {
                "push": "→ ",
                "text": ": 三年前叫你南向 你自己不去的"
            },
            {
                "push": "推 ",
                "text": ": 1.41%......你公司要不要收一收了?"
            },
            {
                "push": "推 ",
                "text": ": obov:還不是代工"
            },
            {
                "push": "推 ",
                "text": ": 北七，關台灣屁事，去跟習帝說啊"
            },
            {
                "push": "噓 ",
                "text": ": 那就倒一倒阿 講一堆廢話還不是想要向政府蹭飯"
            },
            {
                "push": "推 ",
                "text": ": 川普一上台的時候就來勢洶洶，你現在還沒跑掉是要找誰"
            },
            {
                "push": "→ ",
                "text": ": 來救？幫不了你"
            },
            {
                "push": "推 ",
                "text": ": 你家的事"
            },
            {
                "push": "→ ",
                "text": ": 又不是他想搬就搬是看下游客戶來決定"
            },
            {
                "push": "→ ",
                "text": ": 客戶算的錢就是現有你的成本加一點不要就拉倒搬廠自己吞"
            },
            {
                "push": "推 ",
                "text": ": 看財報就知道啦"
            },
            {
                "push": "→ ",
                "text": ": 中國補貼政策干預市場所造成的後果~只能說活該"
            },
            {
                "push": "推 ",
                "text": ": 誰叫你被當成中國企業"
            },
            {
                "push": "推 ",
                "text": ": 乾我屁4 倒掉最好"
            },
            {
                "push": "→ ",
                "text": ": 自己去跟老闆講"
            },
            {
                "push": "推 ",
                "text": ": 淨利率1.4%, ROE還能有11%其實很好了"
            },
            {
                "push": "→ ",
                "text": ": 怪誰"
            },
            {
                "push": "噓 ",
                "text": ": 當年你能去中國也是美國政策走向 現在離開也是美國"
            },
            {
                "push": "噓 ",
                "text": ": 賺錢的時候眼睛長在頭頂 現在哭哭？"
            },
            {
                "push": "推 ",
                "text": ": 不要買豪宅、跑車不要養小三（選我正解"
            },
            {
                "push": "噓 ",
                "text": ": 品牌廠會要求你撤出中國，不然就轉單"
            },
            {
                "push": "→ ",
                "text": ": 林百里是香港人"
            },
            {
                "push": "→ ",
                "text": ": 不是說進口商會吸收…"
            },
            {
                "push": "推 ",
                "text": ": 臺積電：？"
            },
            {
                "push": "推 ",
                "text": ": 作幾十年了還是在代工，怪誰！"
            },
            {
                "push": "噓 ",
                "text": ": 又不趕快把工廠遷出中國，在那邊喊這個，最好你的顧客會佛"
            },
            {
                "push": "→ ",
                "text": ": 心幫你攤成本"
            },
            {
                "push": "噓 ",
                "text": ": 然後咧？政府要保證你賺錢嗎?"
            },
            {
                "push": "推 ",
                "text": ": 殭屍企業"
            },
            {
                "push": "推 ",
                "text": ": s大 你也真幽默 貼這幹嘛"
            },
            {
                "push": "→ ",
                "text": ": 覺青認為台灣是美國附庸國"
            },
            {
                "push": "→ ",
                "text": ": 只要主人贏了 自己死了也開心啊"
            },
            {
                "push": "→ ",
                "text": ": 自己過去當台商賺那麼多年了怎都沒聽你抱怨"
            },
            {
                "push": "→ ",
                "text": ": 自己當初愛去怪誰，你可以不要回來！"
            },
            {
                "push": "噓 ",
                "text": ": 愛貼中國，死了剛好而已啦！"
            },
            {
                "push": "噓 ",
                "text": ": 倒一倒 回家抱著你買的藝術品哭!!!!"
            },
            {
                "push": "推 ",
                "text": ": 代工這淨利不賴了 比血海好很多"
            },
            {
                "push": "推 ",
                "text": ": 產線可以移報東南亞阿"
            },
            {
                "push": "推 ",
                "text": ": 一堆23K出來嗆代工囉"
            }
        ]
    },
    {
        "title": "廣達法務團隊 vs 鴻海法務團隊 誰比較強",
        "date": "2019/04/21",
        "content": "之前鴻海的郭董喊出「民主不能當飯吃」  今天被廣達的林百里打臉說「民主要當飯吃」  郭董會不會氣噗噗要他手下地表最強的鴻海法務團隊去告林百里啊？  面對即將來勢洶洶的鴻海法務團隊，廣達的法務團隊擋的住嗎？  還是說廣達可能把鴻海的法務團隊給打趴呢？  郭董除了要應付廣達的林百里外，還要對抗來自旺旺蔡董的攻擊  最近台灣是要上演第一屆台灣有錢人武鬥大會嗎？  ",
        "comment": [
            {
                "push": "→ ",
                "text": ": 萌萌  戰起來"
            },
            {
                "push": "推 ",
                "text": ": 兩岸一家親"
            },
            {
                "push": "推 ",
                "text": ": 五樓跟六樓床上大戰300回合"
            },
            {
                "push": "→ ",
                "text": ": 政治服務經濟 先教習禁評乖乖聽商人的話"
            },
            {
                "push": "推 ",
                "text": ": 法務是多厲害？欺負百姓？"
            },
            {
                "push": "推 ",
                "text": ": 去去武器走"
            },
            {
                "push": "→ ",
                "text": ": 限制別人講話？"
            },
            {
                "push": "→ ",
                "text": ": 會去當法務的通常都是法律系又考不上執照的"
            },
            {
                "push": "→ ",
                "text": ": 而且官司打法就是拿整個公司去欺負你"
            },
            {
                "push": "推 ",
                "text": ": 你會先被告"
            },
            {
                "push": "→ ",
                "text": ": 叫習禁評不要整天搞政治不顧民生經濟 害支共失業率那麼高"
            },
            {
                "push": "推 ",
                "text": ": 某樓不知道公司法務很多都有執照喔zzz"
            },
            {
                "push": "推 ",
                "text": ": 這種大公司的法務沒有律師執照?我不太信"
            },
            {
                "push": "→ ",
                "text": ": 現在知名上市公司新徵法務很多會求要有律師證書"
            },
            {
                "push": "推 ",
                "text": ": 那個要幫原po您更正一下，民主要當飯吃是太陽花學運的"
            },
            {
                "push": "→ ",
                "text": ": 時候林百里說的，不是今天說的"
            },
            {
                "push": "推 ",
                "text": ": 那兩人幾十年前都都戰過幾百回合了,還曾經稱兄道弟咧"
            },
            {
                "push": "噓 ",
                "text": ": 廣達那個好幾年前的，不是今天"
            },
            {
                "push": "推 ",
                "text": ": 林百里香港人知道老共那一套"
            }
        ]
    },
    {
        "title": "假冒廣達詐騙臉書谷歌逾億美元 立陶宛男",
        "date": "2019/03/22",
        "content": "http://www.rti.org.tw/news/view/id/2015263 假冒廣達詐騙臉書谷歌逾億美元 立陶宛男子認罪  美國聯邦檢察官表示，遭美國指控協助策劃騙局、詐取臉書和谷歌逾1億美元的立陶宛男子黎瑪索斯卡斯(Evaldas Rimasauskas)，已在20日認罪。據指出，他假冒台灣廣達電腦詐騙這2家公司，騙取逾1億美元。  50歲的黎瑪索斯卡斯針對被控的電匯詐欺罪名，向曼哈頓地方法院法官丹尼爾斯(George Daniels)認罪。他最高恐面臨30年有期徒刑，目前法院計劃在7月24日宣判。  根據法院文件，黎瑪索斯卡斯已同意歸還他從詐騙案中取得的不當獲利4,970萬美元。  黎瑪索斯卡斯是在2017年8月從立陶宛被引渡至美國。美國檢方說，黎瑪索斯卡斯和另一名未透露身份的共犯，假冒成某家亞洲硬體供應商，並宣稱谷歌和臉書欠他們錢，詐騙了超過1億美元。  雖然檢方並未點名被捲入此案的企業，但在黎瑪索斯卡斯被捕後，台灣電子企業廣達電腦證實，就是遭假冒的亞洲供應商。而立陶宛法院2017年的裁定，則確認谷歌和臉書是受害者。  根據立陶宛的這份裁定，谷歌被詐騙了2,300萬美元，而臉書則損失9,900萬美元。檢方表示，黎瑪索斯卡斯是透過在拉脫維亞設立假公司和假帳戶進行詐騙。  美國聯邦調查局(FBI)2017年2月表示，這種也被稱為商務電子郵件詐騙(BEC)，自2013年開始追蹤以來，造成的損失已逾30億美元。  ",
        "comment": [
            {
                "push": "→ ",
                "text": ": 台灣教的?"
            },
            {
                "push": "推 ",
                "text": ": 猛..."
            },
            {
                "push": "→ ",
                "text": ": 說欠錢他們就還？都沒作帳的？"
            },
            {
                "push": "推 ",
                "text": ": 在台灣搞不好因為沒有實質影響力就..."
            },
            {
                "push": "推 ",
                "text": ": 人才"
            },
            {
                "push": "噓 ",
                "text": ": 逾一億美元第一段是要講幾次 什麼文筆"
            },
            {
                "push": "推 ",
                "text": ": 這個厲害"
            }
        ]
    },
    {
        "title": "假冒廣達騙臉書與谷歌31億 立陶宛男子認",
        "date": "2019/03/21",
        "content": "1.媒體來源: ※ 例如蘋果日報、自由時報 中央通訊社 Central News Agency  2.完整新聞標題: ※ 標題沒有完整寫出來 ---> 依照板規刪除文章 假冒廣達騙臉書與谷歌31億 立陶宛男子認罪  3.完整新聞內文: ※ 社論特稿都不能貼! 違者刪除(政治類水桶3個月)，貼廣告也會被刪除喔! 最新更新：2019/03/21 11:37 https://img5.cna.com.tw/www/WebPhotos/1024/20190321/223933598147.jpg 立陶宛50歲男子黎瑪索斯卡斯涉嫌詐騙Facebook和Google超過1億美元，20日認罪。（圖取自Pixabay圖庫）  （中央社紐約20日綜合外電報導）美國聯邦檢察官宣布，立陶宛50歲男子黎瑪索斯卡斯遭美國指控，協助策劃詐騙臉書和Alphabet旗下谷歌（Google）超過1億美元，今天認罪。他假冒的公司為台灣電子企業廣達電腦。  路透社報導，黎瑪索斯卡斯（Evaldas Rimasauskas）在曼哈頓地方法院法官丹尼爾斯（George Daniels）面前對一項電匯詐騙罪名認罪，恐面臨最高30年有期徒刑，宣判日訂在7月24日。  根據法院文件，黎瑪索斯卡斯也同意歸還他個人從這起詐騙案獲得的4970萬美元。  黎瑪索斯卡斯的律師佩特魯（Paul Petrus）表示，認罪聲明本身就很清楚，並拒絕進一步回應。  黎瑪索斯卡斯來自立陶宛首都維爾紐斯（Vilnius），2017年8月從立陶宛引渡至美國。  美國檢方指控，他及一名未透露姓名的共犯假冒某亞洲硬體供應商，並宣稱Google及臉書欠錢，藉此詐騙超過1億美元（約新台幣31億元）。  檢方沒有點出捲入此案的企業，但廣達在黎瑪索斯卡斯被捕後證實，自己是遭假冒的亞洲供應商，而立陶宛法院2017年的命令確認Google及臉書為受害公司。  根據這份命令，Google遭詐騙2300萬美元，而臉書則被騙走9900萬美元。檢方表示，黎瑪索斯卡斯透過在拉脫維亞設立假公司及假帳戶，達成這起陰謀。  這是種日益普遍的詐騙手法，又稱為「商務電子郵件詐騙」（BEC），欺詐者鎖定與外國供應商合作或定期進行電匯的企業，透過電郵要錢。  美國聯邦調查局（FBI）2017年2月表示，自2013年開始追蹤以來，這類詐騙案造成的損失共達超過30億美元。（譯者：侯文婷/核稿：張曉雯）1080321  4.完整新聞連結 (或短網址): ※ 當新聞連結過長時，需提供短網址方便網友點擊 https://www.cna.com.tw/news/firstnews/201903210068.aspx  5.備註: ※ 一個人一天只能張貼一則新聞，被刪或自刪也算額度內，超貼者水桶，請注意 立陶宛50歲男子假冒台灣廣達，向Google和Facebook索討超過1億美元的欠款。  ",
        "comment": [
            {
                "push": "→ ",
                "text": ": 冒充賣肉醬的也能騙那麼多"
            },
            {
                "push": "推 ",
                "text": ": 神鬼交鋒歐洲版"
            },
            {
                "push": "推 ",
                "text": ": 這沒有內鬼 我是不相信..."
            },
            {
                "push": "→ ",
                "text": ": 假冒賣肉醬的可以騙那麼多錢喔"
            },
            {
                "push": "→ ",
                "text": ": 好猛"
            },
            {
                "push": "→ ",
                "text": ": 賣香肉醬也能騙"
            },
            {
                "push": "推 ",
                "text": ": 好屌，他怎會知道google和fb有欠廣達什麼款項，應該是"
            },
            {
                "push": "→ ",
                "text": ": 有內應"
            },
            {
                "push": "推 ",
                "text": ": 當然是跟廣達香有內應 要駭進谷歌難多了"
            },
            {
                "push": "→ ",
                "text": ": 笑死, google與fb二家公司合計被騙超過1億美元.."
            },
            {
                "push": "→ ",
                "text": ": 準備再被廣達告"
            },
            {
                "push": "推 ",
                "text": ": 因為廣達提供google 客制硬體server啊"
            },
            {
                "push": "推 ",
                "text": ": 連google也敢騙？"
            },
            {
                "push": "噓 ",
                "text": ": 難怪我的肉鬆一直跌  耖"
            },
            {
                "push": "推 ",
                "text": ": 這案子，被騙的公司怕人知道，被冒名公司的怕人不知道"
            }
        ]
    },
    {
        "title": "擔心中國竊密？日經：光寶科、廣達應美國",
        "date": "2019/03/09",
        "content": "1.媒體來源: 經濟日報  2.完整新聞標題: 擔心中國竊密？日經：光寶科、廣達應美企要求撤出中國  3.完整新聞內文: 日經新聞報導，美國科技企業擔心連伺服器電源線和插頭，都可能被中國用來竊取機密資 料，已要求光寶科、廣達等台廠將這些零件的生產移出中國。  報導指出，一名主管表示，光寶科技正在台灣建造一座生產伺服器電源零件的新工廠，以 回應美國客戶的這些要求。光寶科的主要客戶包括Dell EMC、惠普（HP）和IBM等。  廣達電腦的一名主管告訴日經，已將生產移至台灣和其他地方，其中一項原因為安全考量 。廣達主要提供Google、臉書等美國科技企業客戶伺服器和資料中心設備。該主管說：「 數位安全、關稅和地緣政治風險是主要的三項原因。」  美國IT公司為了根絕安全威脅，對供應商的要求甚至連最平常的原件都得做到滴水不漏。 不少廠商都面臨必須將這些原件移往中國以外地方生產的壓力，即便生產成本會因此提高 。  光寶這名匿名主管說：「許多台灣科技廠將生產線撤出中國是為了避免美國對中國產品的 關稅，我們這座新廠的主要目的則是為了化解美國客戶的安全疑慮，跟其他台廠不同。」  光寶供應的電源零件和供電系統用在智慧手機、筆電、伺服器和資料中心等各種電子產品 上，會出貨給廣達、緯創、英業達等公司做伺服器的最後組裝。  光寶科這名主管表示，自從去年彭博商業週刊報導中國涉嫌在美國科技企業的資料中心供 應鏈裡植入微小晶片後，該公司的美國客戶開始人心惶惶，「雖然該報導的可信度有待商 榷，但美國客戶希望提升其安全措施，而且他們也不想讓川普政府失望。」  光寶目前投資了約新台幣100億元興建這座位在高雄的新設施和研究中心，預計今年6月開 始試運轉，這座廠房原本計劃生產車用電子零件。  數位安全專家表示，美國企業對這種風險的擔憂是合理的，雖然在目前已知的駭客事件中 ，尚未聽聞主要侵入管道是透過伺服器的電源零件。台灣資策會產業情報研究所底下的數 位安全研究所副主任田謹維表示：「駭客確實能從電源供應系統或電源線擷取存在伺服器 內的資料，而且並不困難。因此美國企業會有這種疑慮完全合理。」  不過專家也說，光是將生產移出中國並不能移除所有風險，因為有心人士永遠都有辦法操 控製程。田謹維說：「所有零件與零件、或主機板和電源供應系統間的介面，都有可能成 為蓄意入侵的漏洞。你只能減少或控制這些風險，但無法完全消滅這些威脅。」  專家表示，除了一般易成駭客目標的伺服器、資料中心或通訊基建設施外，個人的電子裝 置也可能遭受這種攻擊。  4.完整新聞連結 (或短網址): https://money.udn.com/money/story/5599/3685851  5.備註: 原文：台湾サーバー部品、中国生産見直し　米顧客の懸念で https://www.nikkei.com/article/DGXMZO42195270Y9A300C1FFE000/  -- → realtw: 百越民族在古代就是禮失求諸野的“野”　中原文明之外的    03/06 00:19 → realtw: 你吹得再厲害　也是“野”  03/06 00:20 → realtw: 吳語當然也是百越方言  03/06 00:32 → realtw: 我前面早就闡述得很清楚了 03/06 00:33 → realtw: 吳語　滬語　蘇州話當然是百越方言為底層的　還有什麼問的  03/06 00:34 → realtw: 百越地區都是野　不要翻來覆去的問了                      03/06 00:34  ",
        "comment": [
            {
                "push": "→ ",
                "text": ": 我前面早就闡述得很清楚了"
            },
            {
                "push": "→ ",
                "text": ": 支或贏"
            },
            {
                "push": "→ ",
                "text": ": 廣達撤出???????"
            },
            {
                "push": "→ ",
                "text": ": 完了  強國又要拿掉幾個邦交國出氣了"
            },
            {
                "push": "推 ",
                "text": ": 他們哪來這麼多外星科技啊太猛了吧"
            },
            {
                "push": "推 ",
                "text": ": =="
            },
            {
                "push": "→ ",
                "text": ": PoE 入侵嗎?"
            },
            {
                "push": "→ ",
                "text": ": 柯黑只要媒體發一篇就跟著high XDDD"
            },
            {
                "push": "→ ",
                "text": ": 推錯..."
            },
            {
                "push": "→ ",
                "text": ": 美國反制"
            },
            {
                "push": "推 ",
                "text": ": 那篇報導是真的? https://tinyurl.com/y3vm74sz"
            },
            {
                "push": "推 ",
                "text": ": 還有很多人不相信線材對數據傳輸有影響，說是音響玄學"
            },
            {
                "push": "→ ",
                "text": ": CIA幹過這種事 所以知道可以這樣幹~"
            },
            {
                "push": "推 ",
                "text": ": 以後要求廠商建獨立電網了，免得駭客沿著電線入侵"
            },
            {
                "push": "推 ",
                "text": ": 恕我才疏學淺，電源線是能夠竊取啥?每天的上班時數嗎？"
            },
            {
                "push": "推 ",
                "text": ": 靠無線電波都能竊了，不用說還靠電路傳輸，資訊該更新了"
            }
        ]
    }
]