[
    {
        "title": "新普科技:持續經營大陸市場 堅持九二共識",
        "date": "2019/04/30",
        "content": "覺青就真的噁心啊，看看之前還願就知道了，  明明就沒破百萬覺青在那邊一直講，  講到發行商都出來澄清，  結果現在從steam下架不知道重新上架了沒。  而且不做中國生意根本傻，連空心菜都不敢放棄  ----- Sent from JPTT on my Sony H9493.  -- ！！！！！！！！！！！！！！簽名檔破915000點擊率啦！！！！！！！！！！！！！！ Fw: [問卦] 電影：決勝21點的機率問題  https://goo.gl/2BpbB7 #1MfN3FgZ (joke) → yeebon: chx64的1/2悖論真的很經典呢07/22 16:41 https://upload.cc/i/tiloxB.jpg https://upload.cc/i/phcMAP.jpg chx64註冊tisen這帳號是想幹嘛啊？哈哈哈  ",
        "comment": [
            {
                "push": "→ ",
                "text": ": chx64的1/2悖論真的很經典呢"
            }
        ]
    },
    {
        "title": "新普科技:持續經營大陸市場 堅持九二共識",
        "date": "2019/04/30",
        "content": "1.媒體來源: 聯合新聞網  2.記者署名: 謝艾莉  3.完整新聞標題:  新普科技:持續經營大陸市場 堅持九二共識  4.完整新聞內文:  新普科技今（30）日發表聲明表示，針對3月27日法說會相關媒體報導說明事宜，新普強 調，將全面且積極的針對中國大陸市場的相關需求，進行研發和布局。  新普表示，針對本公司3月27日法說會時，部分媒體報導『宋福祥董事長提及新普科技從 不與中國大陸客戶做生意』實非新普科技和宋福祥董事長當下所表達原意，對於中國大陸 市場佈局的相關說法，亦非事實，由於時間倉促，無法完整陳述，引發媒體的誤會與相關 人士的疑慮，本公司除深感遺憾外，特在此做出完整的澄清與說明：  1. 中國大陸市場一向是本公司相當重視的市場之一，在全球市場佈局中佔有重要關鍵地 位。目前而言，本公司對於傳統和非傳統資訊類電池模組產品的推出在商業策略的進程上 有各種評估及考慮，本公司已將全面而且積極的針對中國大陸市場的相關需求進行研發和 佈局。  2. 本公司在“兩岸一家親”理念指引下，當進一步持續對中國大陸的投資和建廠，進一 步拓寬大陸市場，進而提升自己的科技水平，以全面強化新普科技的國際競爭力。  3. 新普科技一向堅定支持九二共識，認同兩岸一中，全力支援兩岸之間走和平發展的道 路，為兩岸同胞的共同福祉做出自己的貢獻。目前，我公司在中國大陸投資的企業在來自 各界包含政府、投資人、供應商及客戶等的關心和支持下，發展相當順利，請各位投資人 放心。    5.完整新聞連結 (或短網址): https://udn.com/news/story/7254/3785313   6.備註:  新普董事長:我從不做中國生意 https://tinyurl.com/yyvp6dfm  ",
        "comment": [
            {
                "push": "噓 ",
                "text": ": 嘻嘻"
            },
            {
                "push": "噓 ",
                "text": ": 想玩兩面手法"
            },
            {
                "push": "推 ",
                "text": ": 讚哦"
            },
            {
                "push": "推 ",
                "text": ": 覺青又被打臉 XD"
            },
            {
                "push": "推 ",
                "text": ": 笑死"
            },
            {
                "push": "噓 ",
                "text": ": 當初推文那些吉娃娃去那了"
            },
            {
                "push": "→ ",
                "text": ": 董事長愛講被關切了吼 笑死"
            },
            {
                "push": "推 ",
                "text": ": 滿噁的"
            },
            {
                "push": "推 ",
                "text": ": 愛講被關切了吧"
            },
            {
                "push": "推 ",
                "text": ": 當初就低調不是就沒事了嗎"
            },
            {
                "push": "推 ",
                "text": ": 恭喜您宋董事長符資格 來KMT參加初選吧"
            },
            {
                "push": "推 ",
                "text": ": 如果這樣講台灣人能賺到錢那也很好 一家公司決定不了什"
            },
            {
                "push": "→ ",
                "text": ": 麼"
            },
            {
                "push": "推 ",
                "text": ": XDDDD靠 太好笑了吧"
            }
        ]
    },
    {
        "title": "新普董事長︰我從不做中國生意",
        "date": "2019/04/30",
        "content": "※ 引述《spidina ()》之銘言： : : 自由時報 : : 2.完整新聞標題:新普董事長︰我從不做中國生意 : 新普今日發出聲明稿:針對本公司3月27日法說會時，部分媒體報導『宋福祥董事長提及新普科技從 : 不與中國大陸客戶做生意』實非新普科技和宋福祥董事長當下所表達原意，對於中國大陸 : 市場佈局的相關說法，亦非事實，由於時間倉促，無法完整陳述，引發媒體的誤會與相關 : 人士的疑慮，本公司除深感遺憾外，特在此做出完整的澄清與說明： : 1. 中國大陸市場一向是本公司相當重視的市場之一，在全球市場佈局中佔有重要關鍵地 : 位。目前而言，本公司對於傳統和非傳統資訊類電池模組產品的推出在商業策略的進程上 : 有各種評估及考慮，本公司已將全面而且積極的針對中國大陸市場的相關需求進行研發和 : 佈局。 : 2. 本公司在“兩岸一家親”理念指引下，當進一步持續對中國大陸的投資和建廠，進一 : 步拓寬大陸市場，進而提升自己的科技水平，以全面強化新普科技的國際競爭力。 : 3. 新普科技一向堅定支持九二共識，認同兩岸一中，全力支援兩岸之間走和平發展的道 : 路，為兩岸同胞的共同福祉做出自己的貢獻。目前，我公司在中國大陸投資的企業在來自 : 各界包含政府、投資人、供應商及客戶等的關心和支持下，發展相當順利，請各位投資人 : 放心。 笑翻天了  我不知道是新普董事長說真話，還是豬報又做了一次假新聞  若是後者  它X的，豬報真的超會造假   果然是台灣第一造假大報  再配合民退黨的黨工  刷一波  營造成  新普是間台獨企業  我看大陸同胞開始在抵制這間企業了  我認為新普董事長本人應開記者會  反駁一下豬報的假新聞  不然，大陸同胞可沒這麼好騙    看到吸獨仔被打臉打的媽媽不知道嫁給誰，就是爽啦  -- 皇民特徵： 1、認為慰安婦(性奴隸)是自願的                2、731部隊對人類貢獻舉世無雙 3、稱中國人為支那人，中國為支那              4、分不清中國大陸跟亞洲大陸的差別 5、認為他們祖先來自非洲，但絕對不去非洲掃墓  6、釣魚台是偉大皇國的 7、自許為反華急先鋒，否認南京大屠殺          8、稱讚倭據時代之台灣為世界最先進 符合四項以上-高級皇民          符合三項-中級皇民         符合二項以下-低級皇民  ",
        "comment": [
            {
                "push": "→ ",
                "text": ": 大陸?美洲大陸同胞嗎???"
            },
            {
                "push": "推 ",
                "text": ": 推 來看看這篇會有幾個高級皇民"
            },
            {
                "push": "噓 ",
                "text": ": 南極大陸？"
            },
            {
                "push": "噓 ",
                "text": ": 感覺這篇講的是黑暗大陸"
            },
            {
                "push": "→ ",
                "text": ": 畢竟共慘狗黨本來就黑暗 習近平等著韓公國瑜來取代他吧"
            },
            {
                "push": "噓 ",
                "text": ": 愛支那?愛滋那?"
            },
            {
                "push": "→ ",
                "text": ": 講到韓公國瑜就怕了喔  叫習近平回去喝奶等著韓公指導"
            },
            {
                "push": "噓 ",
                "text": ": 真是精甚阿  習精瓶的支那人"
            },
            {
                "push": "噓 ",
                "text": ": ☆愛支病大爆發★"
            },
            {
                "push": "→ ",
                "text": ": 台灣國台幣，謝謝"
            }
        ]
    },
    {
        "title": "新普董事長︰我從不做中國生意",
        "date": "2019/04/30",
        "content": ": 自由時報  : 2.完整新聞標題:新普董事長︰我從不做中國生意  新普今日發出聲明稿:針對本公司3月27日法說會時，部分媒體報導『宋福祥董事長提及新普科技從  不與中國大陸客戶做生意』實非新普科技和宋福祥董事長當下所表達原意，對於中國大陸  市場佈局的相關說法，亦非事實，由於時間倉促，無法完整陳述，引發媒體的誤會與相關  人士的疑慮，本公司除深感遺憾外，特在此做出完整的澄清與說明：   1. 中國大陸市場一向是本公司相當重視的市場之一，在全球市場佈局中佔有重要關鍵地  位。目前而言，本公司對於傳統和非傳統資訊類電池模組產品的推出在商業策略的進程上  有各種評估及考慮，本公司已將全面而且積極的針對中國大陸市場的相關需求進行研發和  佈局。  2. 本公司在“兩岸一家親”理念指引下，當進一步持續對中國大陸的投資和建廠，進一  步拓寬大陸市場，進而提升自己的科技水平，以全面強化新普科技的國際競爭力。   3. 新普科技一向堅定支持九二共識，認同兩岸一中，全力支援兩岸之間走和平發展的道  路，為兩岸同胞的共同福祉做出自己的貢獻。目前，我公司在中國大陸投資的企業在來自  各界包含政府、投資人、供應商及客戶等的關心和支持下，發展相當順利，請各位投資人  放心。  ",
        "comment": [
            {
                "push": "→ ",
                "text": ": 廠工，開噓!!!!!"
            },
            {
                "push": "→ ",
                "text": ": 轉彎了"
            },
            {
                "push": "→ ",
                "text": ": 不要學赤燭"
            },
            {
                "push": "→ ",
                "text": ": 哎呀   被抵制了"
            },
            {
                "push": "噓 ",
                "text": ": 五樓說自己不甲 隨後又被朋友踢爆根本毒甲"
            },
            {
                "push": "推 ",
                "text": ": 假新聞要禁嗎?"
            },
            {
                "push": "→ ",
                "text": ": =="
            },
            {
                "push": "推 ",
                "text": ": XD 讓覺青爽一爽背後道歉"
            },
            {
                "push": "推 ",
                "text": ": 綠吱崩潰"
            },
            {
                "push": "推 ",
                "text": ": 哇喔"
            },
            {
                "push": "推 ",
                "text": ": 太慢惹 1450都洗完一波了"
            },
            {
                "push": "→ ",
                "text": ": 爽完了 你可以滾了"
            },
            {
                "push": "推 ",
                "text": ": 不意外"
            },
            {
                "push": "→ ",
                "text": ": 股價開始跌會怕了哦"
            },
            {
                "push": "→ ",
                "text": ": 哈哈哈"
            },
            {
                "push": "→ ",
                "text": ": 董事長拉屎，拉的好神氣，屬下擦屁股，擦的好緊張"
            },
            {
                "push": "→ ",
                "text": ": 人民幣真香  嘻嘻"
            },
            {
                "push": "噓 ",
                "text": ": 五樓…"
            },
            {
                "push": "→ ",
                "text": ": 公3小，笑死我wwwwwwwwwwww"
            },
            {
                "push": "推 ",
                "text": ": 可能要被换了"
            }
        ]
    },
    {
        "title": "新普董︰我從不做中國生意",
        "date": "2019/03/29",
        "content": "※ 引述《showgo (goboy)》之銘言： : 新普董事長︰我從不做中國生意 : 自由 : 反觀... : ----- : Sent from JPTT on my HTC_U-1u.  新普在中國的廠商即將在中國A股上市： 太普動力新能源（常熟）股份有限公司（董事長宋維哲，董事宋福祥）擬首次發行人民 幣普通股并上市，現正接受中信證券股份有限公司輔導……。 A股首家純正綠色能源企 業即將上市。  就一個愚蠢的兩面人，這里還有人會為他護航洗白。 說啥產品沒有賣給中國人？  在大陸開了那么多廠，需要銷售給中國人？ 玩文字游戲嗎？到大陸投資不就是做生意？？？  好了這次又被中國黨媒環球時報抓包了 https://reurl.cc/mRqL7  看來不出幾天，新普又要發所謂九二共識一中聲明了。  ",
        "comment": [
            {
                "push": "→ ",
                "text": ": 裝逼一時爽"
            },
            {
                "push": "噓 ",
                "text": ": 看426瘋狂跳腳就知道宋董說對話了"
            },
            {
                "push": "推 ",
                "text": ": 哈哈，原文爽到高潮"
            },
            {
                "push": "推 ",
                "text": ": 董事長：我祖籍XX我熱愛中國"
            },
            {
                "push": "→ ",
                "text": ": 並、裡、麼、遊，你們轉換軟體到底有沒有在更新？"
            },
            {
                "push": "→ ",
                "text": ": 赤蠋：哈哈，又來一個"
            },
            {
                "push": "推 ",
                "text": ": 真的有人就愛這一味"
            },
            {
                "push": "推 ",
                "text": ": 看貼貼紙建國就知道智障很愛這一款人啊"
            },
            {
                "push": "→ ",
                "text": ": 快去舉報 讓他死"
            },
            {
                "push": "推 ",
                "text": ": 五毛乖，謝謝你幫忙抓喔！"
            }
        ]
    },
    {
        "title": "新普董事長︰我從不做中國生意",
        "date": "2019/03/28",
        "content": "可以說閃開讓專業來   1.新普(Simplo)有家子公司 合普新能源(2010年成立)   非本國公司無統一編號    合普新能源科技有限公司  母公司名稱:  母公司名稱: Simplo Technology STSZ (HK) Limited新普科技宏益(香港)  資料來源 https://thaubing.gcaa.org.tw/group/name/G6121   2.合普新能源科技 是中國國企普天子公司.. 然後宋董說不做國內市場...(笑)   https://www.qichacha.com/firm_1accc1a7a436a8626050ac784b6487a8.html   3.中國的104 51Jobs也是這樣寫  http://big5.51job.com/gate/big5/jobs.51job.com/all/co2530019.html   4.但到2017年公司好像賣給大陸私人企業   http://ggjd.cnstock.com/company/scp_ggjd/tjd_ggkx/201710/4141958.htm   宋董給我翻譯翻譯  什麼叫不做中國生意?   ※ 引述《zzahoward (Cheshire Cat)》之銘言： : 那個.... : 我以前做過這家的生意阿，他下游明明就不少中資廠商XD : 而且，我記得他也有在中國設立分公司和子公司啊 : 查了一下還真的有QQ : https://imgur.com/4UkUd2H.jpg : 所以我不太清楚他的供應鏈是怎樣屏除中國下游或上游 : 不過我記得他也有跟普天合作過...現在還有沒有我不太確定 : 普天在中國是哪個等級的企業，大家可以google看看 : 他們也算是在2000年左右就布局中國了 : 所以，大家看一看就好 : ※ 引述《staedtler (鐵甲武士)》之銘言： : : 1.媒體來源: : : 自由時報 : : 2.完整新聞標題: : : 新普董事長︰我從不做中國生意 : : 3.完整新聞內文: : : 中國付款條件就是吃喝玩樂 : : 〔記者卓怡君／台北報導〕「我從不做中國生意！中國付款條件就是吃喝玩樂！」新普（ : : 6121）董事長宋福祥直言，他到現在一毛錢中國生意都沒有做，做中國生意賺不到錢、收 : : 不到錢，中國廠商抄襲很凶，新普的公司策略就是百分之百外銷到歐、美、日這3大區域 : : ，這些客戶不會欠款，時間一到就付款。 : : 昨日在新普法說會上，法人問到新普如何因應中國競爭者的威脅，宋福祥劈頭就說，新普 : : 到現在一毛錢中國生意都沒有做！因為做中國生意，賺不到錢、收不到錢，中國市場付款 : : 條件就是「吃喝玩樂」，宋福祥砲轟：「我不來這套，不跟你打屁，我最討厭吃飯喝酒。 : : 」 : : 只做歐美日 客戶絕不欠款 : : 所以，新普只做歐、美、日外銷，宋福祥強調，中國是殺戮戰場，他跳開這個殺戮戰場， : : 只做歐、美、日外銷，把技術做好就好，歐洲客戶雖然很難打進去、很麻煩，不過，一旦 : : 打進去，合約時間就很長，從台灣打進歐洲，要比中國打進歐洲更有利，台灣人的素質、 : : 品質、技術都比較好。 : : 新普位居全球NB鋰電池龍頭，因全球NB已經飽和，迅速轉到手機領域，成為蘋果全系列供 : : 應商， 近年宋福祥有感於傳統資訊IT產品成長有限，大刀闊斧進行轉型大計，朝電動車 : : 、伺服器電池等領域發展。 : : 4.完整新聞連結 (或短網址): : : https://tinyurl.com/yyvp6dfm : : 5.備註:  -- Yoda      ▁▁▁▁▁▁▁▁▁▁▁▁▁▁▁▁▁▁▁▁▁▁▁▁▁╴╴╴╴▃▃   ▕█████████████████████████▅ o       ∥     ▔▔▔▔▔▔▔▔▔▔▔▔▔▔▔▔▔▔▔▔▔▔▔▔▔▃▔▔▔▅▅   ",
        "comment": [
            {
                "push": "推 ",
                "text": ": 讚讚"
            },
            {
                "push": "推 ",
                "text": ": 你這樣覺青怎麼辦"
            },
            {
                "push": "推 ",
                "text": ": 先幫你補血 不然等一下一群黨工讓你XX"
            },
            {
                "push": "推 ",
                "text": ": 做輸賣了就不算做囉"
            },
            {
                "push": "→ ",
                "text": ": 他說“我”不做，啊公司其他人做不會怎樣"
            },
            {
                "push": "推 ",
                "text": ": XDDDDD"
            },
            {
                "push": "推 ",
                "text": ": 可能會說：我也是看報紙才知道的"
            },
            {
                "push": "噓 ",
                "text": ": 因為不誠信，所以現在不做了，含粉不懂中文吧。"
            },
            {
                "push": "→ ",
                "text": ": 說詞與事實落差大可能有隱情也可能是講給特定人士聽的"
            },
            {
                "push": "噓 ",
                "text": ": 專業XDDDDDDDDDDDDDDDDDDDDDDDDDDDDDDDDDDDDDDDDDDDDD"
            },
            {
                "push": "→ ",
                "text": ": 自由新聞下架了"
            }
        ]
    },
    {
        "title": "新普董事長︰我從不做中國生意",
        "date": "2019/03/28",
        "content": "其實上網看一下就有相關資訊了  本來還想說買個股票支持一下  https://reurl.cc/XRzbM  結果看到這篇，08年的文了  20年前就在大陸設廠，還大肆報導  怎麼看都不像不做中國生意啊  還是覺醒了？  ※ 引述《zzahoward (Cheshire Cat)》之銘言： : 那個.... : 我以前做過這家的生意阿，他下游明明就不少中資廠商XD : 而且，我記得他也有在中國設立分公司和子公司啊 : 查了一下還真的有QQ : https://imgur.com/4UkUd2H.jpg : 所以我不太清楚他的供應鏈是怎樣屏除中國下游或上游 : 不過我記得他也有跟普天合作過...現在還有沒有我不太確定 : 普天在中國是哪個等級的企業，大家可以google看看 : 他們也算是在2000年左右就布局中國了 : 所以，大家看一看就好 : ※ 引述《staedtler (鐵甲武士)》之銘言： : : 1.媒體來源: : : 自由時報 : : 2.完整新聞標題: : : 新普董事長︰我從不做中國生意 : : 3.完整新聞內文: : : 中國付款條件就是吃喝玩樂 : : 〔記者卓怡君／台北報導〕「我從不做中國生意！中國付款條件就是吃喝玩樂！」新 普 : : 6121）董事長宋福祥直言，他到現在一毛錢中國生意都沒有做，做中國生意賺不到錢 、 : : 不到錢，中國廠商抄襲很凶，新普的公司策略就是百分之百外銷到歐、美、日這3大 區? : : ，這些客戶不會欠款，時間一到就付款。 : : 昨日在新普法說會上，法人問到新普如何因應中國競爭者的威脅，宋福祥劈頭就說， 新 : : 到現在一毛錢中國生意都沒有做！因為做中國生意，賺不到錢、收不到錢，中國市場 付 : : 條件就是「吃喝玩樂」，宋福祥砲轟：「我不來這套，不跟你打屁，我最討厭吃飯喝 酒 : : 」 : : 只做歐美日 客戶絕不欠款 : : 所以，新普只做歐、美、日外銷，宋福祥強調，中國是殺戮戰場，他跳開這個殺戮戰 場 : : 只做歐、美、日外銷，把技術做好就好，歐洲客戶雖然很難打進去、很麻煩，不過， 一 : : 打進去，合約時間就很長，從台灣打進歐洲，要比中國打進歐洲更有利，台灣人的素 質 : : 品質、技術都比較好。 : : 新普位居全球NB鋰電池龍頭，因全球NB已經飽和，迅速轉到手機領域，成為蘋果全系 列 : : 應商， 近年宋福祥有感於傳統資訊IT產品成長有限，大刀闊斧進行轉型大計，朝電 動? : : 、伺服器電池等領域發展。 : : 4.完整新聞連結 (或短網址): : : https://tinyurl.com/yyvp6dfm : : 5.備註:  ",
        "comment": [
            {
                "push": "→ ",
                "text": ": 只好當沖了"
            },
            {
                "push": "推 ",
                "text": ": 時代背景不同啦"
            },
            {
                "push": "→ ",
                "text": ": 是和祖國生意 不是中國啦"
            },
            {
                "push": "噓 ",
                "text": ": 如果是20年前就別太放大鏡惹，有人20分鐘都不能考驗惹"
            },
            {
                "push": "推 ",
                "text": ": 不做中國生意 因為工廠在中國所以都是跟其他國家做生意 懂"
            },
            {
                "push": "推 ",
                "text": ": 說給綠共/覺青聽的，見鬼說鬼話罷了"
            },
            {
                "push": "→ ",
                "text": ": https://i.imgur.com/H3b4Zk5.jpg"
            },
            {
                "push": "推 ",
                "text": ": 聯想到反扁麵包師父的怪麵包"
            },
            {
                "push": "→ ",
                "text": ": 嘻嘻"
            },
            {
                "push": "→ ",
                "text": ": 他是說他不賣水果生意啦。"
            },
            {
                "push": "→ ",
                "text": ": 賣給歐米日品牌的代工廠嘛~"
            },
            {
                "push": "推 ",
                "text": ": 講講而已高潮一下臭了嗎"
            },
            {
                "push": "推 ",
                "text": ": 就炒個新聞嘛"
            },
            {
                "push": "推 ",
                "text": ": 今天一根六啪你敢嘴"
            },
            {
                "push": "推 ",
                "text": ": 他意思應該是客戶不做中國  不算設廠？"
            },
            {
                "push": "推 ",
                "text": ": 不做中國生意不代表不在中國生產，做得都不賣中國而已"
            },
            {
                "push": "→ ",
                "text": ": 那女的臉好恐怖啊, 被政治洗腦洗過頭了, 記住,不過你挺"
            },
            {
                "push": "→ ",
                "text": ": 白綠藍什麼色,以後你沒錢流落街頭時,它們都不會理你."
            },
            {
                "push": "推 ",
                "text": ": 台灣很多廠在台灣生產但只外銷歐美的 這叫做做歐美生意"
            },
            {
                "push": "→ ",
                "text": ": 不叫做做台灣生意 懂了吧"
            },
            {
                "push": "推 ",
                "text": ": 不售往中國就可以說他不做中國人的生意了吧，中國薪"
            },
            {
                "push": "→ ",
                "text": ": 水提高廠房就會移往東南亞了"
            },
            {
                "push": "推 ",
                "text": ": 吉娃娃不敢回這篇，嘻嘻"
            },
            {
                "push": "推 ",
                "text": ": 這也行?幫中國增加就業機會 交稅給中國 就是不賺中國錢"
            },
            {
                "push": "噓 ",
                "text": ": 你是在誣賴自由發假新聞嗎"
            },
            {
                "push": "推 ",
                "text": ": 老董隨便嘴隨便信的智商也堪慮"
            },
            {
                "push": "→ ",
                "text": ": 不要臉天下無敵"
            },
            {
                "push": "→ ",
                "text": ": 中下游都沒跟中國買零件，你唬爛誰，別護航了"
            },
            {
                "push": "推 ",
                "text": ": 在中國設廠還敢講這種話，可能過兩天就要道歉了。"
            },
            {
                "push": "推 ",
                "text": ": 沒像郭台銘那樣深陷進去，中共對他的控制力可能不大"
            },
            {
                "push": "→ ",
                "text": ": ，說不定早就想換地方設廠了"
            },
            {
                "push": "推 ",
                "text": ": 不然會像郭董虧到賣水果"
            },
            {
                "push": "噓 ",
                "text": ": 不去擔心，去了傷心，回家放心！"
            },
            {
                "push": "推 ",
                "text": ": 是他個人不做，又不是他公司不做中國生意。"
            },
            {
                "push": "→ ",
                "text": ": 只能說廠廠真多 檢查一下身上mic的東西可能會脫光光"
            },
            {
                "push": "噓 ",
                "text": ": 邏輯有問題,不做中國生意是不賣中國客戶,跟哪裡製造生"
            },
            {
                "push": "→ ",
                "text": ": 產有關係嗎？"
            },
            {
                "push": "推 ",
                "text": ": 聯想是新普的客戶之一，樓上知道聯想是什麼公司嗎"
            },
            {
                "push": "→ ",
                "text": ": 個人不做   但是公司做"
            },
            {
                "push": "→ ",
                "text": ": 大陸設廠不等於做生意 賣給聯想是供應鏈不是做生意"
            },
            {
                "push": "→ ",
                "text": ": 如果你還是不懂，請充值臺灣精神或者帶上玫瑰色眼鏡"
            },
            {
                "push": "推 ",
                "text": ": 自由新聞下架了"
            }
        ]
    },
    {
        "title": "新普董事長︰我從不做中國生意",
        "date": "2019/03/28",
        "content": "那個....  我以前做過這家的生意阿，他下游明明就不少中資廠商XD  而且，我記得他也有在中國設立分公司和子公司啊  查了一下還真的有QQ  https://imgur.com/4UkUd2H.jpg  所以我不太清楚他的供應鏈是怎樣屏除中國下游或上游  不過我記得他也有跟普天合作過...現在還有沒有我不太確定  普天在中國是哪個等級的企業，大家可以google看看  他們也算是在2000年左右就布局中國了  所以，大家看一看就好   ※ 引述《staedtler (鐵甲武士)》之銘言： : 1.媒體來源: : 自由時報 : 2.完整新聞標題: : 新普董事長︰我從不做中國生意 : 3.完整新聞內文: : 中國付款條件就是吃喝玩樂 : 〔記者卓怡君／台北報導〕「我從不做中國生意！中國付款條件就是吃喝玩樂！」新普（ : 6121）董事長宋福祥直言，他到現在一毛錢中國生意都沒有做，做中國生意賺不到錢、收 : 不到錢，中國廠商抄襲很凶，新普的公司策略就是百分之百外銷到歐、美、日這3大區域 : ，這些客戶不會欠款，時間一到就付款。 : 昨日在新普法說會上，法人問到新普如何因應中國競爭者的威脅，宋福祥劈頭就說，新普 : 到現在一毛錢中國生意都沒有做！因為做中國生意，賺不到錢、收不到錢，中國市場付款 : 條件就是「吃喝玩樂」，宋福祥砲轟：「我不來這套，不跟你打屁，我最討厭吃飯喝酒。 : 」 : 只做歐美日 客戶絕不欠款 : 所以，新普只做歐、美、日外銷，宋福祥強調，中國是殺戮戰場，他跳開這個殺戮戰場， : 只做歐、美、日外銷，把技術做好就好，歐洲客戶雖然很難打進去、很麻煩，不過，一旦 : 打進去，合約時間就很長，從台灣打進歐洲，要比中國打進歐洲更有利，台灣人的素質、 : 品質、技術都比較好。 : 新普位居全球NB鋰電池龍頭，因全球NB已經飽和，迅速轉到手機領域，成為蘋果全系列供 : 應商， 近年宋福祥有感於傳統資訊IT產品成長有限，大刀闊斧進行轉型大計，朝電動車 : 、伺服器電池等領域發展。 : 4.完整新聞連結 (或短網址): : https://tinyurl.com/yyvp6dfm : 5.備註:  ",
        "comment": [
            {
                "push": "→ ",
                "text": ": 專業打臉"
            },
            {
                "push": "推 ",
                "text": ": 成立自由貿易區後，mit就等於mic了"
            },
            {
                "push": "→ ",
                "text": ": 上一篇哪幾個id吹捧的"
            },
            {
                "push": "→ ",
                "text": ": 啪啪啪啪"
            },
            {
                "push": "噓 ",
                "text": ": 做到翻臉 不然怎麼知道被支那廠商玩過"
            },
            {
                "push": "推 ",
                "text": ": 會覺得生意人不做某個地方生意是因為愛國的人本來就"
            },
            {
                "push": "→ ",
                "text": ": 是智障吧"
            },
            {
                "push": "推 ",
                "text": ": 全都是商業考量，支那風險太高"
            },
            {
                "push": "推 ",
                "text": ": 你這樣鄉民很難捧"
            },
            {
                "push": "推 ",
                "text": ": 客戶也有聯想"
            },
            {
                "push": "→ ",
                "text": ": 這沒什麼好打臉的 經銷商代理商賣中國是它家的事 成立"
            },
            {
                "push": "→ ",
                "text": ": 一家獨立公司去玩中國市場 爛了就收掉 不會動搖本業就"
            },
            {
                "push": "→ ",
                "text": ": 好 傻的人是把中國市場當自己的本業 那種的就三好加一"
            },
            {
                "push": "→ ",
                "text": ": 好"
            },
            {
                "push": "推 ",
                "text": ": 所以是用分身去做生意 就不算跟中國做囉?"
            },
            {
                "push": "推 ",
                "text": ": 我剛剛還去看了職缺…業務、locate在江蘇…"
            },
            {
                "push": "→ ",
                "text": ": 笑到肚子痛"
            },
            {
                "push": "→ ",
                "text": ": 去新普集團的職缺就看的到、不是什麼代理商的"
            },
            {
                "push": "→ ",
                "text": ": 跟普天合資啦!! 然後這家合資公司底下又有台廠供應鏈.."
            },
            {
                "push": "推 ",
                "text": ": 上一篇捧的吉娃娃哭暈在廁所"
            },
            {
                "push": "→ ",
                "text": ": 最重要的是普天是合資公司大股東,中國生意由他出面就好"
            },
            {
                "push": "→ ",
                "text": ": 說不定他出貨轉給別人處理啊.不用直接對大陸客戶.."
            },
            {
                "push": "推 ",
                "text": ": 真香"
            },
            {
                "push": "噓 ",
                "text": ": 你知道太多了  不自殺聲明?"
            },
            {
                "push": "推 ",
                "text": ": 掛推"
            },
            {
                "push": "推 ",
                "text": ": 以前有交易過+1 這個董事長真的知道自己家的狀況嗎？"
            },
            {
                "push": "推 ",
                "text": ": 一群智障還在推聰明，只有他最笨吧"
            },
            {
                "push": "推 ",
                "text": ": 廠工推文你別太在意"
            },
            {
                "push": "推 ",
                "text": ": 廠工開啟無視"
            },
            {
                "push": "推 ",
                "text": ": 沒事兒"
            },
            {
                "push": "推 ",
                "text": ": https://i.imgur.com/H3b4Zk5.jpg"
            },
            {
                "push": "→ ",
                "text": ": 我是不確定啦 不過他是指產品不賣中 不是不設廠"
            },
            {
                "push": "→ ",
                "text": ": 他沒說不投資中國  講法不衝突"
            },
            {
                "push": "噓 ",
                "text": ": 廠商又不是客戶"
            },
            {
                "push": "推 ",
                "text": ": 推"
            },
            {
                "push": "→ ",
                "text": ": 供應給聯想原來不是中國牌子"
            },
            {
                "push": "推 ",
                "text": ": 基本上經營較久又有一定規模的電子業幾乎不可能不曾在"
            },
            {
                "push": "→ ",
                "text": ": 中國投資或作生意的"
            },
            {
                "push": "噓 ",
                "text": ": 原來在中國設廠和跟中國做生意一樣"
            },
            {
                "push": "→ ",
                "text": ": 原來新普沒有做聯想生意"
            },
            {
                "push": "推 ",
                "text": ": 這算假新聞"
            },
            {
                "push": "推 ",
                "text": ": 綠吱們別在傻傻護航了，人家目冉時報已經徹下報導囉，"
            },
            {
                "push": "→ ",
                "text": ": 在應坳護航更難看而已"
            }
        ]
    },
    {
        "title": "新普董︰我從不做中國生意",
        "date": "2019/03/28",
        "content": " 新普董事長︰我從不做中國生意  自由 〔記者卓怡君／台北報導〕「我從不做中國生意！中國付款條件就是吃喝玩樂！」新普（6121）董事長宋福祥直言，他到現在一毛錢中國生意都沒有做，做中國生意賺不到錢、收不到錢，中國廠商抄襲很凶，新普的公司策略就是百分之百外銷到歐、美、日這3大區域，這些客戶不會欠款，時間一到就付款。 昨日在新普法說會上，法人問到新普如何因應中國競爭者的威脅，宋福祥劈頭就說，新普到現在一毛錢中國生意都沒有做！因為做中國生意，賺不到錢、收不到錢，中國市場付款條件就是「吃喝玩樂」，宋福祥砲轟：「我不來這套，不跟你打屁，我最討厭吃飯喝酒。」 所以，新普只做歐、美、日外銷，宋福祥強調，中國是殺戮戰場，他跳開這個殺戮戰場，只做歐、美、日外銷，把技術做好就好，歐洲客戶雖然很難打進去、很麻煩，不過，一旦打進去，合約時間就很長，從台灣打進歐洲，要比中國打進歐洲更有利，台灣人的素質、品質、技術都比較好。  新普位居全球NB鋰電池龍頭，因全球NB已經飽和，迅速轉到手機領域，成為蘋果全系列供應商， 近年宋福祥有感於傳統資訊IT產品成長有限，大刀闊斧進行轉型大計，朝電動車、伺服器電池等領域發展。  https://ec.ltn.com.tw/m/article/breakingnews/2741409  反觀...  ----- Sent from JPTT on my HTC_U-1u.  ",
        "comment": [
            {
                "push": "推 ",
                "text": ": 反觀"
            },
            {
                "push": "推 ",
                "text": ": 禿頭：我最愛吃飯喝酒還會到你家睡覺"
            },
            {
                "push": "推 ",
                "text": ":  這間真的很棒"
            },
            {
                "push": "推 ",
                "text": ": 反觀"
            },
            {
                "push": "推 ",
                "text": ": 反觀HTC舔共舔到快倒閉"
            },
            {
                "push": "推 ",
                "text": ": 完了，9.2要抵制了"
            },
            {
                "push": "→ ",
                "text": ": 臉書: 我做。你誰?"
            },
            {
                "push": "推 ",
                "text": ": 中肯，但有人不懂"
            },
            {
                "push": "→ ",
                "text": ": 沃爾瑪: 我做。你誰?"
            },
            {
                "push": "推 ",
                "text": ": 賺這樣當然不用舔  這種等級公司老闆話聽聽就好"
            },
            {
                "push": "→ ",
                "text": ": 跟直銷一樣"
            },
            {
                "push": "→ ",
                "text": ": 紅海:我做。你誰?"
            },
            {
                "push": "→ ",
                "text": ": 生意人不做某個地方的生意會是因為愛國嗎？XDDD"
            },
            {
                "push": "推 ",
                "text": ": 新普真的超猛... 這麼猛 結果沒支那單 蠻意外的77777"
            },
            {
                "push": "推 ",
                "text": ": 這塊中國本來就不是大買家 而且中國市場有自己的業者"
            },
            {
                "push": "推 ",
                "text": ": 腦袋清楚 反觀有人跪舔乞討還要被封殺"
            },
            {
                "push": "→ ",
                "text": ": 台G電: 我做。你誰?"
            },
            {
                "push": "→ ",
                "text": ": flavorBZ: 台獨萬歲 ←你認真= =?"
            },
            {
                "push": "→ ",
                "text": ": 你說這話不怕被中共消失?"
            },
            {
                "push": "→ ",
                "text": ": 在中國生產 然後賣給國外大廠 這還單純一點"
            },
            {
                "push": "→ ",
                "text": ": 要吃麻辣鍋的話,站在鍋子外面吃是可以啦.如果為了吃還要自己"
            },
            {
                "push": "→ ",
                "text": ": 股價沒低於100塊過..算了"
            },
            {
                "push": "推 ",
                "text": ": 做中國生意就是要打紅海戰"
            },
            {
                "push": "→ ",
                "text": ": 台獨萬萬歲"
            },
            {
                "push": "→ ",
                "text": ": 跳進去,那到底是能吃更多,還是自己也變成鍋裡的火鍋料XD"
            },
            {
                "push": "推 ",
                "text": ": 韓粉、柯粉:鎖國、井蛙"
            },
            {
                "push": "→ ",
                "text": ": 新普在中國有很多投資 但不跟中國廠商攪和"
            },
            {
                "push": "推 ",
                "text": ": 鄉民居然會認為商人不做中國生意是因為愛國？這…"
            },
            {
                "push": "推 ",
                "text": ": 不會簽MOU還好意思來講幹話?"
            },
            {
                "push": "→ ",
                "text": ": …"
            },
            {
                "push": "推 ",
                "text": ": 好公司!"
            },
            {
                "push": "推 ",
                "text": ":"
            },
            {
                "push": "推 ",
                "text": ": 反觀"
            },
            {
                "push": "推 ",
                "text": ": 新光少東當年從北京連夜逃回台灣,整碗被人拿走還連屁都不敢放"
            },
            {
                "push": "推 ",
                "text": ": 站著把錢賺"
            },
            {
                "push": "推 ",
                "text": ": 腦袋清楚還不用拋棄尊嚴人格去舔，賺錢就靠本事真的技術好"
            },
            {
                "push": "→ ",
                "text": ": 大陸廠商也會自己來談的"
            },
            {
                "push": "推 ",
                "text": ": 李嘉誠敢做啊 逃夠快就ok"
            },
            {
                "push": "推 ",
                "text": ": 他的客戶做中國生意做好做滿就夠了啊，還有，他公司中"
            },
            {
                "push": "→ ",
                "text": ": 國設廠講幹話"
            },
            {
                "push": "推 ",
                "text": ": 柯粉表示"
            },
            {
                "push": "推 ",
                "text": ": 一堆中小企業去大陸被套養殺"
            },
            {
                "push": "推 ",
                "text": ": 反觀"
            },
            {
                "push": "→ ",
                "text": ": 股版有人挖出他子公司在中國，覺青認為設廠=\\=做生意，"
            },
            {
                "push": "→ ",
                "text": ": 哈哈哈哈哈"
            },
            {
                "push": "推 ",
                "text": ": 覺青高潮了 結果有賣聯想 又有新聞說要跟中資合作"
            },
            {
                "push": "推 ",
                "text": ": 反觀"
            },
            {
                "push": "推 ",
                "text": ": ㄎㄎ"
            },
            {
                "push": "→ ",
                "text": ": 北七覺青"
            },
            {
                "push": "→ ",
                "text": ": 他是做電池模組的 但是現在很多電池芯大廠都 MIC"
            },
            {
                "push": "→ ",
                "text": ": 唉 當初押鋰電股押錯支 只能看新普衝高高"
            },
            {
                "push": "推 ",
                "text": ": 中國有廠 歡迎舉報"
            },
            {
                "push": "推 ",
                "text": ": 慘了 6121要被韓粉們放空了~"
            },
            {
                "push": "→ ",
                "text": ": 在中國生產沒啥不合理 只是不想跟中國的買主瞎攪和"
            },
            {
                "push": "推 ",
                "text": ": 反觀郭董"
            },
            {
                "push": "推 ",
                "text": ": 推"
            },
            {
                "push": "推 ",
                "text": ": 讚"
            },
            {
                "push": "→ ",
                "text": ": \"這些客戶不會欠款，時間一到就付款\" 做生意不就這樣?"
            },
            {
                "push": "→ ",
                "text": ": 樓上可以查一下剛開放中國旅遊的時候倒了多少旅行社的原因"
            },
            {
                "push": "→ ",
                "text": ": 子公司做算嗎？商人這麼帶種值得鼓勵"
            },
            {
                "push": "推 ",
                "text": ": 覺青表示 :"
            },
            {
                "push": "→ ",
                "text": ": https://www.ettoday.net/news/20120424/41644.htm"
            },
            {
                "push": "→ ",
                "text": ": 台中的精密機械也都不跟中國做生意了  原因也是這樣"
            },
            {
                "push": "推 ",
                "text": ": 推"
            },
            {
                "push": "推 ",
                "text": ": 新普是台獨企業 讚啦"
            },
            {
                "push": "→ ",
                "text": ": 欠款  要求移廠  技術轉移  合資  每樣都是挖你家老本"
            },
            {
                "push": "推 ",
                "text": ": 霸氣 真的猛!"
            },
            {
                "push": "推 ",
                "text": ": 超屌 這個才叫做有競爭力有國際觀"
            },
            {
                "push": "→ ",
                "text": ": 白癡才跟中國做生意  在中國的工廠只要末端組裝線就好了"
            },
            {
                "push": "→ ",
                "text": ": 反觀一堆影視圈的廢物"
            },
            {
                "push": "推 ",
                "text": ": 這種老闆真的是有實力"
            },
            {
                "push": "推 ",
                "text": ": 好聰明睿智啊"
            },
            {
                "push": "推 ",
                "text": ": 推"
            },
            {
                "push": "推 ",
                "text": ": 設廠 = 跟中國做生意，我也是笑了。"
            },
            {
                "push": "推 ",
                "text": ": 這才是臺灣的未來"
            },
            {
                "push": "推 ",
                "text": ": 這才叫競爭力啊......"
            },
            {
                "push": "推 ",
                "text": ": 有技術的 有全球競爭力的 才可以這樣子喊 可惜台灣這樣"
            },
            {
                "push": "→ ",
                "text": ": 的廠商並不算多"
            },
            {
                "push": "噓 ",
                "text": ": 本來就只有沒能力的才在那哀哀叫想抱大腿"
            },
            {
                "push": "推 ",
                "text": ": 反觀"
            },
            {
                "push": "→ ",
                "text": ": 中國也有不做美國生意的，好像更牛逼？比如華為。呵呵"
            },
            {
                "push": "推 ",
                "text": ": 超霸氣而且是真正的聰明人"
            },
            {
                "push": "推 ",
                "text": ": 原來聯想不是中國的 受教了"
            },
            {
                "push": "→ ",
                "text": ": 這個台雜如果不做美國日本的生意，我還當他是個人。在島上"
            },
            {
                "push": "→ ",
                "text": ": 只能推了"
            },
            {
                "push": "推 ",
                "text": ":"
            },
            {
                "push": "→ ",
                "text": ": 不做中國生意的，沒有十萬也有一千吧。呵呵，這孫子"
            },
            {
                "push": "→ ",
                "text": ": 反觀"
            },
            {
                "push": "推 ",
                "text": ": 推"
            },
            {
                "push": "推 ",
                "text": ": 厲害"
            },
            {
                "push": "推 ",
                "text": ": 我翹著二郎腿掙～～～懂？"
            },
            {
                "push": "→ ",
                "text": ": 有些人的語句用法已經透露出自己是五毛了"
            },
            {
                "push": "推 ",
                "text": ": !"
            },
            {
                "push": "推 ",
                "text": ": 早期台灣也不少這種的吧 只做外銷"
            },
            {
                "push": "噓 ",
                "text": ": hfptt罵人雜種小心被告"
            },
            {
                "push": "→ ",
                "text": ": 啊查了一下ip是中國人啊"
            },
            {
                "push": "噓 ",
                "text": ": 這篇會推的就真的是黨的網軍耶……這董事長明明有對岸客"
            },
            {
                "push": "→ ",
                "text": ": 戶，明顯是講幹話"
            },
            {
                "push": "推 ",
                "text": ": 黑名單一直加 我的八卦越來越乾淨 爽"
            },
            {
                "push": "推 ",
                "text": ": 推 好直接的說法 反觀某些商人裝睡.."
            },
            {
                "push": "推 ",
                "text": ": 反觀"
            },
            {
                "push": "推 ",
                "text": ": 說得好!!推!!"
            },
            {
                "push": "推 ",
                "text": ": 高調"
            },
            {
                "push": "推 ",
                "text": ": 在中國設廠不等於和中國人做生意 只是負責生產和組裝之類"
            },
            {
                "push": "噓 ",
                "text": ": 下一篇就被查到有在中國開分公司，自由這樣沒查證就報假"
            },
            {
                "push": "→ ",
                "text": ": 新聞會不會被罰錢啊！？"
            },
            {
                "push": "→ ",
                "text": ": 跟中國人買東西不算做生意賣東西才算嗎 ？民進黨支持者的"
            },
            {
                "push": "→ ",
                "text": ": 邏輯超好笑"
            },
            {
                "push": "推 ",
                "text": ": 有種有膽識！"
            },
            {
                "push": "→ ",
                "text": ": 請問樓上..可不可幫大家跟郭董說一說"
            },
            {
                "push": "→ ",
                "text": ": 回按噓的樓"
            },
            {
                "push": "推 ",
                "text": ": 柯韓粉崩潰"
            },
            {
                "push": "推 ",
                "text": ": 這才是正確的做法"
            },
            {
                "push": "→ ",
                "text": ": 跟郭董說什麼？ 郭董有給跟這個老闆一樣說他不跟中國人做"
            },
            {
                "push": "→ ",
                "text": ": 生意嗎？連台積電跟聯發科都在跟華為做生意了， 這兩家公"
            },
            {
                "push": "→ ",
                "text": ": 司的老闆是不是應該抓起來判刑？！"
            },
            {
                "push": "推 ",
                "text": ": 北七的選舉操盤團隊"
            },
            {
                "push": "推 ",
                "text": ": \"我最討厭吃飯喝酒\"   反觀最愛喝酒的韓導"
            },
            {
                "push": "→ ",
                "text": ": 查證一下啦 我以前跟他們做過生意 他們中國投資了不少"
            },
            {
                "push": "→ ",
                "text": ": 是吸獨仔會崩潰吧，好不容易找到一個可以展現台灣人氣魄"
            },
            {
                "push": "→ ",
                "text": ": 不跟中國往來的例子， 馬上就被下一篇打臉了！"
            },
            {
                "push": "推 ",
                "text": ": 聰明 這才是台灣商人"
            },
            {
                "push": "推 ",
                "text": ": 樓上說來說去 不敢直接向郭董說出你的真實想法"
            },
            {
                "push": "→ ",
                "text": ": 繼續舔"
            },
            {
                "push": "→ ",
                "text": ": 因為你說的有部份有打臉"
            },
            {
                "push": "推 ",
                "text": ": 不是不能投資大陸吧？ 是別短視近利被牽著鼻子走"
            },
            {
                "push": "→ ",
                "text": ": 他在那邊投資..就代表有上下游阿 新普本身持股很多...."
            },
            {
                "push": "推 ",
                "text": ": 推"
            },
            {
                "push": "推 ",
                "text": ": 霸氣側露"
            },
            {
                "push": "→ ",
                "text": ": 3星吃了大虧技術被迫外流就是個例子"
            },
            {
                "push": "→ ",
                "text": ": 那邊的生產基地可不小 以前還跟央企合資過...."
            },
            {
                "push": "推 ",
                "text": ": 讚"
            },
            {
                "push": "→ ",
                "text": ": 全世界都不缺舔共的，光美國就一堆了"
            },
            {
                "push": "推 ",
                "text": ": 帥氣啊"
            },
            {
                "push": "推 ",
                "text": ": 強"
            },
            {
                "push": "推 ",
                "text": ": 看店小二演的\"樹大招風\" 要作生意就是陪一堆官喝酒給錢"
            },
            {
                "push": "→ ",
                "text": ": 然後真的出了事情對方有背景 還不是直接給你壓下來"
            },
            {
                "push": "推 ",
                "text": ": 完全正確"
            },
            {
                "push": "推 ",
                "text": ": 這才是有遠見的老闆"
            },
            {
                "push": "推 ",
                "text": ": 推"
            },
            {
                "push": "推 ",
                "text": ": 語畢股價跳一根七趴"
            },
            {
                "push": "推 ",
                "text": ": 好屌"
            },
            {
                "push": "推 ",
                "text": ": Hf本來就不是台灣人"
            },
            {
                "push": "推 ",
                "text": ": 禿頭：我最愛吃飯喝酒還會到你家睡覺XDDDD"
            },
            {
                "push": "推 ",
                "text": ": 對啊"
            },
            {
                "push": "噓 ",
                "text": ": 我聯想筆電裡的電池就是新普的哀...怎麼一回事?"
            },
            {
                "push": "推 ",
                "text": ": 推推"
            },
            {
                "push": "→ ",
                "text": ": 有競爭力"
            },
            {
                "push": "→ ",
                "text": ": 這本來就不是統獨議題 這只是說明只想靠中國賺錢是多天真"
            },
            {
                "push": "→ ",
                "text": ": 的"
            },
            {
                "push": "推 ",
                "text": ": 推 廢物才靠吃喝玩樂做生意"
            },
            {
                "push": "噓 ",
                "text": ": 只是利用中國勞工而已 我懂"
            },
            {
                "push": "推 ",
                "text": ": 他在中國有廠喔，等等應該會被查水表"
            },
            {
                "push": "噓 ",
                "text": ": 你誰？ 我們韓總說要做中國生意！別跟韓總唱反調"
            },
            {
                "push": "噓 ",
                "text": ": 幹話老板 明明在重慶設廠養大陸人"
            },
            {
                "push": "推 ",
                "text": ": 聰明"
            },
            {
                "push": "→ ",
                "text": ": 不用想太多 這支高點到了  直接空下去就對了"
            },
            {
                "push": "推 ",
                "text": ": 推老闆有腦"
            },
            {
                "push": "推 ",
                "text": ": 這個可以寫進歷史課本了，告誡小孩靠山山倒"
            },
            {
                "push": "推 ",
                "text": ": 廠工高潮"
            },
            {
                "push": "推 ",
                "text": ": 宋董超誠實XD"
            },
            {
                "push": "推 ",
                "text": ": 讚一發"
            },
            {
                "push": "推 ",
                "text": ": 9.2:沒國際觀"
            },
            {
                "push": "推 ",
                "text": ": 反觀"
            },
            {
                "push": "推 ",
                "text": ": 猛"
            },
            {
                "push": "推 ",
                "text": ": 真 臺灣企業"
            },
            {
                "push": "→ ",
                "text": ": 原來設廠不算做生意"
            },
            {
                "push": "推 ",
                "text": ": 反觀"
            },
            {
                "push": "推 ",
                "text": ": 推"
            },
            {
                "push": "推 ",
                "text": ": 讚"
            },
            {
                "push": "推 ",
                "text": ": 推"
            },
            {
                "push": "推 ",
                "text": ": 反觀舔到快跟地板合為一體的"
            },
            {
                "push": "推 ",
                "text": ": 推"
            },
            {
                "push": "噓 ",
                "text": ": 認真 電池技術已經卡很久了 人家有自己的產業鍊"
            },
            {
                "push": "→ ",
                "text": ": 就只是比便宜而已"
            },
            {
                "push": "推 ",
                "text": ": 猛"
            },
            {
                "push": "噓 ",
                "text": ": 呵呵，等被翻出然後打臉！吉娃娃在出來護航！"
            },
            {
                "push": "→ ",
                "text": ": 有風骨的企業家"
            },
            {
                "push": "推 ",
                "text": ": 真實血淚經驗分享"
            },
            {
                "push": "→ ",
                "text": ": 鴻海的寶鑫是新普大股東董事"
            },
            {
                "push": "噓 ",
                "text": ": 這篇推文裡也太多五毛了吧！"
            },
            {
                "push": "推 ",
                "text": ": htc再舔啊 誰買帳 可悲"
            },
            {
                "push": "推 ",
                "text": ": 聰明，一堆北七還搶著去中國"
            },
            {
                "push": "推 ",
                "text": ":"
            },
            {
                "push": "噓 ",
                "text": ": eebear一定是五毛，竟然說台積跟發哥老闆抓起來判刑"
            },
            {
                "push": "推 ",
                "text": ": 你不做不代表所有人都不做好嗎......"
            },
            {
                "push": "→ ",
                "text": ": 讚"
            },
            {
                "push": "推 ",
                "text": ": 聰明耶"
            },
            {
                "push": "推 ",
                "text": ": 感動！終於有一家企業是這樣的 我盼了好久啊～害我一直幻"
            },
            {
                "push": "→ ",
                "text": ": 想如果是我開公司不賺中國錢不看中國臉"
            },
            {
                "push": "推 ",
                "text": ": 厲害"
            },
            {
                "push": "推 ",
                "text": ": 真有實力根本不用去舔中國 中國自己跪著找你"
            },
            {
                "push": "推 ",
                "text": ": 推 反觀低能kmt"
            },
            {
                "push": "推 ",
                "text": ": 帥"
            },
            {
                "push": "噓 ",
                "text": ": 去股版看看   設廠跟供應鏈都不是生意???"
            },
            {
                "push": "推 ",
                "text": ": 反觀蔡英文"
            },
            {
                "push": "噓 ",
                "text": ": 買報導等著被打臉"
            },
            {
                "push": "推 ",
                "text": ": 行，可以買"
            },
            {
                "push": "→ ",
                "text": ": 完了"
            },
            {
                "push": "推 ",
                "text": ": 所以韓導前幾天不就在吃喝玩樂嗎"
            },
            {
                "push": "推 ",
                "text": ": 腦袋超清楚"
            },
            {
                "push": "推 ",
                "text": ": 推 反觀八卦綠畜:為什麼不能賺中國錢?"
            },
            {
                "push": "推 ",
                "text": ": 幫你teg 王雪紅跟吳寶春"
            },
            {
                "push": "推 ",
                "text": ": 反觀又老又窮又賤 笑死人"
            },
            {
                "push": "推 ",
                "text": ": 鴻海是新普最大的股東耶 這麼說不怕郭董不高興呀"
            },
            {
                "push": "推 ",
                "text": ": 反觀某智慧手機品牌現況  笑死"
            },
            {
                "push": "推 ",
                "text": ": 帥"
            },
            {
                "push": "推 ",
                "text": ": 推"
            },
            {
                "push": "推 ",
                "text": ": 推"
            },
            {
                "push": "→ ",
                "text": ": 歐陽__？"
            },
            {
                "push": "→ ",
                "text": ": 霸氣!"
            },
            {
                "push": "推 ",
                "text": ": 反觀"
            },
            {
                "push": "推 ",
                "text": ": 反觀"
            },
            {
                "push": "推 ",
                "text": ": 推"
            },
            {
                "push": "推 ",
                "text": ": 發大財"
            },
            {
                "push": "推 ",
                "text": ": 反觀歐陽支那"
            },
            {
                "push": "噓 ",
                "text": ": 原來新普網站上說的上海江蘇重慶生產基地都是假的?"
            },
            {
                "push": "推 ",
                "text": ": 讚！"
            },
            {
                "push": "→ ",
                "text": ": 跟中國做生意一定要吃飯喝酒這倒是真的"
            },
            {
                "push": "推 ",
                "text": ": ！"
            },
            {
                "push": "推 ",
                "text": ": 85度c"
            },
            {
                "push": "推 ",
                "text": ": 中國放利給你就是要盜你套養殺"
            },
            {
                "push": "→ ",
                "text": ": 台灣也有不少老闆很愛吃飯喝酒這套"
            },
            {
                "push": "推 ",
                "text": ": 事實"
            },
            {
                "push": "推 ",
                "text": ": 看看其他垃圾公司 還有手機板買中國機的乞丐id 幹"
            },
            {
                "push": "推 ",
                "text": ": 舔共的沒好下場，呵呵中國雪紅活該"
            },
            {
                "push": "推 ",
                "text": ": 推"
            },
            {
                "push": "推 ",
                "text": ": 反觀一堆公司 技術被學光惹 沒市場後出來罵政府"
            },
            {
                "push": "推 ",
                "text": ": 推"
            },
            {
                "push": "推 ",
                "text": ": 這家的電池真的超猛"
            },
            {
                "push": "推 ",
                "text": ": 反觀"
            },
            {
                "push": "推 ",
                "text": ": 推"
            },
            {
                "push": "推 ",
                "text": ": 反觀"
            },
            {
                "push": "推 ",
                "text": ": 反觀垃圾舔共豬"
            },
            {
                "push": "推 ",
                "text": ": 推"
            },
            {
                "push": "推 ",
                "text": ": 中肯"
            },
            {
                "push": "→ ",
                "text": ": 新普的中國廠區要小心了......"
            },
            {
                "push": "推 ",
                "text": ": 新普真的不錯，賺很多，董事長是我爸以前的同事，他這發言"
            },
            {
                "push": "推 ",
                "text": ": 應跟長期待在外商有關，跟歐美日做生意的確安穩非常多"
            },
            {
                "push": "推 ",
                "text": ": 推"
            },
            {
                "push": "→ ",
                "text": ": 我看他99年2月 有在中國設廠呀"
            },
            {
                "push": "推 ",
                "text": ": 換句話說 在中國的廠都在賠錢"
            },
            {
                "push": "→ ",
                "text": ":  https://i.imgur.com/1dG9Fxn.jpg"
            },
            {
                "push": "噓 ",
                "text": ": 一堆人舔共舔到破產"
            },
            {
                "push": "推 ",
                "text": ": 鴻海股東表示:"
            },
            {
                "push": "推 ",
                "text": ": 推"
            },
            {
                "push": "推 ",
                "text": ": 9.2: 台獨，鎖國，反中，皇民....."
            },
            {
                "push": "推 ",
                "text": ": 生產跟賣出是兩回事吧…混為一談的都是智障嗎？"
            },
            {
                "push": "推 ",
                "text": ": 推"
            },
            {
                "push": "推 ",
                "text": ": 推"
            },
            {
                "push": "推 ",
                "text": ": 推"
            },
            {
                "push": "推 ",
                "text": ": 推"
            },
            {
                "push": "→ ",
                "text": ": =====「赤色高棉」台灣版====="
            },
            {
                "push": "→ ",
                "text": ": 「他們先殺了我父親，柬埔寨女孩的回憶」"
            },
            {
                "push": "→ ",
                "text": ": https://i.imgur.com/aQMV1X5.jpg"
            },
            {
                "push": "→ ",
                "text": ": 拜託有Netflix的人 去看看這部電影"
            },
            {
                "push": "→ ",
                "text": ": 希望台灣不要成為第二個「赤色高棉」"
            },
            {
                "push": "→ ",
                "text": ": https://i.imgur.com/kD2IP5Y.jpg"
            },
            {
                "push": "→ ",
                "text": ": 五毛出來玩"
            },
            {
                "push": "→ ",
                "text": ": 原來聯想不是中國品牌"
            },
            {
                "push": "推 ",
                "text": ":"
            },
            {
                "push": "推 ",
                "text": ": 普字輩的從來不會讓我失望"
            },
            {
                "push": "推 ",
                "text": ": 推"
            },
            {
                "push": "推 ",
                "text": ": 自由再幫高調一點 新普中國廠會感謝自由的"
            },
            {
                "push": "噓 ",
                "text": ": 重慶跟江蘇!?!?!?"
            },
            {
                "push": "推 ",
                "text": ": 買一張"
            },
            {
                "push": "推 ",
                "text": ": 舔到舌頭出血"
            },
            {
                "push": "噓 ",
                "text": ": 都去中設廠了？干話？"
            },
            {
                "push": "推 ",
                "text": ": 讚"
            },
            {
                "push": "推 ",
                "text": ": 推"
            },
            {
                "push": "推 ",
                "text": ": 聰明 有種"
            },
            {
                "push": "推 ",
                "text": ": 推"
            },
            {
                "push": "推 ",
                "text": ": 反觀舔中"
            },
            {
                "push": "→ ",
                "text": ": 推推推"
            },
            {
                "push": "推 ",
                "text": ": 紅姨表示......."
            },
            {
                "push": "→ ",
                "text": ": 原來新普沒有做聯想生意"
            },
            {
                "push": "推 ",
                "text": ": 反觀"
            },
            {
                "push": "推 ",
                "text": ": 人家有資格大聲,反觀"
            },
            {
                "push": "→ ",
                "text": ": 朝聖 呵呵"
            },
            {
                "push": "推 ",
                "text": ": 有腦有guts  反觀..."
            },
            {
                "push": "推 ",
                "text": ": 觀念正確"
            },
            {
                "push": "→ ",
                "text": ": 大陸先撤資在來嘴啦......"
            },
            {
                "push": "推 ",
                "text": ": 水啦"
            },
            {
                "push": "推 ",
                "text": ": 推"
            },
            {
                "push": "推 ",
                "text": ": 推，本董也是"
            },
            {
                "push": "→ ",
                "text": ": 聰明"
            },
            {
                "push": "推 ",
                "text": ": 哈哈 某人就多喝一點交隨時捅你的朋友"
            },
            {
                "push": "推 ",
                "text": ": 部分生產在中國，但市場在歐美日，有什麼問題？中國奸商"
            },
            {
                "push": "→ ",
                "text": ": 多，這大家都知道，上不正下歪邪，這就是中國"
            },
            {
                "push": "噓 ",
                "text": ": 呃...在中國設廠做出口外銷...利用中國的廉價成本賺錢.."
            },
            {
                "push": "→ ",
                "text": ": 我從不做中國（廠商）生意，但我和中國（政府）做生意"
            },
            {
                "push": "推 ",
                "text": ": 這才是政治正確，反觀韓…一堆跟中國一起的新聞"
            },
            {
                "push": "噓 ",
                "text": ": 這智力 常罵人低能啊 哈"
            },
            {
                "push": "推 ",
                "text": ": 反觀"
            },
            {
                "push": "推 ",
                "text": ": 就評估風險後的決定有能力才能這樣 而跟中國做生意的."
            },
            {
                "push": "→ ",
                "text": ": 清流"
            },
            {
                "push": "推 ",
                "text": ": 讚"
            },
            {
                "push": "推 ",
                "text": ": 9.2:中國是唯一出路"
            },
            {
                "push": "推 ",
                "text": ": 反觀一堆蒼蠅想吃屎的"
            },
            {
                "push": "→ ",
                "text": ": 新聞不見了?假新聞?"
            },
            {
                "push": "推 ",
                "text": ": 聰明人"
            },
            {
                "push": "推 ",
                "text": ": 難道有這麼清醒的商人！"
            },
            {
                "push": "噓 ",
                "text": ": 廠公推文還是跟風看標題推？"
            },
            {
                "push": "→ ",
                "text": ": 讚"
            },
            {
                "push": "噓 ",
                "text": ": 推文的覺青們是多無知才會被這種新聞騙？新普做的大"
            },
            {
                "push": "→ ",
                "text": ": 陸生意又多又早 還想在大陸上市勒"
            },
            {
                "push": "推 ",
                "text": ": 最好的宣傳，就是不做中國生意XD"
            },
            {
                "push": "推 ",
                "text": ": 推"
            },
            {
                "push": "→ ",
                "text": ": 新聞被下架了 還有人裝不知道喔XD"
            },
            {
                "push": "推 ",
                "text": ": 無腦9.2"
            }
        ]
    },
    {
        "title": "新普董事長︰我從不做中國生意",
        "date": "2019/03/28",
        "content": "1.媒體來源: 自由時報  2.完整新聞標題: 新普董事長︰我從不做中國生意  3.完整新聞內文:  中國付款條件就是吃喝玩樂  〔記者卓怡君／台北報導〕「我從不做中國生意！中國付款條件就是吃喝玩樂！」新普（ 6121）董事長宋福祥直言，他到現在一毛錢中國生意都沒有做，做中國生意賺不到錢、收 不到錢，中國廠商抄襲很凶，新普的公司策略就是百分之百外銷到歐、美、日這3大區域 ，這些客戶不會欠款，時間一到就付款。  昨日在新普法說會上，法人問到新普如何因應中國競爭者的威脅，宋福祥劈頭就說，新普 到現在一毛錢中國生意都沒有做！因為做中國生意，賺不到錢、收不到錢，中國市場付款 條件就是「吃喝玩樂」，宋福祥砲轟：「我不來這套，不跟你打屁，我最討厭吃飯喝酒。 」  只做歐美日 客戶絕不欠款 所以，新普只做歐、美、日外銷，宋福祥強調，中國是殺戮戰場，他跳開這個殺戮戰場， 只做歐、美、日外銷，把技術做好就好，歐洲客戶雖然很難打進去、很麻煩，不過，一旦 打進去，合約時間就很長，從台灣打進歐洲，要比中國打進歐洲更有利，台灣人的素質、 品質、技術都比較好。  新普位居全球NB鋰電池龍頭，因全球NB已經飽和，迅速轉到手機領域，成為蘋果全系列供 應商， 近年宋福祥有感於傳統資訊IT產品成長有限，大刀闊斧進行轉型大計，朝電動車 、伺服器電池等領域發展。  4.完整新聞連結 (或短網址): https://tinyurl.com/yyvp6dfm  5.備註:  ",
        "comment": [
            {
                "push": "→ ",
                "text": ": 9.2崩潰"
            },
            {
                "push": "推 ",
                "text": ": 好 買一張"
            },
            {
                "push": "→ ",
                "text": ": 還有好蘋果爸爸"
            },
            {
                "push": "→ ",
                "text": ": 轉不到錢，打不進市場...講的很偉大的樣子"
            },
            {
                "push": "推 ",
                "text": ": ...坦白講 法國付款很喜歡拖"
            },
            {
                "push": "推 ",
                "text": ": 帥，推這位董事長。中國人uccu"
            },
            {
                "push": "→ ",
                "text": ": 廣告文?"
            },
            {
                "push": "推 ",
                "text": ": 中國市場付款條件就是「吃喝玩樂」欠款是日常"
            },
            {
                "push": "推 ",
                "text": ": 支那賤畜崩潰"
            },
            {
                "push": "推 ",
                "text": ": 推 中國人東西都加料 還容易不守信用"
            },
            {
                "push": "推 ",
                "text": ": 慘了  喜韓兒要抵制了"
            },
            {
                "push": "→ ",
                "text": ": 9.2崩潰"
            },
            {
                "push": "噓 ",
                "text": ": 下次要進去 就會被韓迷檢舉台獨 要你低頭"
            },
            {
                "push": "→ ",
                "text": ": 沒技術的低端廢物才要靠支那"
            },
            {
                "push": "推 ",
                "text": ": 你唬爛"
            },
            {
                "push": "→ ",
                "text": ": ....這個嘛"
            },
            {
                "push": "推 ",
                "text": ": 推，雖然這種高端技術是少數"
            },
            {
                "push": "→ ",
                "text": ": 新普這麼大一家原來完全沒進中國市場？這真的有點強耶.."
            },
            {
                "push": "推 ",
                "text": ": 新普真的不錯，跨電動車的力度要大一點"
            },
            {
                "push": "→ ",
                "text": ": https://i.imgur.com/gjejeXb.jpg 技術賣出去屁民來"
            },
            {
                "push": "推 ",
                "text": ": 新普唬爛的話，那叫支那人快買下他啊，6121都給你看"
            },
            {
                "push": "→ ",
                "text": ": 種菜"
            },
            {
                "push": "推 ",
                "text": ": 新普給推 我家附近"
            },
            {
                "push": "推 ",
                "text": ": 歐美就算了 日本也要吃喝玩樂吧"
            },
            {
                "push": "→ ",
                "text": ": 酒水文化……"
            },
            {
                "push": "推 ",
                "text": ": 不過...敢這樣說其實會被股東抗議"
            },
            {
                "push": "→ ",
                "text": ": 中國心眼很小的.."
            },
            {
                "push": "推 ",
                "text": ": 柯粉：台獨吉娃娃"
            },
            {
                "push": "→ ",
                "text": ": 商人的話………呵呵呵呵"
            },
            {
                "push": "推 ",
                "text": ": 這種等級老闆講的話 聽聽就好 跟直銷一樣"
            },
            {
                "push": "→ ",
                "text": ": 反正他不要賺什麼違法的錢 我們也管不著吧 只要公司"
            },
            {
                "push": "→ ",
                "text": ": 有賺錢 他對得起股東就好"
            },
            {
                "push": "推 ",
                "text": ": 這家一張很貴= ="
            },
            {
                "push": "→ ",
                "text": ": 憑你堂堂董事長 還要陪人吃喝玩樂？！"
            },
            {
                "push": "推 ",
                "text": ": 中國的電池產業也是補貼的很凶"
            },
            {
                "push": "→ ",
                "text": ": EPS也不差,如果本來就不吃中國市場那能賺這麼多股東也"
            },
            {
                "push": "推 ",
                "text": ": 韓粉進攻嚕"
            },
            {
                "push": "→ ",
                "text": ": 不會有意見,除非大股東舔中"
            },
            {
                "push": "推 ",
                "text": ": 去中國市場公司董事長被抓去應酬交際很常發生..."
            },
            {
                "push": "推 ",
                "text": ": 東亞好像都普遍有這種行為 多少A一點才給你生意做"
            },
            {
                "push": "→ ",
                "text": ": 不過他下游客戶做很多中國生意 所以他進不進去也沒差吧"
            },
            {
                "push": "推 ",
                "text": ": 韓粉抵制鋰電池"
            },
            {
                "push": "推 ",
                "text": ": 中肯"
            },
            {
                "push": "推 ",
                "text": ": 屌"
            },
            {
                "push": "→ ",
                "text": ": 沒有性招待  就沒有訂單  這是中國商業的規則"
            },
            {
                "push": "推 ",
                "text": ": 好 買一張"
            },
            {
                "push": "推 ",
                "text": ": 蠻中肯的阿"
            },
            {
                "push": "推 ",
                "text": ": 猛，推這種文化，專注於技術"
            },
            {
                "push": "推 ",
                "text": ": 今天飛高高"
            },
            {
                "push": "→ ",
                "text": ": 對岸很在意來應酬的職務夠不夠大"
            },
            {
                "push": "→ ",
                "text": ": 好，買了"
            },
            {
                "push": "→ ",
                "text": ": All in"
            },
            {
                "push": "→ ",
                "text": ": 葡萄好酸"
            },
            {
                "push": "推 ",
                "text": ": 狂"
            },
            {
                "push": "推 ",
                "text": ": 柯韓粉要把手上iphone丟掉了"
            },
            {
                "push": "推 ",
                "text": ": 飯局很正常 但說到玩樂...董事長還陪人上酒店啊？"
            },
            {
                "push": "推 ",
                "text": ": 讚 有guts"
            },
            {
                "push": "→ ",
                "text": ": 這家是真的很屌，我記得有連續N年EPS破10"
            },
            {
                "push": "→ ",
                "text": ": 討厭吃飯喝酒 這董事長不錯"
            },
            {
                "push": "→ ",
                "text": ": 公司有條件 所以站著掙錢"
            },
            {
                "push": "→ ",
                "text": ": 這種等級==你知道人家事業多大嗎...井底之蛙"
            },
            {
                "push": "→ ",
                "text": ": 不懂不要亂留言"
            },
            {
                "push": "推 ",
                "text": ": 推"
            },
            {
                "push": "推 ",
                "text": ": 推，有骨氣的老闆。"
            },
            {
                "push": "推 ",
                "text": ": 這支股價根本裝火箭 一直衝"
            },
            {
                "push": "推 ",
                "text": ": 很厲害!"
            },
            {
                "push": "推 ",
                "text": ": 推，中肯到不行"
            },
            {
                "push": "→ ",
                "text": ": 人家不賺中國錢，但月營收40億，eps破10，股價兩百多。"
            },
            {
                "push": "→ ",
                "text": ": 結果四樓五毛不認識這間公司，以為台灣只有台積電。"
            },
            {
                "push": "推 ",
                "text": ": 股東：中國14億 做到發抖"
            },
            {
                "push": "推 ",
                "text": ": 推"
            },
            {
                "push": "推 ",
                "text": ": 讚，有骨氣"
            },
            {
                "push": "推 ",
                "text": ": 推個"
            },
            {
                "push": "推 ",
                "text": ": 推"
            },
            {
                "push": "推 ",
                "text": ": 沒技術去舔中國剛剛好而已"
            },
            {
                "push": "推 ",
                "text": ": 一堆公司都不靠中國吃飯 靠外銷到中東地區的一堆"
            },
            {
                "push": "推 ",
                "text": ": 支持 買一張"
            },
            {
                "push": "推 ",
                "text": ": 賺不到錢?四樓會看財報嗎?"
            },
            {
                "push": "推 ",
                "text": ": 台灣的價值從來不需要依靠中國，結果居然有人靠下"
            },
            {
                "push": "→ ",
                "text": ": 跪舔中國懶趴當政治訴求，還有一票信徒，果然台人"
            },
            {
                "push": "→ ",
                "text": ": 因為他們銷到中國都有不好的經驗 噗"
            },
            {
                "push": "→ ",
                "text": ": 趕快被統一統被當狗關起來養ㄅ"
            },
            {
                "push": "推 ",
                "text": ": 好 我買一張"
            },
            {
                "push": "→ ",
                "text": ": 最主要的就是欠款 <- 超常見，在台灣你發芭樂票看看"
            },
            {
                "push": "→ ",
                "text": ": 大陸的貨款可以一拖拖到半年 拖著你一起死"
            },
            {
                "push": "推 ",
                "text": ": 主要客戶包括HP、Dell、Apple、聯想…。聯想不是中國的？"
            },
            {
                "push": "→ ",
                "text": ": 資料來源：MoneyDJ理財網。"
            },
            {
                "push": "→ ",
                "text": ": 完全正確 你以為簽合約就沒事了嗎 簽了合約也收不到錢啦"
            },
            {
                "push": "推 ",
                "text": ": 屌"
            },
            {
                "push": "推 ",
                "text": ": 欠款真的ㄐㄅ"
            },
            {
                "push": "推 ",
                "text": ": 有骨氣給推！"
            },
            {
                "push": "推 ",
                "text": ": 佛心公司"
            },
            {
                "push": "推 ",
                "text": ": 反觀某位市長"
            },
            {
                "push": "推 ",
                "text": ": 推"
            },
            {
                "push": "推 ",
                "text": ": 你不懂發大財？"
            },
            {
                "push": "推 ",
                "text": ": 酷"
            },
            {
                "push": "→ ",
                "text": ": 中國真的很愛欠 旅遊業應該很清楚 車資都過很久才付"
            },
            {
                "push": "推 ",
                "text": ": 台灣經濟起飛時期完全不靠中國的"
            },
            {
                "push": "推 ",
                "text": ": 一堆韓粉帶風向"
            },
            {
                "push": "推 ",
                "text": ": 推"
            },
            {
                "push": "推 ",
                "text": ": 石斑魚的概念"
            },
            {
                "push": "推 ",
                "text": ": 推"
            },
            {
                "push": "→ ",
                "text": ": 中小企業特別需要周轉金的 被拖個半年就直接死一連片"
            },
            {
                "push": "推 ",
                "text": ": #國際觀"
            },
            {
                "push": "推 ",
                "text": ": 推"
            },
            {
                "push": "推 ",
                "text": ": 好 買十張"
            },
            {
                "push": "推 ",
                "text": ": 聰明"
            },
            {
                "push": "→ ",
                "text": ": 靠中國真正能賺錢的是在於你之前打通的關節有多深"
            },
            {
                "push": "→ ",
                "text": ": 中國就搞那套上下疏通交際應酬培養感情囉"
            },
            {
                "push": "→ ",
                "text": ": 跟之前台商過去被大陸招待的情況根本反過來了"
            },
            {
                "push": "推 ",
                "text": ": 推 有實力大聲就是爽"
            },
            {
                "push": "推 ",
                "text": ": 反觀郭董"
            },
            {
                "push": "推 ",
                "text": ": 董ㄟ帶大家賺世界財"
            },
            {
                "push": "推 ",
                "text": ": 買起來 買起來"
            },
            {
                "push": "→ ",
                "text": ": 反觀某廢物超貸銀行的舔共仔"
            },
            {
                "push": "推 ",
                "text": ": 不要說當業務做生意，我朋友碼農過去出差都會被招待"
            },
            {
                "push": "→ ",
                "text": ": 小姐了"
            },
            {
                "push": "推 ",
                "text": ": 意圖使人買一張"
            },
            {
                "push": "推 ",
                "text": ": 確實我最會喝跟打麻將的朋友都去中國當業務了 XD"
            },
            {
                "push": "推 ",
                "text": ": #不顧北京反對"
            },
            {
                "push": "推 ",
                "text": ": 支那賤畜又要抵制了，咦，本來就沒往來怎麼抵制"
            },
            {
                "push": "推 ",
                "text": ": 結果今天噴出"
            },
            {
                "push": "推 ",
                "text": ": 帥"
            },
            {
                "push": "推 ",
                "text": ": 股票代號幾號？我買了"
            },
            {
                "push": "推 ",
                "text": ": 買一張"
            },
            {
                "push": "推 ",
                "text": ": 這個董事長屌爆了"
            },
            {
                "push": "推 ",
                "text": ": 聰明 知道遠離災禍"
            },
            {
                "push": "推 ",
                "text": ": 推"
            },
            {
                "push": "推 ",
                "text": ": 歐美人都守信用？霤曼兄弟"
            },
            {
                "push": "推 ",
                "text": ": 他看清中國市場啊!意思表面上給的之外，私底下要再給一份"
            },
            {
                "push": "推 ",
                "text": ": 說的是實話 歐美對於企業信用很看重 加上是需求端也不用"
            },
            {
                "push": "推 ",
                "text": ": 中國人不可信 看看那些接中國團的旅行社吧  被搞到倒掉的"
            },
            {
                "push": "→ ",
                "text": ": 經過中間層層剝削 利潤大"
            },
            {
                "push": "→ ",
                "text": ": 有多少？"
            },
            {
                "push": "推 ",
                "text": ": 反觀"
            },
            {
                "push": "推 ",
                "text": ": 反觀"
            },
            {
                "push": "推 ",
                "text": ": 聰明，全世界都知道支那就是騙子國"
            },
            {
                "push": "→ ",
                "text": ": 這家下游明明就不少中國廠商XDDD"
            },
            {
                "push": "推 ",
                "text": ": 反觀"
            },
            {
                "push": "推 ",
                "text": ": 舔共就只能賺EZ money 蠢蛆講打不進市場根本搞笑"
            },
            {
                "push": "推 ",
                "text": ": 支共會找性病小模女明星申裝你"
            },
            {
                "push": "推 ",
                "text": ": 這麼簡單的道理怎一堆人沒想到，跳出中國可以擁抱全世"
            },
            {
                "push": "→ ",
                "text": ": 界"
            },
            {
                "push": "推 ",
                "text": ": 之前的公司曾經被中國客戶拖帳超過一年"
            },
            {
                "push": "推 ",
                "text": ": 酷"
            },
            {
                "push": "推 ",
                "text": ": 推"
            },
            {
                "push": "推 ",
                "text": ": 推"
            },
            {
                "push": "推 ",
                "text": ": 每個出來講這種話的人，過兩年都不一樣了"
            },
            {
                "push": "推 ",
                "text": ": 推推～"
            },
            {
                "push": "推 ",
                "text": ": 推"
            },
            {
                "push": "→ ",
                "text": ": 以前在博奕公司作中國生意真他媽的煩死人，幹"
            },
            {
                "push": "推 ",
                "text": ": 聰明人"
            },
            {
                "push": "推 ",
                "text": ": 沒競爭力才會一直想做中國生意"
            },
            {
                "push": "推 ",
                "text": ": 中國付款真的很愛拖 從中國回來的台商也都學壞了..."
            },
            {
                "push": "推 ",
                "text": ": 世界的工廠還是中國 台灣是代工廠 歐美那是賣商品的"
            },
            {
                "push": "推 ",
                "text": ": 韓粉别睡了~集合點名要夜襲了"
            },
            {
                "push": "推 ",
                "text": ": 這間真的很威啊 不懂不要亂酸..."
            },
            {
                "push": "推 ",
                "text": ": 漲停了！好猛，拒絕中國生意，賺飽飽，爽。"
            },
            {
                "push": "推 ",
                "text": ": 9.2崩潰"
            },
            {
                "push": "推 ",
                "text": ": 推"
            },
            {
                "push": "推 ",
                "text": ": 這種等級…你認識幾家說來聽聽"
            },
            {
                "push": "推 ",
                "text": ": 一定是個案啦！支國哪會這樣"
            },
            {
                "push": "推 ",
                "text": ": 電池要被抵制了"
            },
            {
                "push": "推 ",
                "text": ":"
            },
            {
                "push": "→ ",
                "text": ": 台商有好過？"
            },
            {
                "push": "推 ",
                "text": ": 不來這套，有點霸氣"
            },
            {
                "push": "推 ",
                "text": ": 推"
            },
            {
                "push": "推 ",
                "text": ": 可是韓導喜歡吃飯喝酒"
            },
            {
                "push": "推 ",
                "text": ": 推"
            },
            {
                "push": "推 ",
                "text": ": 推!"
            },
            {
                "push": "→ ",
                "text": ": 好帥  敬佩他"
            },
            {
                "push": "推 ",
                "text": ": 這才是真正的聰明人"
            },
            {
                "push": "推 ",
                "text": ": 飯酒應酬其實沒必要 即便應酬愉快 誰知道最後的決定會"
            },
            {
                "push": "→ ",
                "text": ": 是怎樣"
            },
            {
                "push": "推 ",
                "text": ": 推"
            },
            {
                "push": "推 ",
                "text": ": kmter崩潰"
            },
            {
                "push": "→ ",
                "text": ": 推"
            },
            {
                "push": "→ ",
                "text": ": 這要不要查證一下啊XDDD 明明就不少子公司在中國"
            },
            {
                "push": "→ ",
                "text": ": 他們以為每個人都像黄士福一樣XDDD"
            },
            {
                "push": "噓 ",
                "text": ": 所以這麼多國內外廠商去中國大陸都是笨？"
            },
            {
                "push": "推 ",
                "text": ": 真有遠見！"
            },
            {
                "push": "→ ",
                "text": ": 話不要說太滿"
            },
            {
                "push": "推 ",
                "text": ": 怒買 新普 股票"
            },
            {
                "push": "推 ",
                "text": ": 買一張"
            },
            {
                "push": "→ ",
                "text": ": 好哦"
            },
            {
                "push": "推 ",
                "text": ": 繼續舔"
            },
            {
                "push": "推 ",
                "text": ": 喝 為什麼認識的裡面出來的 都狂抱中國大腿 還說跟"
            },
            {
                "push": "→ ",
                "text": ": 中國統一都比較好勒 明明一堆供應商在中國"
            },
            {
                "push": "→ ",
                "text": ": 雖然說公司政策跟個人傾向不能並論"
            },
            {
                "push": "→ ",
                "text": ": 但我覺得表面話聽聽就好"
            },
            {
                "push": "推 ",
                "text": ": 被打臉了還在推 哈哈"
            },
            {
                "push": "推 ",
                "text": ": 太強了 原來他們沒進中國？"
            },
            {
                "push": "推 ",
                "text": ": 推 反觀"
            },
            {
                "push": "推 ",
                "text": ": 之前我們公司就亂接了一堆中國案子，結果收不到錢賠一"
            },
            {
                "push": "→ ",
                "text": ": 屁股"
            },
            {
                "push": "推 ",
                "text": ": 不做大陸生意，可以大陸設廠開子公司...不過這間確實很強"
            },
            {
                "push": "→ ",
                "text": ": 收不到錢是真的 驗收脫了五六年都還在拖"
            },
            {
                "push": "推 ",
                "text": ": 市佔率第一"
            },
            {
                "push": "推 ",
                "text": ": 趕快買新普"
            },
            {
                "push": "→ ",
                "text": ": 難怪蘋果電池那麼爛"
            },
            {
                "push": "推 ",
                "text": ": 不夠國際化嘻嘻"
            },
            {
                "push": "推 ",
                "text": ": 其實東歐也差不多  跟中國一樣很會倒債"
            },
            {
                "push": "推 ",
                "text": ": 這家股票可以買"
            },
            {
                "push": "推 ",
                "text": ": ！"
            },
            {
                "push": "推 ",
                "text": ": 新普中國有廠，也有接聯想的pack 搞得好像完全跟中國沒關"
            },
            {
                "push": "→ ",
                "text": ": 係？！ 免費賺到一則新聞真好"
            },
            {
                "push": "推 ",
                "text": ": 9.2五毛韓粉崩潰 決定開始搜集黑歷史"
            },
            {
                "push": "推 ",
                "text": ": 了不起"
            },
            {
                "push": "噓 ",
                "text": ": 明明就有跟大陸做生意  還在騙"
            },
            {
                "push": "推 ",
                "text": ": 不靠中國靠實力，真的厲害"
            },
            {
                "push": "推 ",
                "text": ": 完了 中國網民又要在微勃高喊抵制了"
            },
            {
                "push": "推 ",
                "text": ": 你這樣柯韓會生氣喔"
            },
            {
                "push": "→ ",
                "text": ": 棒"
            },
            {
                "push": "推 ",
                "text": ": 推，本來就不一定要賺人民幣"
            },
            {
                "push": "推 ",
                "text": ": 買一張"
            },
            {
                "push": "推 ",
                "text": ": 唉"
            },
            {
                "push": "推 ",
                "text": ": 郭董?"
            },
            {
                "push": "推 ",
                "text": ": 推 值得佩服"
            },
            {
                "push": "推 ",
                "text": ": 推"
            },
            {
                "push": "推 ",
                "text": ": 覺得強"
            },
            {
                "push": "推 ",
                "text": ": 酷"
            },
            {
                "push": "推 ",
                "text": ": 怒買一張"
            },
            {
                "push": "噓 ",
                "text": ": 可憐垃圾韓狗還在嘴 人生是多可憐"
            },
            {
                "push": "推 ",
                "text": ": 推"
            },
            {
                "push": "推 ",
                "text": ": 帥"
            },
            {
                "push": "→ ",
                "text": ": 鴻海的寶鑫是新普的大股東董事"
            },
            {
                "push": "推 ",
                "text": ": 屌"
            },
            {
                "push": "推 ",
                "text": ": 推"
            },
            {
                "push": "推 ",
                "text": ": 推 優質"
            },
            {
                "push": "推 ",
                "text": ": 新普讚"
            },
            {
                "push": "推 ",
                "text": ": 帥"
            },
            {
                "push": "推 ",
                "text": ": 奏效了"
            },
            {
                "push": "推 ",
                "text": ": 買一張了"
            },
            {
                "push": "推 ",
                "text": ": 小心被搞啊"
            },
            {
                "push": "推 ",
                "text": ": 日本也要吃喝玩樂 不過至少他們有守信"
            },
            {
                "push": "推 ",
                "text": ": 推"
            },
            {
                "push": "推 ",
                "text": ": 跟中國做生意還會被抄技術"
            },
            {
                "push": "推 ",
                "text": ": 買了！"
            },
            {
                "push": "推 ",
                "text": ": 猛  有眼界 頭腦清楚"
            },
            {
                "push": "推 ",
                "text": ": 有中資的股可以賣一賣了 隨時倒很可怕"
            },
            {
                "push": "→ ",
                "text": ": 好！"
            },
            {
                "push": "推 ",
                "text": ": 哇噻帥氣給推!!!!!!"
            },
            {
                "push": "推 ",
                "text": ": 真的有骨氣....不被眼前的數字所迷惑"
            },
            {
                "push": "噓 ",
                "text": ": 完了，要被道歉了"
            },
            {
                "push": "推 ",
                "text": ": 大推 聰明的老闆"
            },
            {
                "push": "噓 ",
                "text": ": 原來新普網站上說的上海江蘇重慶生產基地都是假的?"
            },
            {
                "push": "推 ",
                "text": ": Mou..."
            },
            {
                "push": "推 ",
                "text": ": 推"
            },
            {
                "push": "推 ",
                "text": ": 推"
            },
            {
                "push": "推 ",
                "text": ": 推，親戚也有類似案例，差點血本無歸=="
            },
            {
                "push": "推 ",
                "text": ": 西進中國的要嘛死在中國要嘛氣到賠本殺出"
            },
            {
                "push": "推 ",
                "text": ": 聰明有骨氣"
            },
            {
                "push": "噓 ",
                "text": ": 哥巴契夫頭髮最長海珊總統最不愛打仗六師傅玩遊戲喜歡慢"
            },
            {
                "push": "→ ",
                "text": ": 慢玩"
            },
            {
                "push": "推 ",
                "text": ": 推"
            },
            {
                "push": "噓 ",
                "text": ": 回答那麼爛==還有人挺 這就嘴砲回答 避重就輕"
            },
            {
                "push": "→ ",
                "text": ": 屌報"
            },
            {
                "push": "推 ",
                "text": ": 推，去敵國工作就得卑躬屈膝。何必，看看江西娜"
            },
            {
                "push": "推 ",
                "text": ": 現在去那邊的只有稍微舔跟舔全身的差別，稍微舔的例"
            },
            {
                "push": "→ ",
                "text": ": 如：周杰倫，舔全身的就歐陽這種破麻"
            },
            {
                "push": "→ ",
                "text": ": 推"
            },
            {
                "push": "→ ",
                "text": ": 怒買十張股票"
            },
            {
                "push": "推 ",
                "text": ": 就炒個新聞嘛 幹嘛這麼認真呢"
            },
            {
                "push": "推 ",
                "text": ": 從來都是靠中國的喊最大聲  這個難得講話"
            },
            {
                "push": "→ ",
                "text": ": 真的是靠中國的喊的比誰都大聲......"
            },
            {
                "push": "推 ",
                "text": ": 有能力才敢這樣說. 其他台商...就..."
            },
            {
                "push": "→ ",
                "text": ": 韓粉進攻！"
            },
            {
                "push": "推 ",
                "text": ": 買一張"
            },
            {
                "push": "推 ",
                "text": ": 反觀舔共仔"
            },
            {
                "push": "推 ",
                "text": ": 老實說 若是真的還蠻屌的"
            },
            {
                "push": "推 ",
                "text": ": 新普中國廠表示：老闆您不要我們了嗎？"
            },
            {
                "push": "→ ",
                "text": ": 鴻海:那我的錢怎麼來的？"
            },
            {
                "push": "推 ",
                "text": ": 讚叫小賀大家多支持他們家股票"
            },
            {
                "push": "推 ",
                "text": ": 讚，開始注意這間公司"
            },
            {
                "push": "推 ",
                "text": ": 5毛翻牆準備中"
            },
            {
                "push": "推 ",
                "text": ": 圈套就放在那，9、2就愛踩"
            },
            {
                "push": "→ ",
                "text": ": =====「赤色高棉」台灣版====="
            },
            {
                "push": "→ ",
                "text": ": 「他們先殺了我父親，柬埔寨女孩的回憶」"
            },
            {
                "push": "→ ",
                "text": ": https://i.imgur.com/aQMV1X5.jpg"
            },
            {
                "push": "→ ",
                "text": ": 拜託有Netflix的人 去看看這部電影"
            },
            {
                "push": "→ ",
                "text": ": 希望台灣不要成為第二個「赤色高棉」"
            },
            {
                "push": "→ ",
                "text": ": https://i.imgur.com/kD2IP5Y.jpg"
            },
            {
                "push": "→ ",
                "text": ": 五毛有拿到黨給你的薪水嗎？"
            },
            {
                "push": "噓 ",
                "text": ": 現在批踢踢使用者連查證都懶得做嗎?公開資訊觀測站一望即知"
            },
            {
                "push": "推 ",
                "text": ": 讚啦!"
            },
            {
                "push": "噓 ",
                "text": ": 幹，在中國設一堆廠，不做中國生意xDD"
            },
            {
                "push": "噓 ",
                "text": ": 覺青們會不會google啊?新普 中國廠 拜託看一下好嗎XD"
            },
            {
                "push": "→ ",
                "text": ": 難道用他們的水電土地人力不算是另一種型式的做生意??"
            },
            {
                "push": "→ ",
                "text": ": 當然不算!只要DPP定義不算 就不算"
            },
            {
                "push": "→ ",
                "text": ": 它說的是客戶只有歐美 不是說沒在中國設廠 前幾樓看得懂?"
            },
            {
                "push": "→ ",
                "text": ": 聯想也是他客戶欸"
            },
            {
                "push": "→ ",
                "text": ": 難道聯想不是中國公司？"
            },
            {
                "push": "→ ",
                "text": ": 還是愛台灣就不算跟中國做生意？"
            },
            {
                "push": "推 ",
                "text": ": ！"
            },
            {
                "push": "推 ",
                "text": ": 宋董撿到槍喔 在大陸一堆工廠 又說自己不做大陸生意"
            },
            {
                "push": "推 ",
                "text": ": 推"
            },
            {
                "push": "推 ",
                "text": ": 推"
            },
            {
                "push": "推 ",
                "text": ": 下一讚新普讚"
            },
            {
                "push": "→ ",
                "text": ": 這是哪家？"
            },
            {
                "push": "推 ",
                "text": ": 反觀"
            },
            {
                "push": "推 ",
                "text": ": 推"
            },
            {
                "push": "→ ",
                "text": ": 原來新普沒有做聯想生意"
            },
            {
                "push": "→ ",
                "text": ": 這篇告訴我們的是，覺青吸獨仔真的有一堆無腦智障"
            },
            {
                "push": "推 ",
                "text": ": 有懶蛋有頭腦…推一個"
            },
            {
                "push": "推 ",
                "text": ": 推"
            },
            {
                "push": "推 ",
                "text": ": 推"
            },
            {
                "push": "推 ",
                "text": ": 推"
            },
            {
                "push": "噓 ",
                "text": ": 朝聖 呵呵"
            },
            {
                "push": "噓 ",
                "text": ": 自己不做  下面的做"
            },
            {
                "push": "噓 ",
                "text": ": 我從不做中國（廠商）生意，但我和中國（政府）做生意"
            },
            {
                "push": "→ ",
                "text": ": 這篇告訴我們真的很多吸獨仔超白痴的，google就查到的謊"
            },
            {
                "push": "→ ",
                "text": ": 話退得好高興！真好騙！"
            },
            {
                "push": "噓 ",
                "text": ": 一篇謊言綠畜就高潮啊 智商太高了"
            },
            {
                "push": "推 ",
                "text": ": 早說嘛 其他公司真的只會吃飯喝酒"
            },
            {
                "push": "推 ",
                "text": ": 高調"
            },
            {
                "push": "推 ",
                "text": ": 推"
            },
            {
                "push": "推 ",
                "text": ": 推"
            },
            {
                "push": "推 ",
                "text": ": 讚啦"
            },
            {
                "push": "推 ",
                "text": ": 新聞下架.公司否認.讚歐"
            },
            {
                "push": "→ ",
                "text": ": 我不做啊 下面屬下做"
            },
            {
                "push": "噓 ",
                "text": ": 騙鬼！林北就在你手下當過血汗工程師，你最好完全沒"
            },
            {
                "push": "→ ",
                "text": ": 有產品賣給大陸！"
            },
            {
                "push": "→ ",
                "text": ": 還很喜歡去員工餐廳裝親民 叫廚房特別準備健康餐給你"
            },
            {
                "push": "→ ",
                "text": ": 吃 根本沒人敢跟你同桌吃好嗎？"
            },
            {
                "push": "噓 ",
                "text": ": 打臉來朝聖"
            },
            {
                "push": "噓 ",
                "text": ": 隨便說說，吉娃娃就高潮了。"
            },
            {
                "push": "→ ",
                "text": ": 樓上上上有卦快報"
            },
            {
                "push": "→ ",
                "text": ": 滯台支那賤畜狗黨個個都是綏靖主義孬種"
            },
            {
                "push": "推 ",
                "text": ": 怎麼可能，最北七的永遠都是禿頭教民"
            }
        ]
    }
]